Workbook

Sheet JAN
A1: HISTORICO | B1: DATA COMPETENCIA | C1: CONTA CONTABIL | D1: BROKER | E1: VALOR | F1: FORNECEDOR | G1: DATA LANCAMENTO | H1: CLIENTE | I1: ( | J1: DESPESA DE REPRESENTAÇÃO - | K1: CODIGO | L1: CONVIDADO | M1: CARGO DO CONVIDADO | N1: RAZÃO SOCIAL
A2: =CONCATENATE($J$1,J2,$I$3,M2,$I$3,L2,$I$1,K2,$I$2) -> DESPESA DE REPRESENTAÇÃO - 1/4 PARCELA DO BOX DO RIO OPEN 2026--FILHO DO ERMINIO (AGENDA 38499) | B2: 46023 | C2: 817991 | D2: ERMINIO OLIVI LUCCI | E2: -868 | F2: EVENTO | G2: 45966 | H2: 1170 | I2: ) | J2: 1/4 PARCELA DO BOX DO RIO OPEN 2026 | K2: AGENDA 38499 | L2: FILHO DO ERMINIO | N2: =VLOOKUP(H2,Clientes!B:D,3,) -> BGC LIQUIDEZ DTVM LTDA | P2: =_xlfn.XLOOKUP(K2,#REF!,#REF!,0,0,1) -> #REF!
A3: =CONCATENATE($J$1,J3,$I$3,M3,$I$3,L3,$I$1,K3,$I$2) -> DESPESA DE REPRESENTAÇÃO - 1/4 PARCELA DO BOX DO RIO OPEN 2026--AMIGO DO FILHO DO ERMINIO (AGENDA 38499) | B3: 46023 | C3: 817991 | D3: ERMINIO OLIVI LUCCI | E3: -868 | F3: EVENTO | G3: 45966 | H3: 1170 | I3: - | J3: 1/4 PARCELA DO BOX DO RIO OPEN 2026 | K3: AGENDA 38499 | L3: AMIGO DO FILHO DO ERMINIO | N3: =VLOOKUP(H3,Clientes!B:D,3,) -> BGC LIQUIDEZ DTVM LTDA | P3: =_xlfn.XLOOKUP(K3,#REF!,#REF!,0,0,1) -> #REF!
A4: =CONCATENATE($J$1,J4,$I$3,M4,$I$3,L4,$I$1,K4,$I$2) -> DESPESA DE REPRESENTAÇÃO - 1/4 PARCELA DO BOX DO RIO OPEN 2026-TRADER-PATRICK GRANDMASSON CROCKETT C (AGENDA 38499) | B4: 46023 | C4: 817991 | D4: RICARDO FERREIRA DA COSTA | E4: -868 | F4: EVENTO | G4: 45966 | H4: 14498 | J4: 1/4 PARCELA DO BOX DO RIO OPEN 2026 | K4: AGENDA 38499 | L4: PATRICK GRANDMASSON CROCKETT C | M4: TRADER | N4: =VLOOKUP(H4,Clientes!B:D,3,) -> BANCO BOCOM BBM S/A | P4: =_xlfn.XLOOKUP(K4,#REF!,#REF!,0,0,1) -> #REF!
A5: =CONCATENATE($J$1,J5,$I$3,M5,$I$3,L5,$I$1,K5,$I$2) -> DESPESA DE REPRESENTAÇÃO - 1/4 PARCELA DO BOX DO RIO OPEN 2026-TRADER-LUCAS BARROS (AGENDA 38499) | B5: 46023 | C5: 817991 | D5: RICARDO FERREIRA DA COSTA | E5: -868 | F5: EVENTO | G5: 45966 | H5: 14498 | J5: 1/4 PARCELA DO BOX DO RIO OPEN 2026 | K5: AGENDA 38499 | L5: LUCAS BARROS | M5: TRADER | N5: =VLOOKUP(H5,Clientes!B:D,3,) -> BANCO BOCOM BBM S/A | P5: =_xlfn.XLOOKUP(K5,#REF!,#REF!,0,0,1) -> #REF!
A6: =CONCATENATE($J$1,J6,$I$3,M6,$I$3,L6,$I$1,K6,$I$2) -> DESPESA DE REPRESENTAÇÃO - 1/4 PARCELA DO BOX DO RIO OPEN 2026-TRADER-JOÃO GROSSO (AGENDA 38499) | B6: 46023 | C6: 817991 | D6: RICARDO FERREIRA DA COSTA | E6: -868 | F6: EVENTO | G6: 45966 | H6: 14498 | J6: 1/4 PARCELA DO BOX DO RIO OPEN 2026 | K6: AGENDA 38499 | L6: JOÃO GROSSO | M6: TRADER | N6: =VLOOKUP(H6,Clientes!B:D,3,) -> BANCO BOCOM BBM S/A | P6: =_xlfn.XLOOKUP(K6,#REF!,#REF!,0,0,1) -> #REF!
A7: =CONCATENATE($J$1,J7,$I$3,M7,$I$3,L7,$I$1,K7,$I$2) -> DESPESA DE REPRESENTAÇÃO - 1/4 PARCELA DO BOX DO RIO OPEN 2026-TRADER-JOAO BESSA (AGENDA 38499) | B7: 46023 | C7: 817991 | D7: RAFAEL TENORIO CAVALCANTI | E7: -992 | F7: EVENTO | G7: 45966 | H7: 14416 | J7: 1/4 PARCELA DO BOX DO RIO OPEN 2026 | K7: AGENDA 38499 | L7: JOAO BESSA | M7: TRADER | N7: =VLOOKUP(H7,Clientes!B:D,3,) -> BANCO JP MORGAN S/A | P7: =_xlfn.XLOOKUP(K7,#REF!,#REF!,0,0,1) -> #REF!
A8: =CONCATENATE($J$1,J8,$I$3,M8,$I$3,L8,$I$1,K8,$I$2) -> DESPESA DE REPRESENTAÇÃO - 1/4 PARCELA DO BOX DO RIO OPEN 2026--NAMORADA DO JOAO BESSA (AGENDA 38499) | B8: 46023 | C8: 817991 | D8: RAFAEL TENORIO CAVALCANTI | E8: -992 | F8: EVENTO | G8: 45966 | H8: 14416 | J8: 1/4 PARCELA DO BOX DO RIO OPEN 2026 | K8: AGENDA 38499 | L8: NAMORADA DO JOAO BESSA | N8: =VLOOKUP(H8,Clientes!B:D,3,) -> BANCO JP MORGAN S/A | P8: =_xlfn.XLOOKUP(K8,#REF!,#REF!,0,0,1) -> #REF!
A9: =CONCATENATE($J$1,J9,$I$3,M9,$I$3,L9,$I$1,K9,$I$2) -> DESPESA DE REPRESENTAÇÃO - 1/4 PARCELA DO BOX DO RIO OPEN 2026-TRADER-FELIPE NOVAIS GARCIA (AGENDA 38499) | B9: 46023 | C9: 817991 | D9: ANTONIO AUGUSTO DAS CHAGAS CARVALHO | E9: -992 | F9: EVENTO | G9: 45966 | H9: 80573 | J9: 1/4 PARCELA DO BOX DO RIO OPEN 2026 | K9: AGENDA 38499 | L9: FELIPE NOVAIS GARCIA | M9: TRADER | N9: =VLOOKUP(H9,Clientes!B:D,3,) -> BANCO C6 S/A | P9: =_xlfn.XLOOKUP(K9,#REF!,#REF!,0,0,1) -> #REF!
A10: =CONCATENATE($J$1,J10,$I$3,M10,$I$3,L10,$I$1,K10,$I$2) -> DESPESA DE REPRESENTAÇÃO - 1/4 PARCELA DO BOX DO RIO OPEN 2026-TRADER-MARCELO ORTEGA (AGENDA 38499) | B10: 46023 | C10: 817991 | D10: ANTONIO AUGUSTO DAS CHAGAS CARVALHO | E10: -992 | F10: EVENTO | G10: 45966 | H10: 80573 | J10: 1/4 PARCELA DO BOX DO RIO OPEN 2026 | K10: AGENDA 38499 | L10: MARCELO ORTEGA | M10: TRADER | N10: =VLOOKUP(H10,Clientes!B:D,3,) -> BANCO C6 S/A | P10: =_xlfn.XLOOKUP(K10,#REF!,#REF!,0,0,1) -> #REF!
A11: =CONCATENATE($J$1,J11,$I$3,M11,$I$3,L11,$I$1,K11,$I$2) -> DESPESA DE REPRESENTAÇÃO - 1/4 PARCELA DO BOX DO RIO OPEN 2026-TRADER-LUCIANA GARCIA (AGENDA 38499) | B11: 46023 | C11: 817991 | D11: ANTONIO AUGUSTO DAS CHAGAS CARVALHO | E11: -992 | F11: EVENTO | G11: 45966 | H11: 80573 | J11: 1/4 PARCELA DO BOX DO RIO OPEN 2026 | K11: AGENDA 38499 | L11: LUCIANA GARCIA | M11: TRADER | N11: =VLOOKUP(H11,Clientes!B:D,3,) -> BANCO C6 S/A | P11: =_xlfn.XLOOKUP(K11,#REF!,#REF!,0,0,1) -> #REF!
A12: =CONCATENATE($J$1,J12,$I$3,M12,$I$3,L12,$I$1,K12,$I$2) -> DESPESA DE REPRESENTAÇÃO - 1/4 PARCELA DO BOX DO RIO OPEN 2026-TRADER-DIEGO MONT - STAR SEGURADORA (AGENDA 38499) | B12: 46023 | C12: 817991 | D12: JUAREZ JOAQUIM DE LACERDA | E12: -1116 | F12: EVENTO | G12: 45966 | H12: 1170 | J12: 1/4 PARCELA DO BOX DO RIO OPEN 2026 | K12: AGENDA 38499 | L12: DIEGO MONT - STAR SEGURADORA | M12: TRADER | N12: =VLOOKUP(H12,Clientes!B:D,3,) -> BGC LIQUIDEZ DTVM LTDA | P12: =_xlfn.XLOOKUP(K12,#REF!,#REF!,0,0,1) -> #REF!
A13: =CONCATENATE($J$1,J13,$I$3,M13,$I$3,L13,$I$1,K13,$I$2) -> DESPESA DE REPRESENTAÇÃO - 1/4 PARCELA DO BOX DO RIO OPEN 2026--ESPOSA DO DIEGO MONT - STAR SEGURADORA (AGENDA 38499) | B13: 46023 | C13: 817991 | D13: JUAREZ JOAQUIM DE LACERDA | E13: -1116 | F13: EVENTO | G13: 45966 | H13: 1170 | J13: 1/4 PARCELA DO BOX DO RIO OPEN 2026 | K13: AGENDA 38499 | L13: ESPOSA DO DIEGO MONT - STAR SEGURADORA | N13: =VLOOKUP(H13,Clientes!B:D,3,) -> BGC LIQUIDEZ DTVM LTDA | P13: =_xlfn.XLOOKUP(K13,#REF!,#REF!,0,0,1) -> #REF!
A14: =CONCATENATE($J$1,J14,$I$3,M14,$I$3,L14,$I$1,K14,$I$2) -> DESPESA DE REPRESENTAÇÃO - 1/4 PARCELA DO BOX DO RIO OPEN 2026-TRADER-MARCOS DE CASTRO LOPEZ (AGENDA 38499) | B14: 46023 | C14: 817991 | D14: GUSTAVO D ELBOUX FERRIELLO | E14: -1116 | F14: EVENTO | G14: 45966 | H14: 12413 | J14: 1/4 PARCELA DO BOX DO RIO OPEN 2026 | K14: AGENDA 38499 | L14: MARCOS DE CASTRO LOPEZ | M14: TRADER | N14: =VLOOKUP(H14,Clientes!B:D,3,) -> KAPITALO INVESTIMENTOS LTDA | P14: =_xlfn.XLOOKUP(K14,#REF!,#REF!,0,0,1) -> #REF!
A15: =CONCATENATE($J$1,J15,$I$3,M15,$I$3,L15,$I$1,K15,$I$2) -> DESPESA DE REPRESENTAÇÃO - 1/4 PARCELA DO BOX DO RIO OPEN 2026--ESPOSA DO MARCOS DE CASTRO LOPEZ (AGENDA 38499) | B15: 46023 | C15: 817991 | D15: GUSTAVO D ELBOUX FERRIELLO | E15: -1116 | F15: EVENTO | G15: 45966 | H15: 12413 | J15: 1/4 PARCELA DO BOX DO RIO OPEN 2026 | K15: AGENDA 38499 | L15: ESPOSA DO MARCOS DE CASTRO LOPEZ | N15: =VLOOKUP(H15,Clientes!B:D,3,) -> KAPITALO INVESTIMENTOS LTDA | P15: =_xlfn.XLOOKUP(K15,#REF!,#REF!,0,0,1) -> #REF!
A16: =CONCATENATE($J$1,J16,$I$3,M16,$I$3,L16,$I$1,K16,$I$2) -> DESPESA DE REPRESENTAÇÃO - 1/4 PARCELA DO BOX DO RIO OPEN 2026--FILHO DO MARCOS DE CASTRO LOPEZ (AGENDA 38499) | B16: 46023 | C16: 817991 | D16: GUSTAVO D ELBOUX FERRIELLO | E16: -1116 | F16: EVENTO | G16: 45966 | H16: 12413 | J16: 1/4 PARCELA DO BOX DO RIO OPEN 2026 | K16: AGENDA 38499 | L16: FILHO DO MARCOS DE CASTRO LOPEZ | N16: =VLOOKUP(H16,Clientes!B:D,3,) -> KAPITALO INVESTIMENTOS LTDA | P16: =_xlfn.XLOOKUP(K16,#REF!,#REF!,0,0,1) -> #REF!
A17: =CONCATENATE($J$1,J17,$I$3,M17,$I$3,L17,$I$1,K17,$I$2) -> DESPESA DE REPRESENTAÇÃO - 1/4 PARCELA DO BOX DO RIO OPEN 2026-TRADER-BRUNO PAULO (AGENDA 38499) | B17: 46023 | C17: 817991 | D17: CESAR MARIANO SCARAMBONE MENEZES | E17: -124 | F17: EVENTO | G17: 45966 | H17: 83063 | J17: 1/4 PARCELA DO BOX DO RIO OPEN 2026 | K17: AGENDA 38499 | L17: BRUNO PAULO | M17: TRADER | N17: =VLOOKUP(H17,Clientes!B:D,3,) -> SCHONFELD STRATEGIC ADVISORS BRAZIL LTDA. | P17: =_xlfn.XLOOKUP(K17,#REF!,#REF!,0,0,1) -> #REF!
A18: =CONCATENATE($J$1,J18,$I$3,M18,$I$3,L18,$I$1,K18,$I$2) -> DESPESA DE REPRESENTAÇÃO - 1/4 PARCELA DO BOX DO RIO OPEN 2026--FILHA DO BRUNO PAULO (AGENDA 38499) | B18: 46023 | C18: 817991 | D18: CESAR MARIANO SCARAMBONE MENEZES | E18: -124 | F18: EVENTO | G18: 45966 | H18: 83063 | J18: 1/4 PARCELA DO BOX DO RIO OPEN 2026 | K18: AGENDA 38499 | L18: FILHA DO BRUNO PAULO | N18: =VLOOKUP(H18,Clientes!B:D,3,) -> SCHONFELD STRATEGIC ADVISORS BRAZIL LTDA. | P18: =_xlfn.XLOOKUP(K18,#REF!,#REF!,0,0,1) -> #REF!
A19: =CONCATENATE($J$1,J19,$I$3,M19,$I$3,L19,$I$1,K19,$I$2) -> DESPESA DE REPRESENTAÇÃO - 1/4 PARCELA DO BOX DO RIO OPEN 2026-TRADER-ANDRE LOBATO PINHEIRO (AGENDA 38499) | B19: 46023 | C19: 817991 | D19: ALEXANDRE DA COSTA SOARES | E19: -124 | F19: EVENTO | G19: 45966 | H19: 15501 | J19: 1/4 PARCELA DO BOX DO RIO OPEN 2026 | K19: AGENDA 38499 | L19: ANDRE LOBATO PINHEIRO | M19: TRADER | N19: =VLOOKUP(H19,Clientes!B:D,3,) -> BANCO BTG PACTUAL S/A | P19: =_xlfn.XLOOKUP(K19,#REF!,#REF!,0,0,1) -> #REF!
A20: =CONCATENATE($J$1,J20,$I$3,M20,$I$3,L20,$I$1,K20,$I$2) -> DESPESA DE REPRESENTAÇÃO - 1/4 PARCELA DO BOX DO RIO OPEN 2026--ESPOSA DO ANDRE LOBATO PINHEIRO (AGENDA 38499) | B20: 46023 | C20: 817991 | D20: ALEXANDRE DA COSTA SOARES | E20: -124 | F20: EVENTO | G20: 45966 | H20: 15501 | J20: 1/4 PARCELA DO BOX DO RIO OPEN 2026 | K20: AGENDA 38499 | L20: ESPOSA DO ANDRE LOBATO PINHEIRO | N20: =VLOOKUP(H20,Clientes!B:D,3,) -> BANCO BTG PACTUAL S/A | P20: =_xlfn.XLOOKUP(K20,#REF!,#REF!,0,0,1) -> #REF!
A21: =CONCATENATE($J$1,J21,$I$3,M21,$I$3,L21,$I$1,K21,$I$2) -> DESPESA DE REPRESENTAÇÃO - 1/4 PARCELA DO BOX DO RIO OPEN 2026-TRADER-HENRIQUE DE LA ROCQUE (AGENDA 38499) | B21: 46023 | C21: 817991 | D21: JOSE MAURICIO GOMES TEIXEIRA | E21: -124 | F21: EVENTO | G21: 45966 | H21: 125119 | J21: 1/4 PARCELA DO BOX DO RIO OPEN 2026 | K21: AGENDA 38499 | L21: HENRIQUE DE LA ROCQUE | M21: TRADER | N21: =VLOOKUP(H21,Clientes!B:D,3,) -> IRB ASSET MANAGEMENT S.A | P21: =_xlfn.XLOOKUP(K21,#REF!,#REF!,0,0,1) -> #REF!
A22: =CONCATENATE($J$1,J22,$I$3,M22,$I$3,L22,$I$1,K22,$I$2) -> DESPESA DE REPRESENTAÇÃO - 2/4 PARCELA DO BOX DO RIO OPEN 2026-TRADER-BRUNO PAULO (AGENDA 38500) | B22: 46023 | C22: 817991 | D22: CESAR MARIANO SCARAMBONE MENEZES | E22: -1116 | F22: EVENTO | G22: 45996 | H22: 83063 | J22: 2/4 PARCELA DO BOX DO RIO OPEN 2026 | K22: AGENDA 38500 | L22: BRUNO PAULO | M22: TRADER | N22: =VLOOKUP(H22,Clientes!B:D,3,) -> SCHONFELD STRATEGIC ADVISORS BRAZIL LTDA. | P22: =_xlfn.XLOOKUP(K22,#REF!,#REF!,0,0,1) -> #REF!
A23: =CONCATENATE($J$1,J23,$I$3,M23,$I$3,L23,$I$1,K23,$I$2) -> DESPESA DE REPRESENTAÇÃO - 2/4 PARCELA DO BOX DO RIO OPEN 2026--FILHA DO BRUNO PAULO (AGENDA 38500) | B23: 46023 | C23: 817991 | D23: CESAR MARIANO SCARAMBONE MENEZES | E23: -1116 | F23: EVENTO | G23: 45996 | H23: 83063 | J23: 2/4 PARCELA DO BOX DO RIO OPEN 2026 | K23: AGENDA 38500 | L23: FILHA DO BRUNO PAULO | N23: =VLOOKUP(H23,Clientes!B:D,3,) -> SCHONFELD STRATEGIC ADVISORS BRAZIL LTDA. | P23: =_xlfn.XLOOKUP(K23,#REF!,#REF!,0,0,1) -> #REF!
A24: =CONCATENATE($J$1,J24,$I$3,M24,$I$3,L24,$I$1,K24,$I$2) -> DESPESA DE REPRESENTAÇÃO - 2/4 PARCELA DO BOX DO RIO OPEN 2026-TRADER-ANDRE LOBATO PINHEIRO (AGENDA 38500) | B24: 46023 | C24: 817991 | D24: ALEXANDRE DA COSTA SOARES | E24: -1116 | F24: EVENTO | G24: 45996 | H24: 15501 | J24: 2/4 PARCELA DO BOX DO RIO OPEN 2026 | K24: AGENDA 38500 | L24: ANDRE LOBATO PINHEIRO | M24: TRADER | N24: =VLOOKUP(H24,Clientes!B:D,3,) -> BANCO BTG PACTUAL S/A | P24: =_xlfn.XLOOKUP(K24,#REF!,#REF!,0,0,1) -> #REF!
A25: =CONCATENATE($J$1,J25,$I$3,M25,$I$3,L25,$I$1,K25,$I$2) -> DESPESA DE REPRESENTAÇÃO - 2/4 PARCELA DO BOX DO RIO OPEN 2026--ESPOSA DO ANDRE LOBATO PINHEIRO (AGENDA 38500) | B25: 46023 | C25: 817991 | D25: ALEXANDRE DA COSTA SOARES | E25: -1116 | F25: EVENTO | G25: 45996 | H25: 15501 | J25: 2/4 PARCELA DO BOX DO RIO OPEN 2026 | K25: AGENDA 38500 | L25: ESPOSA DO ANDRE LOBATO PINHEIRO | N25: =VLOOKUP(H25,Clientes!B:D,3,) -> BANCO BTG PACTUAL S/A | P25: =_xlfn.XLOOKUP(K25,#REF!,#REF!,0,0,1) -> #REF!
A26: =CONCATENATE($J$1,J26,$I$3,M26,$I$3,L26,$I$1,K26,$I$2) -> DESPESA DE REPRESENTAÇÃO - 2/4 PARCELA DO BOX DO RIO OPEN 2026-TRADER-HENRIQUE DE LA ROCQUE (AGENDA 38500) | B26: 46023 | C26: 817991 | D26: JOSE MAURICIO GOMES TEIXEIRA | E26: -1116 | F26: EVENTO | G26: 45996 | H26: 125119 | J26: 2/4 PARCELA DO BOX DO RIO OPEN 2026 | K26: AGENDA 38500 | L26: HENRIQUE DE LA ROCQUE | M26: TRADER | N26: =VLOOKUP(H26,Clientes!B:D,3,) -> IRB ASSET MANAGEMENT S.A | P26: =_xlfn.XLOOKUP(K26,#REF!,#REF!,0,0,1) -> #REF!
A27: =CONCATENATE($J$1,J27,$I$3,M27,$I$3,L27,$I$1,K27,$I$2) -> DESPESA DE REPRESENTAÇÃO - 2/4 PARCELA DO BOX DO RIO OPEN 2026-TRADER-MARCOS DE CASTRO LOPEZ (AGENDA 38500) | B27: 46023 | C27: 817991 | D27: GUSTAVO D ELBOUX FERRIELLO | E27: -1860 | F27: EVENTO | G27: 45996 | H27: 12413 | J27: 2/4 PARCELA DO BOX DO RIO OPEN 2026 | K27: AGENDA 38500 | L27: MARCOS DE CASTRO LOPEZ | M27: TRADER | N27: =VLOOKUP(H27,Clientes!B:D,3,) -> KAPITALO INVESTIMENTOS LTDA | P27: =_xlfn.XLOOKUP(K27,#REF!,#REF!,0,0,1) -> #REF!
A28: =CONCATENATE($J$1,J28,$I$3,M28,$I$3,L28,$I$1,K28,$I$2) -> DESPESA DE REPRESENTAÇÃO - 2/4 PARCELA DO BOX DO RIO OPEN 2026--ESPOSA DO MARCOS DE CASTRO LOPEZ (AGENDA 38500) | B28: 46023 | C28: 817991 | D28: GUSTAVO D ELBOUX FERRIELLO | E28: -1860 | F28: EVENTO | G28: 45996 | H28: 12413 | J28: 2/4 PARCELA DO BOX DO RIO OPEN 2026 | K28: AGENDA 38500 | L28: ESPOSA DO MARCOS DE CASTRO LOPEZ | N28: =VLOOKUP(H28,Clientes!B:D,3,) -> KAPITALO INVESTIMENTOS LTDA | P28: =_xlfn.XLOOKUP(K28,#REF!,#REF!,0,0,1) -> #REF!
A29: =CONCATENATE($J$1,J29,$I$3,M29,$I$3,L29,$I$1,K29,$I$2) -> DESPESA DE REPRESENTAÇÃO - 2/4 PARCELA DO BOX DO RIO OPEN 2026-TRADER-FELIPE SANTANA DA SILVEIRA (AGENDA 38500) | B29: 46023 | C29: 817991 | D29: ANTÔNIO MARTINS NETO | E29: -1860 | F29: EVENTO | G29: 45996 | H29: 80958 | J29: 2/4 PARCELA DO BOX DO RIO OPEN 2026 | K29: AGENDA 38500 | L29: FELIPE SANTANA DA SILVEIRA | M29: TRADER | N29: =VLOOKUP(H29,Clientes!B:D,3,) -> ITAU UNIBANCO ASSET - OPTIMUS | P29: =_xlfn.XLOOKUP(K29,#REF!,#REF!,0,0,1) -> #REF!
A30: =CONCATENATE($J$1,J30,$I$3,M30,$I$3,L30,$I$1,K30,$I$2) -> DESPESA DE REPRESENTAÇÃO - 2/4 PARCELA DO BOX DO RIO OPEN 2026--ESPOSA DO FELIPE SANTANA DA SILVEIRA (AGENDA 38500) | B30: 46023 | C30: 817991 | D30: ANTÔNIO MARTINS NETO | E30: -1860 | F30: EVENTO | G30: 45996 | H30: 80958 | J30: 2/4 PARCELA DO BOX DO RIO OPEN 2026 | K30: AGENDA 38500 | L30: ESPOSA DO FELIPE SANTANA DA SILVEIRA | N30: =VLOOKUP(H30,Clientes!B:D,3,) -> ITAU UNIBANCO ASSET - OPTIMUS | P30: =_xlfn.XLOOKUP(K30,#REF!,#REF!,0,0,1) -> #REF!
A31: =CONCATENATE($J$1,J31,$I$3,M31,$I$3,L31,$I$1,K31,$I$2) -> DESPESA DE REPRESENTAÇÃO - 2/4 PARCELA DO BOX DO RIO OPEN 2026-TRADER-GUSTAVO MORAIS SILVA (AGENDA 38500) | B31: 46023 | C31: 817991 | D31: ENRICO BORTPLUZO CASSIANO | E31: -1860 | F31: EVENTO | G31: 45996 | H31: 79372 | J31: 2/4 PARCELA DO BOX DO RIO OPEN 2026 | K31: AGENDA 38500 | L31: GUSTAVO MORAIS SILVA | M31: TRADER | N31: =VLOOKUP(H31,Clientes!B:D,3,) -> ICATU VANGUARDA GESTAO DE RECURSOS LTDA | P31: =_xlfn.XLOOKUP(K31,#REF!,#REF!,0,0,1) -> #REF!
A32: =CONCATENATE($J$1,J32,$I$3,M32,$I$3,L32,$I$1,K32,$I$2) -> DESPESA DE REPRESENTAÇÃO - 2/4 PARCELA DO BOX DO RIO OPEN 2026-TRADER-FERNANDO SCARPA R LEITE (AGENDA 38500) | B32: 46023 | C32: 817991 | D32: FELIPE MEIRELLES RACCAH | E32: -124 | F32: EVENTO | G32: 45996 | H32: 80375 | J32: 2/4 PARCELA DO BOX DO RIO OPEN 2026 | K32: AGENDA 38500 | L32: FERNANDO SCARPA R LEITE | M32: TRADER | N32: =VLOOKUP(H32,Clientes!B:D,3,) -> ITAU UNIBANCO S/A | P32: =_xlfn.XLOOKUP(K32,#REF!,#REF!,0,0,1) -> #REF!
A33: =CONCATENATE($J$1,J33,$I$3,M33,$I$3,L33,$I$1,K33,$I$2) -> DESPESA DE REPRESENTAÇÃO - 2/4 PARCELA DO BOX DO RIO OPEN 2026--FILHA DO FERNANDO SCARPA R LEITE (AGENDA 38500) | B33: 46023 | C33: 817991 | D33: FELIPE MEIRELLES RACCAH | E33: -124 | F33: EVENTO | G33: 45996 | H33: 80375 | J33: 2/4 PARCELA DO BOX DO RIO OPEN 2026 | K33: AGENDA 38500 | L33: FILHA DO FERNANDO SCARPA R LEITE | N33: =VLOOKUP(H33,Clientes!B:D,3,) -> ITAU UNIBANCO S/A | P33: =_xlfn.XLOOKUP(K33,#REF!,#REF!,0,0,1) -> #REF!
A34: =CONCATENATE($J$1,J34,$I$3,M34,$I$3,L34,$I$1,K34,$I$2) -> DESPESA DE REPRESENTAÇÃO - 2/4 PARCELA DO BOX DO RIO OPEN 2026-TRADER-LUIZ ALBERTO BASQUEIRA (AGENDA 38500) | B34: 46023 | C34: 817991 | D34: LIQUIDEZ-OTHER | E34: -124 | F34: EVENTO | G34: 45996 | H34: 79931 | J34: 2/4 PARCELA DO BOX DO RIO OPEN 2026 | K34: AGENDA 38500 | L34: LUIZ ALBERTO BASQUEIRA | M34: TRADER | N34: =VLOOKUP(H34,Clientes!B:D,3,) -> SPX GESTAO DE RECURSOS LTDA | P34: =_xlfn.XLOOKUP(K34,#REF!,#REF!,0,0,1) -> #REF!
A35: =CONCATENATE($J$1,J35,$I$3,M35,$I$3,L35,$I$1,K35,$I$2) -> DESPESA DE REPRESENTAÇÃO - 2/4 PARCELA DO BOX DO RIO OPEN 2026-TRADER-RODRIGO FERREIRA (AGENDA 38500) | B35: 46113 | C35: 817991 | D35: CLAUDIO DE SOUZA PACINI | E35: -124 | F35: EVENTO | G35: 45996 | H35: 12413 | J35: 2/4 PARCELA DO BOX DO RIO OPEN 2026 | K35: AGENDA 38500 | L35: RODRIGO FERREIRA | M35: TRADER | N35: =VLOOKUP(H35,Clientes!B:D,3,) -> KAPITALO INVESTIMENTOS LTDA | P35: =_xlfn.XLOOKUP(K35,#REF!,#REF!,0,0,1) -> #REF!
A36: =CONCATENATE($J$1,J36,$I$3,M36,$I$3,L36,$I$1,K36,$I$2) -> DESPESA DE REPRESENTAÇÃO - 2/4 PARCELA DO BOX DO RIO OPEN 2026--ESPOSA RODRIGO FERREIRA (AGENDA 38500) | B36: 46113 | C36: 817991 | D36: CLAUDIO DE SOUZA PACINI | E36: -124 | F36: EVENTO | G36: 45996 | H36: 12413 | J36: 2/4 PARCELA DO BOX DO RIO OPEN 2026 | K36: AGENDA 38500 | L36: ESPOSA RODRIGO FERREIRA | N36: =VLOOKUP(H36,Clientes!B:D,3,) -> KAPITALO INVESTIMENTOS LTDA | P36: =_xlfn.XLOOKUP(K36,#REF!,#REF!,0,0,1) -> #REF!
A37: =CONCATENATE($J$1,J37,$I$3,M37,$I$3,L37,$I$1,K37,$I$2) -> DESPESA DE REPRESENTAÇÃO - 3/4 PARCELA DO BOX DO RIO OPEN 2026-TRADER-FERNANDO SCARPA R LEITE (AGENDA 38501) | B37: 46023 | C37: 817991 | D37: FELIPE MEIRELLES RACCAH | E37: -2604 | F37: EVENTO | G37: 46027 | H37: 80375 | J37: 3/4 PARCELA DO BOX DO RIO OPEN 2026 | K37: AGENDA 38501 | L37: FERNANDO SCARPA R LEITE | M37: TRADER | N37: =VLOOKUP(H37,Clientes!B:D,3,) -> ITAU UNIBANCO S/A | P37: =_xlfn.XLOOKUP(K37,#REF!,#REF!,0,0,1) -> #REF!
A38: =CONCATENATE($J$1,J38,$I$3,M38,$I$3,L38,$I$1,K38,$I$2) -> DESPESA DE REPRESENTAÇÃO - 3/4 PARCELA DO BOX DO RIO OPEN 2026--FILHA DO FERNANDO SCARPA R LEITE (AGENDA 38501) | B38: 46023 | C38: 817991 | D38: FELIPE MEIRELLES RACCAH | E38: -2604 | F38: EVENTO | G38: 46027 | H38: 80375 | J38: 3/4 PARCELA DO BOX DO RIO OPEN 2026 | K38: AGENDA 38501 | L38: FILHA DO FERNANDO SCARPA R LEITE | N38: =VLOOKUP(H38,Clientes!B:D,3,) -> ITAU UNIBANCO S/A | P38: =_xlfn.XLOOKUP(K38,#REF!,#REF!,0,0,1) -> #REF!
A39: =CONCATENATE($J$1,J39,$I$3,M39,$I$3,L39,$I$1,K39,$I$2) -> DESPESA DE REPRESENTAÇÃO - 3/4 PARCELA DO BOX DO RIO OPEN 2026-TRADER-LUIZ ALBERTO BASQUEIRA (AGENDA 38501) | B39: 46023 | C39: 817991 | D39: LIQUIDEZ-OTHER | E39: -2604 | F39: EVENTO | G39: 46027 | H39: 79931 | J39: 3/4 PARCELA DO BOX DO RIO OPEN 2026 | K39: AGENDA 38501 | L39: LUIZ ALBERTO BASQUEIRA | M39: TRADER | N39: =VLOOKUP(H39,Clientes!B:D,3,) -> SPX GESTAO DE RECURSOS LTDA | P39: =_xlfn.XLOOKUP(K39,#REF!,#REF!,0,0,1) -> #REF!
A40: =CONCATENATE($J$1,J40,$I$3,M40,$I$3,L40,$I$1,K40,$I$2) -> DESPESA DE REPRESENTAÇÃO - 3/4 PARCELA DO BOX DO RIO OPEN 2026-TRADER-RODRIGO FERREIRA (AGENDA 38501) | B40: 46113 | C40: 817991 | D40: CLAUDIO DE SOUZA PACINI | E40: -2604 | F40: EVENTO | G40: 46027 | H40: 12413 | J40: 3/4 PARCELA DO BOX DO RIO OPEN 2026 | K40: AGENDA 38501 | L40: RODRIGO FERREIRA | M40: TRADER | N40: =VLOOKUP(H40,Clientes!B:D,3,) -> KAPITALO INVESTIMENTOS LTDA | P40: =_xlfn.XLOOKUP(K40,#REF!,#REF!,0,0,1) -> #REF!
A41: =CONCATENATE($J$1,J41,$I$3,M41,$I$3,L41,$I$1,K41,$I$2) -> DESPESA DE REPRESENTAÇÃO - 3/4 PARCELA DO BOX DO RIO OPEN 2026--ESPOSA RODRIGO FERREIRA (AGENDA 38501) | B41: 46113 | C41: 817991 | D41: CLAUDIO DE SOUZA PACINI | E41: -2604 | F41: EVENTO | G41: 46027 | H41: 12413 | J41: 3/4 PARCELA DO BOX DO RIO OPEN 2026 | K41: AGENDA 38501 | L41: ESPOSA RODRIGO FERREIRA | N41: =VLOOKUP(H41,Clientes!B:D,3,) -> KAPITALO INVESTIMENTOS LTDA | P41: =_xlfn.XLOOKUP(K41,#REF!,#REF!,0,0,1) -> #REF!
A42: =CONCATENATE($J$1,J42,$I$3,M42,$I$3,L42,$I$1,K42,$I$2) -> DESPESA DE REPRESENTAÇÃO - 3/4 PARCELA DO BOX DO RIO OPEN 2026--ESPOSA DO ANDRE ACCIOLY (AGENDA 38501) | B42: 46023 | C42: 817991 | D42: LIQUIDEZ-OTHER | E42: -496 | F42: EVENTO | G42: 46027 | H42: 1170 | J42: 3/4 PARCELA DO BOX DO RIO OPEN 2026 | K42: AGENDA 38501 | L42: ESPOSA DO ANDRE ACCIOLY | N42: =VLOOKUP(H42,Clientes!B:D,3,) -> BGC LIQUIDEZ DTVM LTDA | P42: =_xlfn.XLOOKUP(K42,#REF!,#REF!,0,0,1) -> #REF!
A43: =CONCATENATE($J$1,J43,$I$3,M43,$I$3,L43,$I$1,K43,$I$2) -> DESPESA DE REPRESENTAÇÃO - 3/4 PARCELA DO BOX DO RIO OPEN 2026--FILHO DO ANDRE ACCIOLY (AGENDA 38501) | B43: 46023 | C43: 817991 | D43: LIQUIDEZ-OTHER | E43: -496 | F43: EVENTO | G43: 46027 | H43: 1170 | J43: 3/4 PARCELA DO BOX DO RIO OPEN 2026 | K43: AGENDA 38501 | L43: FILHO DO ANDRE ACCIOLY | N43: =VLOOKUP(H43,Clientes!B:D,3,) -> BGC LIQUIDEZ DTVM LTDA | P43: =_xlfn.XLOOKUP(K43,#REF!,#REF!,0,0,1) -> #REF!
A44: =CONCATENATE($J$1,J44,$I$3,M44,$I$3,L44,$I$1,K44,$I$2) -> DESPESA DE REPRESENTAÇÃO - 3/4 PARCELA DO BOX DO RIO OPEN 2026-BROKER-JOSE MAURICIO GOMES TEIXEIRA (AGENDA 38501) | B44: 46023 | C44: 817991 | D44: JOSE MAURICIO GOMES TEIXEIRA | E44: -496 | F44: EVENTO | G44: 46027 | H44: 1170 | J44: 3/4 PARCELA DO BOX DO RIO OPEN 2026 | K44: AGENDA 38501 | L44: JOSE MAURICIO GOMES TEIXEIRA | M44: BROKER | N44: =VLOOKUP(H44,Clientes!B:D,3,) -> BGC LIQUIDEZ DTVM LTDA | P44: =_xlfn.XLOOKUP(K44,#REF!,#REF!,0,0,1) -> #REF!
A45: =CONCATENATE($J$1,J45,$I$3,M45,$I$3,L45,$I$1,K45,$I$2) -> DESPESA DE REPRESENTAÇÃO - 3/4 PARCELA DO BOX DO RIO OPEN 2026--ESPOSA DO JOSE MAURICIO GOMES TEIXEIRA (AGENDA 38501) | B45: 46023 | C45: 817991 | D45: JOSE MAURICIO GOMES TEIXEIRA | E45: -496 | F45: EVENTO | G45: 46027 | H45: 1170 | J45: 3/4 PARCELA DO BOX DO RIO OPEN 2026 | K45: AGENDA 38501 | L45: ESPOSA DO JOSE MAURICIO GOMES TEIXEIRA | N45: =VLOOKUP(H45,Clientes!B:D,3,) -> BGC LIQUIDEZ DTVM LTDA | P45: =_xlfn.XLOOKUP(K45,#REF!,#REF!,0,0,1) -> #REF!
A46: =CONCATENATE($J$1,J46,$I$3,M46,$I$3,L46,$I$1,K46,$I$2) -> DESPESA DE REPRESENTAÇÃO - 3/4 PARCELA DO BOX DO RIO OPEN 2026-TRADER-LUAN VALENTE (AGENDA 38501) | B46: 46023 | C46: 817991 | D46: JOSE MAURICIO GOMES TEIXEIRA | E46: -496 | F46: EVENTO | G46: 46027 | H46: 80132 | J46: 3/4 PARCELA DO BOX DO RIO OPEN 2026 | K46: AGENDA 38501 | L46: LUAN VALENTE | M46: TRADER | N46: =VLOOKUP(H46,Clientes!B:D,3,) -> GLOBO COMUNICACAO E PARTICIPACOES S.A | P46: =_xlfn.XLOOKUP(K46,#REF!,#REF!,0,0,1) -> #REF!
A47: =CONCATENATE($J$1,J47,$I$3,M47,$I$3,L47,$I$1,K47,$I$2) -> DESPESA DE REPRESENTAÇÃO - CAMAROTE NFL - SEGUNDA PARCELA-TRADER-THUNAY MOTA RAIA (AGENDA 36310) | B47: 46023 | C47: 817991 | D47: CARLOS BASILE | E47: -4600 | F47: EVENTO | G47: 45828 | H47: 79460 | J47: CAMAROTE NFL - SEGUNDA PARCELA | K47: AGENDA 36310 | L47: THUNAY MOTA RAIA | M47: TRADER | N47: =VLOOKUP(H47,Clientes!B:D,3,) -> ITAU UNIBANCO S/A | P47: =_xlfn.XLOOKUP(K47,#REF!,#REF!,0,0,1) -> #REF!
A48: =CONCATENATE($J$1,J48,$I$3,M48,$I$3,L48,$I$1,K48,$I$2) -> DESPESA DE REPRESENTAÇÃO - CAMAROTE NFL - SEGUNDA PARCELA-TRADER-BRUNO CHIARADIA PERUCHI (AGENDA 36310) | B48: 46023 | C48: 817991 | D48: ANDREA LICASSIA ALMEIDA SANTOS | E48: -4600 | F48: EVENTO | G48: 45828 | H48: 54684 | J48: CAMAROTE NFL - SEGUNDA PARCELA | K48: AGENDA 36310 | L48: BRUNO CHIARADIA PERUCHI | M48: TRADER | N48: =VLOOKUP(H48,Clientes!B:D,3,) -> BANCO RENDIMENTO S/A | P48: =_xlfn.XLOOKUP(K48,#REF!,#REF!,0,0,1) -> #REF!
A49: =CONCATENATE($J$1,J49,$I$3,M49,$I$3,L49,$I$1,K49,$I$2) -> DESPESA DE REPRESENTAÇÃO - CAMAROTE NFL - SEGUNDA PARCELA-TRADER-MAURICIO DA COSTA VELASCO (AGENDA 36310) | B49: 46023 | C49: 817991 | D49: EDUARDO TADEU CARAPIA UTTEMBERG | E49: -2300 | F49: EVENTO | G49: 45828 | H49: 5655 | J49: CAMAROTE NFL - SEGUNDA PARCELA | K49: AGENDA 36310 | L49: MAURICIO DA COSTA VELASCO | M49: TRADER | N49: =VLOOKUP(H49,Clientes!B:D,3,) -> #N/A | P49: =_xlfn.XLOOKUP(K49,#REF!,#REF!,0,0,1) -> #REF!
A50: =CONCATENATE($J$1,J50,$I$3,M50,$I$3,L50,$I$1,K50,$I$2) -> DESPESA DE REPRESENTAÇÃO - CAMAROTE NFL - SEGUNDA PARCELA-TRADER-FERNANDO BARTHOLOMEU] (AGENDA 36310) | B50: 46023 | C50: 817991 | D50: ANTONIO AUGUSTO DAS CHAGAS CARVALHO | E50: -4600 | F50: EVENTO | G50: 45828 | H50: 15781 | J50: CAMAROTE NFL - SEGUNDA PARCELA | K50: AGENDA 36310 | L50: FERNANDO BARTHOLOMEU] | M50: TRADER | N50: =VLOOKUP(H50,Clientes!B:D,3,) -> BANCO SAFRA S/A | P50: =_xlfn.XLOOKUP(K50,#REF!,#REF!,0,0,1) -> #REF!
A51: =CONCATENATE($J$1,J51,$I$3,M51,$I$3,L51,$I$1,K51,$I$2) -> DESPESA DE REPRESENTAÇÃO - CAMAROTE NFL - SEGUNDA PARCELA-TRADER-GUSTAVO VASCONCELLOS (AGENDA 36310) | B51: 46023 | C51: 817991 | D51: RICARDO FERREIRA DA COSTA | E51: -4600 | F51: EVENTO | G51: 45828 | H51: 80233 | J51: CAMAROTE NFL - SEGUNDA PARCELA | K51: AGENDA 36310 | L51: GUSTAVO VASCONCELLOS | M51: TRADER | N51: =VLOOKUP(H51,Clientes!B:D,3,) -> BANCO ABC BRASIL S/A | P51: =_xlfn.XLOOKUP(K51,#REF!,#REF!,0,0,1) -> #REF!
A52: =CONCATENATE($J$1,J52,$I$3,M52,$I$3,L52,$I$1,K52,$I$2) -> DESPESA DE REPRESENTAÇÃO - CAMAROTE NFL - SEGUNDA PARCELA-TRADER-NEWTON AKIHIRO IWAMURA (AGENDA 36310) | B52: 46023 | C52: 817991 | D52: RICARDO FERREIRA DA COSTA | E52: -4600 | F52: EVENTO | G52: 45828 | H52: 80343 | J52: CAMAROTE NFL - SEGUNDA PARCELA | K52: AGENDA 36310 | L52: NEWTON AKIHIRO IWAMURA | M52: TRADER | N52: =VLOOKUP(H52,Clientes!B:D,3,) -> BANCO BS2 S/A | P52: =_xlfn.XLOOKUP(K52,#REF!,#REF!,0,0,1) -> #REF!
A53: =CONCATENATE($J$1,J53,$I$3,M53,$I$3,L53,$I$1,K53,$I$2) -> DESPESA DE REPRESENTAÇÃO - CAMAROTE NFL - SEGUNDA PARCELA-BROKER-ANTONIO AGIZ FILHO (AGENDA 36310) | B53: 46023 | C53: 817991 | D53: ANTONIO AGIZ FILHO | E53: -4600 | F53: EVENTO | G53: 45828 | H53: 1170 | J53: CAMAROTE NFL - SEGUNDA PARCELA | K53: AGENDA 36310 | L53: ANTONIO AGIZ FILHO | M53: BROKER | N53: =VLOOKUP(H53,Clientes!B:D,3,) -> BGC LIQUIDEZ DTVM LTDA | P53: =_xlfn.XLOOKUP(K53,#REF!,#REF!,0,0,1) -> #REF!
A54: =CONCATENATE($J$1,J54,$I$3,M54,$I$3,L54,$I$1,K54,$I$2) -> DESPESA DE REPRESENTAÇÃO - CAMAROTE NFL - SEGUNDA PARCELA-BROKER-ANTONIO AUGUSTO DAS CHAGAS CARVALHO (AGENDA 36310) | B54: 46023 | C54: 817991 | D54: ANTONIO AUGUSTO DAS CHAGAS CARVALHO | E54: -4600 | F54: EVENTO | G54: 45828 | H54: 1170 | J54: CAMAROTE NFL - SEGUNDA PARCELA | K54: AGENDA 36310 | L54: ANTONIO AUGUSTO DAS CHAGAS CARVALHO | M54: BROKER | N54: =VLOOKUP(H54,Clientes!B:D,3,) -> BGC LIQUIDEZ DTVM LTDA | P54: =_xlfn.XLOOKUP(K54,#REF!,#REF!,0,0,1) -> #REF!
A55: =CONCATENATE($J$1,J55,$I$3,M55,$I$3,L55,$I$1,K55,$I$2) -> DESPESA DE REPRESENTAÇÃO - CAMAROTE NFL - SEGUNDA PARCELA-BROKER-CARLOS BASILE (AGENDA 36310) | B55: 46023 | C55: 817991 | D55: CARLOS BASILE | E55: -4600 | F55: EVENTO | G55: 45828 | H55: 1170 | J55: CAMAROTE NFL - SEGUNDA PARCELA | K55: AGENDA 36310 | L55: CARLOS BASILE | M55: BROKER | N55: =VLOOKUP(H55,Clientes!B:D,3,) -> BGC LIQUIDEZ DTVM LTDA | P55: =_xlfn.XLOOKUP(K55,#REF!,#REF!,0,0,1) -> #REF!
A56: =CONCATENATE($J$1,J56,$I$3,M56,$I$3,L56,$I$1,K56,$I$2) -> DESPESA DE REPRESENTAÇÃO - 30 CANECAS DE BRINDE PARA O RIO OPEN 2026--FILHO DO ERMINIO (AGENDA 39003) | B56: 46023 | C56: 817991 | D56: LIQUIDEZ-OTHER | E56: -74.485714 | F56: EVENTO | G56: 45988 | H56: 1170 | J56: 30 CANECAS DE BRINDE PARA O RIO OPEN 2026 | K56: AGENDA 39003 | L56: FILHO DO ERMINIO | N56: =VLOOKUP(H56,Clientes!B:D,3,) -> BGC LIQUIDEZ DTVM LTDA | P56: =_xlfn.XLOOKUP(K56,#REF!,#REF!,0,0,1) -> #REF!
A57: =CONCATENATE($J$1,J57,$I$3,M57,$I$3,L57,$I$1,K57,$I$2) -> DESPESA DE REPRESENTAÇÃO - 30 CANECAS DE BRINDE PARA O RIO OPEN 2026--AMIGO DO FILHO DO ERMINIO (AGENDA 39003) | B57: 46023 | C57: 817991 | D57: LIQUIDEZ-OTHER | E57: -74.485714 | F57: EVENTO | G57: 45988 | H57: 1170 | J57: 30 CANECAS DE BRINDE PARA O RIO OPEN 2026 | K57: AGENDA 39003 | L57: AMIGO DO FILHO DO ERMINIO | N57: =VLOOKUP(H57,Clientes!B:D,3,) -> BGC LIQUIDEZ DTVM LTDA | P57: =_xlfn.XLOOKUP(K57,#REF!,#REF!,0,0,1) -> #REF!
A58: =CONCATENATE($J$1,J58,$I$3,M58,$I$3,L58,$I$1,K58,$I$2) -> DESPESA DE REPRESENTAÇÃO - 30 CANECAS DE BRINDE PARA O RIO OPEN 2026-TRADER-PATRICK GRANDMASSON CROCKETT C (AGENDA 39003) | B58: 46023 | C58: 817991 | D58: RICARDO FERREIRA DA COSTA | E58: -74.485714 | F58: EVENTO | G58: 45988 | H58: 14498 | J58: 30 CANECAS DE BRINDE PARA O RIO OPEN 2026 | K58: AGENDA 39003 | L58: PATRICK GRANDMASSON CROCKETT C | M58: TRADER | N58: =VLOOKUP(H58,Clientes!B:D,3,) -> BANCO BOCOM BBM S/A | P58: =_xlfn.XLOOKUP(K58,#REF!,#REF!,0,0,1) -> #REF!
A59: =CONCATENATE($J$1,J59,$I$3,M59,$I$3,L59,$I$1,K59,$I$2) -> DESPESA DE REPRESENTAÇÃO - 30 CANECAS DE BRINDE PARA O RIO OPEN 2026-TRADER-LUCAS BARROS (AGENDA 39003) | B59: 46023 | C59: 817991 | D59: RICARDO FERREIRA DA COSTA | E59: -74.485714 | F59: EVENTO | G59: 45988 | H59: 14498 | J59: 30 CANECAS DE BRINDE PARA O RIO OPEN 2026 | K59: AGENDA 39003 | L59: LUCAS BARROS | M59: TRADER | N59: =VLOOKUP(H59,Clientes!B:D,3,) -> BANCO BOCOM BBM S/A | P59: =_xlfn.XLOOKUP(K59,#REF!,#REF!,0,0,1) -> #REF!
A60: =CONCATENATE($J$1,J60,$I$3,M60,$I$3,L60,$I$1,K60,$I$2) -> DESPESA DE REPRESENTAÇÃO - 30 CANECAS DE BRINDE PARA O RIO OPEN 2026-TRADER-JOÃO GROSSO (AGENDA 39003) | B60: 46023 | C60: 817991 | D60: RICARDO FERREIRA DA COSTA | E60: -74.485714 | F60: EVENTO | G60: 45988 | H60: 14498 | J60: 30 CANECAS DE BRINDE PARA O RIO OPEN 2026 | K60: AGENDA 39003 | L60: JOÃO GROSSO | M60: TRADER | N60: =VLOOKUP(H60,Clientes!B:D,3,) -> BANCO BOCOM BBM S/A | P60: =_xlfn.XLOOKUP(K60,#REF!,#REF!,0,0,1) -> #REF!
A61: =CONCATENATE($J$1,J61,$I$3,M61,$I$3,L61,$I$1,K61,$I$2) -> DESPESA DE REPRESENTAÇÃO - 30 CANECAS DE BRINDE PARA O RIO OPEN 2026-TRADER-JOAO BESSA (AGENDA 39003) | B61: 46023 | C61: 817991 | D61: RAFAEL TENORIO CAVALCANTI | E61: -74.485714 | F61: EVENTO | G61: 45988 | H61: 14416 | J61: 30 CANECAS DE BRINDE PARA O RIO OPEN 2026 | K61: AGENDA 39003 | L61: JOAO BESSA | M61: TRADER | N61: =VLOOKUP(H61,Clientes!B:D,3,) -> BANCO JP MORGAN S/A | P61: =_xlfn.XLOOKUP(K61,#REF!,#REF!,0,0,1) -> #REF!
A62: =CONCATENATE($J$1,J62,$I$3,M62,$I$3,L62,$I$1,K62,$I$2) -> DESPESA DE REPRESENTAÇÃO - 30 CANECAS DE BRINDE PARA O RIO OPEN 2026--NAMORADA DO JOAO BESSA (AGENDA 39003) | B62: 46023 | C62: 817991 | D62: RAFAEL TENORIO CAVALCANTI | E62: -74.485714 | F62: EVENTO | G62: 45988 | H62: 14416 | J62: 30 CANECAS DE BRINDE PARA O RIO OPEN 2026 | K62: AGENDA 39003 | L62: NAMORADA DO JOAO BESSA | N62: =VLOOKUP(H62,Clientes!B:D,3,) -> BANCO JP MORGAN S/A | P62: =_xlfn.XLOOKUP(K62,#REF!,#REF!,0,0,1) -> #REF!
A63: =CONCATENATE($J$1,J63,$I$3,M63,$I$3,L63,$I$1,K63,$I$2) -> DESPESA DE REPRESENTAÇÃO - 30 CANECAS DE BRINDE PARA O RIO OPEN 2026-TRADER-FELIPE NOVAIS GARCIA (AGENDA 39003) | B63: 46023 | C63: 817991 | D63: ANTONIO AUGUSTO DAS CHAGAS CARVALHO | E63: -74.485714 | F63: EVENTO | G63: 45988 | H63: 80573 | J63: 30 CANECAS DE BRINDE PARA O RIO OPEN 2026 | K63: AGENDA 39003 | L63: FELIPE NOVAIS GARCIA | M63: TRADER | N63: =VLOOKUP(H63,Clientes!B:D,3,) -> BANCO C6 S/A | P63: =_xlfn.XLOOKUP(K63,#REF!,#REF!,0,0,1) -> #REF!
A64: =CONCATENATE($J$1,J64,$I$3,M64,$I$3,L64,$I$1,K64,$I$2) -> DESPESA DE REPRESENTAÇÃO - 30 CANECAS DE BRINDE PARA O RIO OPEN 2026-TRADER-MARCELO ORTEGA (AGENDA 39003) | B64: 46023 | C64: 817991 | D64: ANTONIO AUGUSTO DAS CHAGAS CARVALHO | E64: -74.485714 | F64: EVENTO | G64: 45988 | H64: 80573 | J64: 30 CANECAS DE BRINDE PARA O RIO OPEN 2026 | K64: AGENDA 39003 | L64: MARCELO ORTEGA | M64: TRADER | N64: =VLOOKUP(H64,Clientes!B:D,3,) -> BANCO C6 S/A | P64: =_xlfn.XLOOKUP(K64,#REF!,#REF!,0,0,1) -> #REF!
A65: =CONCATENATE($J$1,J65,$I$3,M65,$I$3,L65,$I$1,K65,$I$2) -> DESPESA DE REPRESENTAÇÃO - 30 CANECAS DE BRINDE PARA O RIO OPEN 2026-TRADER-LUCIANA GARCIA (AGENDA 39003) | B65: 46023 | C65: 817991 | D65: ANTONIO AUGUSTO DAS CHAGAS CARVALHO | E65: -74.485714 | F65: EVENTO | G65: 45988 | H65: 80573 | J65: 30 CANECAS DE BRINDE PARA O RIO OPEN 2026 | K65: AGENDA 39003 | L65: LUCIANA GARCIA | M65: TRADER | N65: =VLOOKUP(H65,Clientes!B:D,3,) -> BANCO C6 S/A | P65: =_xlfn.XLOOKUP(K65,#REF!,#REF!,0,0,1) -> #REF!
A66: =CONCATENATE($J$1,J66,$I$3,M66,$I$3,L66,$I$1,K66,$I$2) -> DESPESA DE REPRESENTAÇÃO - 30 CANECAS DE BRINDE PARA O RIO OPEN 2026-TRADER-DIEGO MONT - STAR SEGURADORA (AGENDA 39003) | B66: 46023 | C66: 817991 | D66: JUAREZ JOAQUIM DE LACERDA | E66: -74.485714 | F66: EVENTO | G66: 45988 | H66: 1170 | J66: 30 CANECAS DE BRINDE PARA O RIO OPEN 2026 | K66: AGENDA 39003 | L66: DIEGO MONT - STAR SEGURADORA | M66: TRADER | N66: =VLOOKUP(H66,Clientes!B:D,3,) -> BGC LIQUIDEZ DTVM LTDA | P66: =_xlfn.XLOOKUP(K66,#REF!,#REF!,0,0,1) -> #REF!
A67: =CONCATENATE($J$1,J67,$I$3,M67,$I$3,L67,$I$1,K67,$I$2) -> DESPESA DE REPRESENTAÇÃO - 30 CANECAS DE BRINDE PARA O RIO OPEN 2026--ESPOSA DO DIEGO MONT - STAR SEGURADORA (AGENDA 39003) | B67: 46023 | C67: 817991 | D67: JUAREZ JOAQUIM DE LACERDA | E67: -74.485714 | F67: EVENTO | G67: 45988 | H67: 1170 | J67: 30 CANECAS DE BRINDE PARA O RIO OPEN 2026 | K67: AGENDA 39003 | L67: ESPOSA DO DIEGO MONT - STAR SEGURADORA | N67: =VLOOKUP(H67,Clientes!B:D,3,) -> BGC LIQUIDEZ DTVM LTDA | P67: =_xlfn.XLOOKUP(K67,#REF!,#REF!,0,0,1) -> #REF!
A68: =CONCATENATE($J$1,J68,$I$3,M68,$I$3,L68,$I$1,K68,$I$2) -> DESPESA DE REPRESENTAÇÃO - 30 CANECAS DE BRINDE PARA O RIO OPEN 2026-TRADER-MARCOS DE CASTRO LOPEZ (AGENDA 39003) | B68: 46023 | C68: 817991 | D68: GUSTAVO D ELBOUX FERRIELLO | E68: -74.485714 | F68: EVENTO | G68: 45988 | H68: 12413 | J68: 30 CANECAS DE BRINDE PARA O RIO OPEN 2026 | K68: AGENDA 39003 | L68: MARCOS DE CASTRO LOPEZ | M68: TRADER | N68: =VLOOKUP(H68,Clientes!B:D,3,) -> KAPITALO INVESTIMENTOS LTDA | P68: =_xlfn.XLOOKUP(K68,#REF!,#REF!,0,0,1) -> #REF!
A69: =CONCATENATE($J$1,J69,$I$3,M69,$I$3,L69,$I$1,K69,$I$2) -> DESPESA DE REPRESENTAÇÃO - 30 CANECAS DE BRINDE PARA O RIO OPEN 2026--ESPOSA DO MARCOS DE CASTRO LOPEZ (AGENDA 39003) | B69: 46023 | C69: 817991 | D69: GUSTAVO D ELBOUX FERRIELLO | E69: -74.485714 | F69: EVENTO | G69: 45988 | H69: 12413 | J69: 30 CANECAS DE BRINDE PARA O RIO OPEN 2026 | K69: AGENDA 39003 | L69: ESPOSA DO MARCOS DE CASTRO LOPEZ | N69: =VLOOKUP(H69,Clientes!B:D,3,) -> KAPITALO INVESTIMENTOS LTDA | P69: =_xlfn.XLOOKUP(K69,#REF!,#REF!,0,0,1) -> #REF!
A70: =CONCATENATE($J$1,J70,$I$3,M70,$I$3,L70,$I$1,K70,$I$2) -> DESPESA DE REPRESENTAÇÃO - 30 CANECAS DE BRINDE PARA O RIO OPEN 2026--FILHO DO MARCOS DE CASTRO LOPEZ (AGENDA 39003) | B70: 46023 | C70: 817991 | D70: GUSTAVO D ELBOUX FERRIELLO | E70: -74.485714 | F70: EVENTO | G70: 45988 | H70: 12413 | J70: 30 CANECAS DE BRINDE PARA O RIO OPEN 2026 | K70: AGENDA 39003 | L70: FILHO DO MARCOS DE CASTRO LOPEZ | N70: =VLOOKUP(H70,Clientes!B:D,3,) -> KAPITALO INVESTIMENTOS LTDA | P70: =_xlfn.XLOOKUP(K70,#REF!,#REF!,0,0,1) -> #REF!
A71: =CONCATENATE($J$1,J71,$I$3,M71,$I$3,L71,$I$1,K71,$I$2) -> DESPESA DE REPRESENTAÇÃO - 30 CANECAS DE BRINDE PARA O RIO OPEN 2026-TRADER-BRUNO PAULO (AGENDA 39003) | B71: 46023 | C71: 817991 | D71: CESAR MARIANO SCARAMBONE MENEZES | E71: -74.485714 | F71: EVENTO | G71: 45988 | H71: 83063 | J71: 30 CANECAS DE BRINDE PARA O RIO OPEN 2026 | K71: AGENDA 39003 | L71: BRUNO PAULO | M71: TRADER | N71: =VLOOKUP(H71,Clientes!B:D,3,) -> SCHONFELD STRATEGIC ADVISORS BRAZIL LTDA. | P71: =_xlfn.XLOOKUP(K71,#REF!,#REF!,0,0,1) -> #REF!
A72: =CONCATENATE($J$1,J72,$I$3,M72,$I$3,L72,$I$1,K72,$I$2) -> DESPESA DE REPRESENTAÇÃO - 30 CANECAS DE BRINDE PARA O RIO OPEN 2026--FILHA DO BRUNO PAULO (AGENDA 39003) | B72: 46023 | C72: 817991 | D72: CESAR MARIANO SCARAMBONE MENEZES | E72: -74.485714 | F72: EVENTO | G72: 45988 | H72: 83063 | J72: 30 CANECAS DE BRINDE PARA O RIO OPEN 2026 | K72: AGENDA 39003 | L72: FILHA DO BRUNO PAULO | N72: =VLOOKUP(H72,Clientes!B:D,3,) -> SCHONFELD STRATEGIC ADVISORS BRAZIL LTDA. | P72: =_xlfn.XLOOKUP(K72,#REF!,#REF!,0,0,1) -> #REF!
A73: =CONCATENATE($J$1,J73,$I$3,M73,$I$3,L73,$I$1,K73,$I$2) -> DESPESA DE REPRESENTAÇÃO - 30 CANECAS DE BRINDE PARA O RIO OPEN 2026-TRADER-ANDRE LOBATO PINHEIRO (AGENDA 39003) | B73: 46023 | C73: 817991 | D73: ALEXANDRE DA COSTA SOARES | E73: -74.485714 | F73: EVENTO | G73: 45988 | H73: 15501 | J73: 30 CANECAS DE BRINDE PARA O RIO OPEN 2026 | K73: AGENDA 39003 | L73: ANDRE LOBATO PINHEIRO | M73: TRADER | N73: =VLOOKUP(H73,Clientes!B:D,3,) -> BANCO BTG PACTUAL S/A | P73: =_xlfn.XLOOKUP(K73,#REF!,#REF!,0,0,1) -> #REF!
A74: =CONCATENATE($J$1,J74,$I$3,M74,$I$3,L74,$I$1,K74,$I$2) -> DESPESA DE REPRESENTAÇÃO - 30 CANECAS DE BRINDE PARA O RIO OPEN 2026--ESPOSA DO ANDRE LOBATO PINHEIRO (AGENDA 39003) | B74: 46023 | C74: 817991 | D74: ALEXANDRE DA COSTA SOARES | E74: -74.485714 | F74: EVENTO | G74: 45988 | H74: 15501 | J74: 30 CANECAS DE BRINDE PARA O RIO OPEN 2026 | K74: AGENDA 39003 | L74: ESPOSA DO ANDRE LOBATO PINHEIRO | N74: =VLOOKUP(H74,Clientes!B:D,3,) -> BANCO BTG PACTUAL S/A | P74: =_xlfn.XLOOKUP(K74,#REF!,#REF!,0,0,1) -> #REF!
A75: =CONCATENATE($J$1,J75,$I$3,M75,$I$3,L75,$I$1,K75,$I$2) -> DESPESA DE REPRESENTAÇÃO - 30 CANECAS DE BRINDE PARA O RIO OPEN 2026-TRADER-HENRIQUE DE LA ROCQUE (AGENDA 39003) | B75: 46023 | C75: 817991 | D75: JOSE MAURICIO GOMES TEIXEIRA | E75: -74.485714 | F75: EVENTO | G75: 45988 | H75: 125119 | J75: 30 CANECAS DE BRINDE PARA O RIO OPEN 2026 | K75: AGENDA 39003 | L75: HENRIQUE DE LA ROCQUE | M75: TRADER | N75: =VLOOKUP(H75,Clientes!B:D,3,) -> IRB ASSET MANAGEMENT S.A | P75: =_xlfn.XLOOKUP(K75,#REF!,#REF!,0,0,1) -> #REF!
A76: =CONCATENATE($J$1,J76,$I$3,M76,$I$3,L76,$I$1,K76,$I$2) -> DESPESA DE REPRESENTAÇÃO - 30 CANECAS DE BRINDE PARA O RIO OPEN 2026-TRADER-MARCOS DE CASTRO LOPEZ (AGENDA 39003) | B76: 46023 | C76: 817991 | D76: GUSTAVO D ELBOUX FERRIELLO | E76: -74.485714 | F76: EVENTO | G76: 45988 | H76: 12413 | J76: 30 CANECAS DE BRINDE PARA O RIO OPEN 2026 | K76: AGENDA 39003 | L76: MARCOS DE CASTRO LOPEZ | M76: TRADER | N76: =VLOOKUP(H76,Clientes!B:D,3,) -> KAPITALO INVESTIMENTOS LTDA | P76: =_xlfn.XLOOKUP(K76,#REF!,#REF!,0,0,1) -> #REF!
A77: =CONCATENATE($J$1,J77,$I$3,M77,$I$3,L77,$I$1,K77,$I$2) -> DESPESA DE REPRESENTAÇÃO - 30 CANECAS DE BRINDE PARA O RIO OPEN 2026--ESPOSA DO MARCOS DE CASTRO LOPEZ (AGENDA 39003) | B77: 46023 | C77: 817991 | D77: GUSTAVO D ELBOUX FERRIELLO | E77: -74.485714 | F77: EVENTO | G77: 45988 | H77: 12413 | J77: 30 CANECAS DE BRINDE PARA O RIO OPEN 2026 | K77: AGENDA 39003 | L77: ESPOSA DO MARCOS DE CASTRO LOPEZ | N77: =VLOOKUP(H77,Clientes!B:D,3,) -> KAPITALO INVESTIMENTOS LTDA | P77: =_xlfn.XLOOKUP(K77,#REF!,#REF!,0,0,1) -> #REF!
A78: =CONCATENATE($J$1,J78,$I$3,M78,$I$3,L78,$I$1,K78,$I$2) -> DESPESA DE REPRESENTAÇÃO - 30 CANECAS DE BRINDE PARA O RIO OPEN 2026-TRADER-FELIPE SANTANA DA SILVEIRA (AGENDA 39003) | B78: 46023 | C78: 817991 | D78: ANTÔNIO MARTINS NETO | E78: -74.485714 | F78: EVENTO | G78: 45988 | H78: 80958 | J78: 30 CANECAS DE BRINDE PARA O RIO OPEN 2026 | K78: AGENDA 39003 | L78: FELIPE SANTANA DA SILVEIRA | M78: TRADER | N78: =VLOOKUP(H78,Clientes!B:D,3,) -> ITAU UNIBANCO ASSET - OPTIMUS | P78: =_xlfn.XLOOKUP(K78,#REF!,#REF!,0,0,1) -> #REF!
A79: =CONCATENATE($J$1,J79,$I$3,M79,$I$3,L79,$I$1,K79,$I$2) -> DESPESA DE REPRESENTAÇÃO - 30 CANECAS DE BRINDE PARA O RIO OPEN 2026--ESPOSA DO FELIPE SANTANA DA SILVEIRA (AGENDA 39003) | B79: 46023 | C79: 817991 | D79: ANTÔNIO MARTINS NETO | E79: -74.485714 | F79: EVENTO | G79: 45988 | H79: 80958 | J79: 30 CANECAS DE BRINDE PARA O RIO OPEN 2026 | K79: AGENDA 39003 | L79: ESPOSA DO FELIPE SANTANA DA SILVEIRA | N79: =VLOOKUP(H79,Clientes!B:D,3,) -> ITAU UNIBANCO ASSET - OPTIMUS | P79: =_xlfn.XLOOKUP(K79,#REF!,#REF!,0,0,1) -> #REF!
A80: =CONCATENATE($J$1,J80,$I$3,M80,$I$3,L80,$I$1,K80,$I$2) -> DESPESA DE REPRESENTAÇÃO - 30 CANECAS DE BRINDE PARA O RIO OPEN 2026-TRADER-GUSTAVO MORAIS SILVA (AGENDA 39003) | B80: 46023 | C80: 817991 | D80: ENRICO BORTPLUZO CASSIANO | E80: -74.485714 | F80: EVENTO | G80: 45988 | H80: 79372 | J80: 30 CANECAS DE BRINDE PARA O RIO OPEN 2026 | K80: AGENDA 39003 | L80: GUSTAVO MORAIS SILVA | M80: TRADER | N80: =VLOOKUP(H80,Clientes!B:D,3,) -> ICATU VANGUARDA GESTAO DE RECURSOS LTDA | P80: =_xlfn.XLOOKUP(K80,#REF!,#REF!,0,0,1) -> #REF!
A81: =CONCATENATE($J$1,J81,$I$3,M81,$I$3,L81,$I$1,K81,$I$2) -> DESPESA DE REPRESENTAÇÃO - 30 CANECAS DE BRINDE PARA O RIO OPEN 2026-TRADER-FERNANDO SCARPA R LEITE (AGENDA 39003) | B81: 46023 | C81: 817991 | D81: FELIPE MEIRELLES RACCAH | E81: -74.485714 | F81: EVENTO | G81: 45988 | H81: 80375 | J81: 30 CANECAS DE BRINDE PARA O RIO OPEN 2026 | K81: AGENDA 39003 | L81: FERNANDO SCARPA R LEITE | M81: TRADER | N81: =VLOOKUP(H81,Clientes!B:D,3,) -> ITAU UNIBANCO S/A | P81: =_xlfn.XLOOKUP(K81,#REF!,#REF!,0,0,1) -> #REF!
A82: =CONCATENATE($J$1,J82,$I$3,M82,$I$3,L82,$I$1,K82,$I$2) -> DESPESA DE REPRESENTAÇÃO - 30 CANECAS DE BRINDE PARA O RIO OPEN 2026--FILHA DO FERNANDO SCARPA R LEITE (AGENDA 39003) | B82: 46023 | C82: 817991 | D82: FELIPE MEIRELLES RACCAH | E82: -74.485714 | F82: EVENTO | G82: 45988 | H82: 80375 | J82: 30 CANECAS DE BRINDE PARA O RIO OPEN 2026 | K82: AGENDA 39003 | L82: FILHA DO FERNANDO SCARPA R LEITE | N82: =VLOOKUP(H82,Clientes!B:D,3,) -> ITAU UNIBANCO S/A | P82: =_xlfn.XLOOKUP(K82,#REF!,#REF!,0,0,1) -> #REF!
A83: =CONCATENATE($J$1,J83,$I$3,M83,$I$3,L83,$I$1,K83,$I$2) -> DESPESA DE REPRESENTAÇÃO - 30 CANECAS DE BRINDE PARA O RIO OPEN 2026-TRADER-LUIZ ALBERTO BASQUEIRA (AGENDA 39003) | B83: 46023 | C83: 817991 | D83: LIQUIDEZ-OTHER | E83: -74.485714 | F83: EVENTO | G83: 45988 | H83: 79931 | J83: 30 CANECAS DE BRINDE PARA O RIO OPEN 2026 | K83: AGENDA 39003 | L83: LUIZ ALBERTO BASQUEIRA | M83: TRADER | N83: =VLOOKUP(H83,Clientes!B:D,3,) -> SPX GESTAO DE RECURSOS LTDA | P83: =_xlfn.XLOOKUP(K83,#REF!,#REF!,0,0,1) -> #REF!
A84: =CONCATENATE($J$1,J84,$I$3,M84,$I$3,L84,$I$1,K84,$I$2) -> DESPESA DE REPRESENTAÇÃO - 30 CANECAS DE BRINDE PARA O RIO OPEN 2026-TRADER-RODRIGO FERREIRA (AGENDA 39003) | B84: 46113 | C84: 817991 | D84: CLAUDIO DE SOUZA PACINI | E84: -74.485714 | F84: EVENTO | G84: 45988 | H84: 12413 | J84: 30 CANECAS DE BRINDE PARA O RIO OPEN 2026 | K84: AGENDA 39003 | L84: RODRIGO FERREIRA | M84: TRADER | N84: =VLOOKUP(H84,Clientes!B:D,3,) -> KAPITALO INVESTIMENTOS LTDA | P84: =_xlfn.XLOOKUP(K84,#REF!,#REF!,0,0,1) -> #REF!
A85: =CONCATENATE($J$1,J85,$I$3,M85,$I$3,L85,$I$1,K85,$I$2) -> DESPESA DE REPRESENTAÇÃO - 30 CANECAS DE BRINDE PARA O RIO OPEN 2026--ESPOSA RODRIGO FERREIRA (AGENDA 39003) | B85: 46113 | C85: 817991 | D85: CLAUDIO DE SOUZA PACINI | E85: -74.485714 | F85: EVENTO | G85: 45988 | H85: 12413 | J85: 30 CANECAS DE BRINDE PARA O RIO OPEN 2026 | K85: AGENDA 39003 | L85: ESPOSA RODRIGO FERREIRA | N85: =VLOOKUP(H85,Clientes!B:D,3,) -> KAPITALO INVESTIMENTOS LTDA | P85: =_xlfn.XLOOKUP(K85,#REF!,#REF!,0,0,1) -> #REF!
A86: =CONCATENATE($J$1,J86,$I$3,M86,$I$3,L86,$I$1,K86,$I$2) -> DESPESA DE REPRESENTAÇÃO - 30 CANECAS DE BRINDE PARA O RIO OPEN 2026--ESPOSA DO ANDRE ACCIOLY (AGENDA 39003) | B86: 46023 | C86: 817991 | D86: LIQUIDEZ-OTHER | E86: -74.485714 | F86: EVENTO | G86: 45988 | H86: 1170 | J86: 30 CANECAS DE BRINDE PARA O RIO OPEN 2026 | K86: AGENDA 39003 | L86: ESPOSA DO ANDRE ACCIOLY | N86: =VLOOKUP(H86,Clientes!B:D,3,) -> BGC LIQUIDEZ DTVM LTDA | P86: =_xlfn.XLOOKUP(K86,#REF!,#REF!,0,0,1) -> #REF!
A87: =CONCATENATE($J$1,J87,$I$3,M87,$I$3,L87,$I$1,K87,$I$2) -> DESPESA DE REPRESENTAÇÃO - 30 CANECAS DE BRINDE PARA O RIO OPEN 2026--FILHO DO ANDRE ACCIOLY (AGENDA 39003) | B87: 46023 | C87: 817991 | D87: LIQUIDEZ-OTHER | E87: -74.485714 | F87: EVENTO | G87: 45988 | H87: 1170 | J87: 30 CANECAS DE BRINDE PARA O RIO OPEN 2026 | K87: AGENDA 39003 | L87: FILHO DO ANDRE ACCIOLY | N87: =VLOOKUP(H87,Clientes!B:D,3,) -> BGC LIQUIDEZ DTVM LTDA | P87: =_xlfn.XLOOKUP(K87,#REF!,#REF!,0,0,1) -> #REF!
A88: =CONCATENATE($J$1,J88,$I$3,M88,$I$3,L88,$I$1,K88,$I$2) -> DESPESA DE REPRESENTAÇÃO - 30 CANECAS DE BRINDE PARA O RIO OPEN 2026-BROKER-JOSE MAURICIO GOMES TEIXEIRA (AGENDA 39003) | B88: 46023 | C88: 817991 | D88: JOSE MAURICIO GOMES TEIXEIRA | E88: -74.485714 | F88: EVENTO | G88: 45988 | H88: 1170 | J88: 30 CANECAS DE BRINDE PARA O RIO OPEN 2026 | K88: AGENDA 39003 | L88: JOSE MAURICIO GOMES TEIXEIRA | M88: BROKER | N88: =VLOOKUP(H88,Clientes!B:D,3,) -> BGC LIQUIDEZ DTVM LTDA | P88: =_xlfn.XLOOKUP(K88,#REF!,#REF!,0,0,1) -> #REF!
A89: =CONCATENATE($J$1,J89,$I$3,M89,$I$3,L89,$I$1,K89,$I$2) -> DESPESA DE REPRESENTAÇÃO - 30 CANECAS DE BRINDE PARA O RIO OPEN 2026--ESPOSA DO JOSE MAURICIO GOMES TEIXEIRA (AGENDA 39003) | B89: 46023 | C89: 817991 | D89: JOSE MAURICIO GOMES TEIXEIRA | E89: -74.485714 | F89: EVENTO | G89: 45988 | H89: 1170 | J89: 30 CANECAS DE BRINDE PARA O RIO OPEN 2026 | K89: AGENDA 39003 | L89: ESPOSA DO JOSE MAURICIO GOMES TEIXEIRA | N89: =VLOOKUP(H89,Clientes!B:D,3,) -> BGC LIQUIDEZ DTVM LTDA | P89: =_xlfn.XLOOKUP(K89,#REF!,#REF!,0,0,1) -> #REF!
A90: =CONCATENATE($J$1,J90,$I$3,M90,$I$3,L90,$I$1,K90,$I$2) -> DESPESA DE REPRESENTAÇÃO - 30 CANECAS DE BRINDE PARA O RIO OPEN 2026-TRADER-LUAN VALENTE (AGENDA 39003) | B90: 46023 | C90: 817991 | D90: JOSE MAURICIO GOMES TEIXEIRA | E90: -74.485714 | F90: EVENTO | G90: 45988 | H90: 80132 | J90: 30 CANECAS DE BRINDE PARA O RIO OPEN 2026 | K90: AGENDA 39003 | L90: LUAN VALENTE | M90: TRADER | N90: =VLOOKUP(H90,Clientes!B:D,3,) -> GLOBO COMUNICACAO E PARTICIPACOES S.A | P90: =_xlfn.XLOOKUP(K90,#REF!,#REF!,0,0,1) -> #REF!
A91: =CONCATENATE($J$1,J91,$I$3,M91,$I$3,L91,$I$1,K91,$I$2) -> DESPESA DE REPRESENTAÇÃO - INGRESSOS PARA O SHOW AC/DC -TRADER-MARCO SILVA (174313-3688EC) | B91: 46023 | C91: 817991 | D91: EDUARDO TADEU CARAPIA UTTEMBERG | E91: =-6566/4 -> -1641.5 | F91: EVENTO | G91: 46002 | H91: 80320 | J91: INGRESSOS PARA O SHOW AC/DC | K91: 174313-3688EC | L91: MARCO SILVA | M91: TRADER | N91: =VLOOKUP(H91,Clientes!B:D,3,) -> BANCO DA CHINA BRASIL S/A | P91: =_xlfn.XLOOKUP(K91,#REF!,#REF!,0,0,1) -> #REF!
A92: =CONCATENATE($J$1,J92,$I$3,M92,$I$3,L92,$I$1,K92,$I$2) -> DESPESA DE REPRESENTAÇÃO - INGRESSOS PARA O SHOW AC/DC -TRADER-GABRIEL MARTONI (174313-3688EC) | B92: 46023 | C92: 817991 | D92: EDUARDO TADEU CARAPIA UTTEMBERG | E92: =-6566/4 -> -1641.5 | F92: EVENTO | G92: 46002 | H92: 80320 | J92: INGRESSOS PARA O SHOW AC/DC | K92: 174313-3688EC | L92: GABRIEL MARTONI | M92: TRADER | N92: =VLOOKUP(H92,Clientes!B:D,3,) -> BANCO DA CHINA BRASIL S/A | P92: =_xlfn.XLOOKUP(K92,#REF!,#REF!,0,0,1) -> #REF!
A93: =CONCATENATE($J$1,J93,$I$3,M93,$I$3,L93,$I$1,K93,$I$2) -> DESPESA DE REPRESENTAÇÃO - INGRESSOS PARA O SHOW AC/DC -TRADER-RICARDO TEIXEIRA (174313-3688EC) | B93: 46023 | C93: 817991 | D93: ANTONIO AUGUSTO DAS CHAGAS CARVALHO | E93: =-6566/4 -> -1641.5 | F93: EVENTO | G93: 46002 | H93: 15501 | J93: INGRESSOS PARA O SHOW AC/DC | K93: 174313-3688EC | L93: RICARDO TEIXEIRA | M93: TRADER | N93: =VLOOKUP(H93,Clientes!B:D,3,) -> BANCO BTG PACTUAL S/A | P93: =_xlfn.XLOOKUP(K93,#REF!,#REF!,0,0,1) -> #REF!
A94: =CONCATENATE($J$1,J94,$I$3,M94,$I$3,L94,$I$1,K94,$I$2) -> DESPESA DE REPRESENTAÇÃO - INGRESSOS PARA O SHOW AC/DC -TRADER-MIGUEL TEIXEIRA (174313-3688EC) | B94: 46023 | C94: 817991 | D94: ANTONIO AUGUSTO DAS CHAGAS CARVALHO | E94: =-6566/4 -> -1641.5 | F94: EVENTO | G94: 46002 | H94: 15501 | J94: INGRESSOS PARA O SHOW AC/DC | K94: 174313-3688EC | L94: MIGUEL TEIXEIRA | M94: TRADER | N94: =VLOOKUP(H94,Clientes!B:D,3,) -> BANCO BTG PACTUAL S/A | P94: =_xlfn.XLOOKUP(K94,#REF!,#REF!,0,0,1) -> #REF!
A95: =CONCATENATE($J$1,J95,$I$3,M95,$I$3,L95,$I$1,K95,$I$2) -> DESPESA DE REPRESENTAÇÃO - ALUGUEL FLAT -BROKER-CHRISTIANO MARCONDES DE BARROS LIMA (AGENDA 39567) | B95: 46023 | C95: 817991 | D95: CHRISTIANO MARCONDES DE BARROS LIMA | E95: -1287.1325 | F95: HOSPEDAGEM | G95: 46024 | H95: 1170 | J95: ALUGUEL FLAT | K95: AGENDA 39567 | L95: CHRISTIANO MARCONDES DE BARROS LIMA | M95: BROKER | N95: =VLOOKUP(H95,Clientes!B:D,3,) -> BGC LIQUIDEZ DTVM LTDA | P95: =_xlfn.XLOOKUP(K95,#REF!,#REF!,0,0,1) -> #REF!
A96: =CONCATENATE($J$1,J96,$I$3,M96,$I$3,L96,$I$1,K96,$I$2) -> DESPESA DE REPRESENTAÇÃO - ALUGUEL FLAT -BROKER-JOSE MAURICIO GOMES TEIXEIRA (AGENDA 39567) | B96: 46023 | C96: 817991 | D96: JOSE MAURICIO GOMES TEIXEIRA | E96: -1287.1325 | F96: HOSPEDAGEM | G96: 46024 | H96: 1170 | J96: ALUGUEL FLAT | K96: AGENDA 39567 | L96: JOSE MAURICIO GOMES TEIXEIRA | M96: BROKER | N96: =VLOOKUP(H96,Clientes!B:D,3,) -> BGC LIQUIDEZ DTVM LTDA | P96: =_xlfn.XLOOKUP(K96,#REF!,#REF!,0,0,1) -> #REF!
A97: =CONCATENATE($J$1,J97,$I$3,M97,$I$3,L97,$I$1,K97,$I$2) -> DESPESA DE REPRESENTAÇÃO - ALUGUEL FLAT -BROKER-LIQUIDEZ-OTHER (AGENDA 39567) | B97: 46023 | C97: 817991 | D97: LIQUIDEZ-OTHER | E97: -2574.265 | F97: HOSPEDAGEM | G97: 46024 | H97: 1170 | J97: ALUGUEL FLAT | K97: AGENDA 39567 | L97: LIQUIDEZ-OTHER | M97: BROKER | N97: =VLOOKUP(H97,Clientes!B:D,3,) -> BGC LIQUIDEZ DTVM LTDA | P97: =_xlfn.XLOOKUP(K97,#REF!,#REF!,0,0,1) -> #REF!
A98: =CONCATENATE($J$1,J98,$I$3,M98,$I$3,L98,$I$1,K98,$I$2) -> DESPESA DE REPRESENTAÇÃO - CONDOMINIO E IPTU - FLAT-BROKER-CHRISTIANO MARCONDES DE BARROS LIMA (AGENDA 39569) | B98: 46023 | C98: 817991 | D98: CHRISTIANO MARCONDES DE BARROS LIMA | E98: -788 | F98: HOSPEDAGEM | G98: 46024 | H98: 1170 | J98: CONDOMINIO E IPTU - FLAT | K98: AGENDA 39569 | L98: CHRISTIANO MARCONDES DE BARROS LIMA | M98: BROKER | N98: =VLOOKUP(H98,Clientes!B:D,3,) -> BGC LIQUIDEZ DTVM LTDA | P98: =_xlfn.XLOOKUP(K98,#REF!,#REF!,0,0,1) -> #REF!
A99: =CONCATENATE($J$1,J99,$I$3,M99,$I$3,L99,$I$1,K99,$I$2) -> DESPESA DE REPRESENTAÇÃO - CONDOMINIO E IPTU - FLAT-BROKER-JOSE MAURICIO GOMES TEIXEIRA (AGENDA 39569) | B99: 46023 | C99: 817991 | D99: JOSE MAURICIO GOMES TEIXEIRA | E99: -788 | F99: HOSPEDAGEM | G99: 46024 | H99: 1170 | J99: CONDOMINIO E IPTU - FLAT | K99: AGENDA 39569 | L99: JOSE MAURICIO GOMES TEIXEIRA | M99: BROKER | N99: =VLOOKUP(H99,Clientes!B:D,3,) -> BGC LIQUIDEZ DTVM LTDA | P99: =_xlfn.XLOOKUP(K99,#REF!,#REF!,0,0,1) -> #REF!
A100: =CONCATENATE($J$1,J100,$I$3,M100,$I$3,L100,$I$1,K100,$I$2) -> DESPESA DE REPRESENTAÇÃO - CONDOMINIO E IPTU - FLAT-BROKER-LIQUIDEZ-OTHER (AGENDA 39569) | B100: 46023 | C100: 817991 | D100: LIQUIDEZ-OTHER | E100: -1576 | F100: HOSPEDAGEM | G100: 46024 | H100: 1170 | J100: CONDOMINIO E IPTU - FLAT | K100: AGENDA 39569 | L100: LIQUIDEZ-OTHER | M100: BROKER | N100: =VLOOKUP(H100,Clientes!B:D,3,) -> BGC LIQUIDEZ DTVM LTDA | P100: =_xlfn.XLOOKUP(K100,#REF!,#REF!,0,0,1) -> #REF!
...

Sheet FEV
A1: HISTORICO | B1: DATA COMPETENCIA | C1: CONTA CONTABIL | D1: BROKER | E1: VALOR | F1: FORNECEDOR | G1: DATA LANCAMENTO | H1: CLIENTE | I1: ( | J1: DESPESA DE REPRESENTAÇÃO - | K1: CODIGO | L1: CONVIDADO | M1: CARGO DO CONVIDADO | N1: RAZÃO SOCIAL
A2: =CONCATENATE($J$1,J2,$I$3,M2,$I$3,L2,$I$1,K2,$I$2) -> DESPESA DE REPRESENTAÇÃO - 4/4 PARCELA DO BOX DO RIO OPEN 2026--ESPOSA DO ANDRE ACCIOLY (AGENDA 38502) | B2: 46054 | C2: 817991 | D2: LIQUIDEZ-OTHER | E2: -3100 | F2: EVENTO | G2: 46058 | H2: 1170 | I2: ) | J2: 4/4 PARCELA DO BOX DO RIO OPEN 2026 | K2: AGENDA 38502 | L2: ESPOSA DO ANDRE ACCIOLY | N2: =VLOOKUP(H2,Clientes!B:D,3,) -> BGC LIQUIDEZ DTVM LTDA
A3: =CONCATENATE($J$1,J3,$I$3,M3,$I$3,L3,$I$1,K3,$I$2) -> DESPESA DE REPRESENTAÇÃO - 4/4 PARCELA DO BOX DO RIO OPEN 2026--FILHO DO ANDRE ACCIOLY (AGENDA 38502) | B3: 46054 | C3: 817991 | D3: LIQUIDEZ-OTHER | E3: -3100 | F3: EVENTO | G3: 46058 | H3: 1170 | I3: - | J3: 4/4 PARCELA DO BOX DO RIO OPEN 2026 | K3: AGENDA 38502 | L3: FILHO DO ANDRE ACCIOLY | N3: =VLOOKUP(H3,Clientes!B:D,3,) -> BGC LIQUIDEZ DTVM LTDA
A4: =CONCATENATE($J$1,J4,$I$3,M4,$I$3,L4,$I$1,K4,$I$2) -> DESPESA DE REPRESENTAÇÃO - 4/4 PARCELA DO BOX DO RIO OPEN 2026-BROKER-JOSE MAURICIO GOMES TEIXEIRA (AGENDA 38502) | B4: 46054 | C4: 817991 | D4: JOSE MAURICIO GOMES TEIXEIRA | E4: -3100 | F4: EVENTO | G4: 46058 | H4: 1170 | J4: 4/4 PARCELA DO BOX DO RIO OPEN 2026 | K4: AGENDA 38502 | L4: JOSE MAURICIO GOMES TEIXEIRA | M4: BROKER | N4: =VLOOKUP(H4,Clientes!B:D,3,) -> BGC LIQUIDEZ DTVM LTDA
A5: =CONCATENATE($J$1,J5,$I$3,M5,$I$3,L5,$I$1,K5,$I$2) -> DESPESA DE REPRESENTAÇÃO - 4/4 PARCELA DO BOX DO RIO OPEN 2026--ESPOSA DO JOSE MAURICIO GOMES TEIXEIRA (AGENDA 38502) | B5: 46054 | C5: 817991 | D5: JOSE MAURICIO GOMES TEIXEIRA | E5: -3100 | F5: EVENTO | G5: 46058 | H5: 1170 | J5: 4/4 PARCELA DO BOX DO RIO OPEN 2026 | K5: AGENDA 38502 | L5: ESPOSA DO JOSE MAURICIO GOMES TEIXEIRA | N5: =VLOOKUP(H5,Clientes!B:D,3,) -> BGC LIQUIDEZ DTVM LTDA
A6: =CONCATENATE($J$1,J6,$I$3,M6,$I$3,L6,$I$1,K6,$I$2) -> DESPESA DE REPRESENTAÇÃO - 4/4 PARCELA DO BOX DO RIO OPEN 2026-TRADER-LUAN VALENTE (AGENDA 38502) | B6: 46054 | C6: 817991 | D6: JOSE MAURICIO GOMES TEIXEIRA | E6: -3100 | F6: EVENTO | G6: 46058 | H6: 80132 | J6: 4/4 PARCELA DO BOX DO RIO OPEN 2026 | K6: AGENDA 38502 | L6: LUAN VALENTE | M6: TRADER | N6: =VLOOKUP(H6,Clientes!B:D,3,) -> GLOBO COMUNICACAO E PARTICIPACOES S.A
A7: =CONCATENATE($J$1,J7,$I$3,M7,$I$3,L7,$I$1,K7,$I$2) -> DESPESA DE REPRESENTAÇÃO - ALMOÇO -TRADER-RAFAEL PERES NABESHIMA (102527-3688FR) | B7: 46054 | C7: 817991 | D7: FELIPE MEIRELLES RACCAH | E7: -943.66 | F7: ALMOÇO | G7: 46058 | H7: 80375 | J7: ALMOÇO | K7: 102527-3688FR | L7: RAFAEL PERES NABESHIMA | M7: TRADER | N7: =VLOOKUP(H7,Clientes!B:D,3,) -> ITAU UNIBANCO S/A
A8: =CONCATENATE($J$1,J8,$I$3,M8,$I$3,L8,$I$1,K8,$I$2) -> DESPESA DE REPRESENTAÇÃO - HAPPY HOUR-TRADER-RODRIGO SANTANA FERREIRA (103534-3688FR) | B8: 46054 | C8: 817991 | D8: FELIPE MEIRELLES RACCAH | E8: -1554.88 | F8: EVENTO | G8: 46058 | H8: 80005 | J8: HAPPY HOUR | K8: 103534-3688FR | L8: RODRIGO SANTANA FERREIRA | M8: TRADER | N8: =VLOOKUP(H8,Clientes!B:D,3,) -> DEUTSCHE BANK S/A
A9: =CONCATENATE($J$1,J9,$I$3,M9,$I$3,L9,$I$1,K9,$I$2) -> DESPESA DE REPRESENTAÇÃO - HAPPY HOUR-TRADER-HENRIQUE TEIXEIRA CASTAGNET (103728-3688AA) | B9: 46054 | C9: 817991 | D9: ANTONIO AGIZ FILHO | E9: -714 | F9: EVENTO | G9: 46058 | H9: 83577 | J9: HAPPY HOUR | K9: 103728-3688AA | L9: HENRIQUE TEIXEIRA CASTAGNET | M9: TRADER | N9: =VLOOKUP(H9,Clientes!B:D,3,) -> BANCO MIZUHO DO BRASIL S/A
A10: =CONCATENATE($J$1,J10,$I$3,M10,$I$3,L10,$I$1,K10,$I$2) -> DESPESA DE REPRESENTAÇÃO - HAPPY HOUR-TRADER-MARCELO SCHOLZ ISSA (103235-3688AA) | B10: 46054 | C10: 817991 | D10: ANTONIO AGIZ FILHO | E10: -406 | F10: EVENTO | G10: 46058 | H10: 81259 | J10: HAPPY HOUR | K10: 103235-3688AA | L10: MARCELO SCHOLZ ISSA | M10: TRADER | N10: =VLOOKUP(H10,Clientes!B:D,3,) -> GOLDMAN SACHS DO BRASIL BANCO MULTIPLO S/A
A11: =CONCATENATE($J$1,J11,$I$3,M11,$I$3,L11,$I$1,K11,$I$2) -> DESPESA DE REPRESENTAÇÃO - ALMOÇO -TRADER-DANILO BASTOS GALVÃO (162755-3688BG) | B11: 46054 | C11: 817991 | D11: JOSE MAURICIO GOMES TEIXEIRA | E11: -1197.8 | F11: ALMOÇO | G11: 46058 | H11: 12402 | J11: ALMOÇO | K11: 162755-3688BG | L11: DANILO BASTOS GALVÃO | M11: TRADER | N11: =VLOOKUP(H11,Clientes!B:D,3,) -> TRUXT INVESTIMENTOS LTDA
A12: =CONCATENATE($J$1,J12,$I$3,M12,$I$3,L12,$I$1,K12,$I$2) -> DESPESA DE REPRESENTAÇÃO - ALMOÇO -TRADER-BENY (140730-3688RP) | B12: 46054 | C12: 817991 | D12: RODRIGO PENTAGNA | E12: -449 | F12: ALMOÇO | G12: 46058 | H12: 81319 | J12: ALMOÇO | K12: 140730-3688RP | L12: BENY | M12: TRADER | N12: =VLOOKUP(H12,Clientes!B:D,3,) -> PRAGMA GESTAO DE PATRIMONIO LTDA
A13: =CONCATENATE($J$1,J13,$I$3,M13,$I$3,L13,$I$1,K13,$I$2) -> DESPESA DE REPRESENTAÇÃO - ALMOÇO -TRADER-LEONARDO AKIRA IZUKA (174940-3688MN) | B13: 46054 | C13: 817991 | D13: CHRISTIANO MARCONDES DE BARROS LIMA | E13: -661.84 | F13: ALMOÇO | G13: 46058 | H13: 82053 | J13: ALMOÇO | K13: 174940-3688MN | L13: LEONARDO AKIRA IZUKA | M13: TRADER | N13: =VLOOKUP(H13,Clientes!B:D,3,) -> ITAU UNIBANCO ASSET - LEGEND
A14: =CONCATENATE($J$1,J14,$I$3,M14,$I$3,L14,$I$1,K14,$I$2) -> DESPESA DE REPRESENTAÇÃO - HAPPY HOUR-TRADER-EDUARDO ROSSI MELLO NOGUEIRA (180639-3688MN) | B14: 46054 | C14: 817991 | D14: CHRISTIANO MARCONDES DE BARROS LIMA | E14: -496.16 | F14: EVENTO | G14: 46058 | H14: 81344 | J14: HAPPY HOUR | K14: 180639-3688MN | L14: EDUARDO ROSSI MELLO NOGUEIRA | M14: TRADER | N14: =VLOOKUP(H14,Clientes!B:D,3,) -> TENAX CAPITAL LTDA
A15: =CONCATENATE($J$1,J15,$I$3,M15,$I$3,L15,$I$1,K15,$I$2) -> DESPESA DE REPRESENTAÇÃO - ALMOÇO -TRADER-LUAN DE AGUIAR CORREIA (154918-3688JT) | B15: 46054 | C15: 817991 | D15: JOSE MAURICIO GOMES TEIXEIRA | E15: -756 | F15: ALMOÇO | G15: 46065 | H15: 12416 | J15: ALMOÇO | K15: 154918-3688JT | L15: LUAN DE AGUIAR CORREIA | M15: TRADER | N15: =VLOOKUP(H15,Clientes!B:D,3,) -> MONGERAL AEGON INVESTIMENTOS LTDA
A16: =CONCATENATE($J$1,J16,$I$3,M16,$I$3,L16,$I$1,K16,$I$2) -> DESPESA DE REPRESENTAÇÃO - JANTAR DE COMEMORAÇÃO DA CONQUISTA NA PERMANENCIA DE DEALER-BROKER-BGC SEGUNDA VOLTA (141905-3688RR) | B16: 46054 | C16: 817991 | D16: BGC SEGUNDA VOLTA | E16: -6153.41 | F16: JANTAR | G16: 46065 | H16: 1170 | J16: JANTAR DE COMEMORAÇÃO DA CONQUISTA NA PERMANENCIA DE DEALER | K16: 141905-3688RR | L16: BGC SEGUNDA VOLTA | M16: BROKER | N16: =VLOOKUP(H16,Clientes!B:D,3,) -> BGC LIQUIDEZ DTVM LTDA
A17: =CONCATENATE($J$1,J17,$I$3,M17,$I$3,L17,$I$1,K17,$I$2) -> DESPESA DE REPRESENTAÇÃO - TAXI-BROKER-FREDERICO PADILHA (105319-3688FP) | B17: 46054 | C17: 817991 | D17: CHRISTIANO MARCONDES DE BARROS LIMA | E17: -60 | F17: LOCOMOÇÃO | G17: 46065 | H17: 1170 | J17: TAXI | K17: 105319-3688FP | L17: FREDERICO PADILHA | M17: BROKER | N17: =VLOOKUP(H17,Clientes!B:D,3,) -> BGC LIQUIDEZ DTVM LTDA
... A90: =CONCATENATE($J$1,J90,$I$3,M90,$I$3,L90,$I$1,K90,$I$2) -> DESPESA DE REPRESENTAÇÃO - TRANSPORTE EXECUTIVO MENSAL DE JANEIRO-CEO-ERMINIO OLIVI LUCCI (AGENDA 40273) | B90: 46054 | C90: 817991 | D90: ERMINIO OLIVI LUCCI | E90: -2070 | F90: LOCOMOÇÃO | G90: 46062 | H90: 1170 | J90: TRANSPORTE EXECUTIVO MENSAL DE JANEIRO | K90: AGENDA 40273 | L90: ERMINIO OLIVI LUCCI | M90: CEO | N90: =VLOOKUP(H90,Clientes!B:D,3,) -> BGC LIQUIDEZ DTVM LTDA
A91: =CONCATENATE($J$1,J91,$I$3,M91,$I$3,L91,$I$1,K91,$I$2) -> DESPESA DE REPRESENTAÇÃO - INGRESSOS PARA O SHOW AC/DC --ALEXANDRA BOKEL ESPOSA DO BERNARDO SALGADO (093659-3688AS) | B91: 46054 | C91: 817991 | D91: BRENO MELLO DOS SANTOS | E91: -1651 | F91: EVENTO | G91: 46065 | H91: 15781 | J91: INGRESSOS PARA O SHOW AC/DC | K91: 093659-3688AS | L91: ALEXANDRA BOKEL ESPOSA DO BERNARDO SALGADO | N91: =VLOOKUP(H91,Clientes!B:D,3,) -> BANCO SAFRA S/A
A92: =CONCATENATE($J$1,J92,$I$3,M92,$I$3,L92,$I$1,K92,$I$2) -> DESPESA DE REPRESENTAÇÃO - INGRESSOS PARA O SHOW AC/DC -TRADER-BERNARDO SALGADO (093659-3688AS) | B92: 46054 | C92: 817991 | D92: BRENO MELLO DOS SANTOS | E92: -1651 | F92: EVENTO | G92: 46065 | H92: 15781 | J92: INGRESSOS PARA O SHOW AC/DC | K92: 093659-3688AS | L92: BERNARDO SALGADO | M92: TRADER | N92: =VLOOKUP(H92,Clientes!B:D,3,) -> BANCO SAFRA S/A
A93: =CONCATENATE($J$1,J93,$I$3,M93,$I$3,L93,$I$1,K93,$I$2) -> DESPESA DE REPRESENTAÇÃO - INGRESSOS PARA O SHOW AC/DC -TRADER-FELIPE S UEDA RUSSO MARTINS (180117-3688FC) | B93: 46054 | C93: 817991 | D93: RICARDO FERREIRA DA COSTA | E93: -1641.74 | F93: EVENTO | G93: 46079 | H93: 80343 | J93: INGRESSOS PARA O SHOW AC/DC | K93: 180117-3688FC | L93: FELIPE S UEDA RUSSO MARTINS | M93: TRADER | N93: =VLOOKUP(H93,Clientes!B:D,3,) -> BANCO BS2 S/A
A94: =CONCATENATE($J$1,J94,$I$3,M94,$I$3,L94,$I$1,K94,$I$2) -> DESPESA DE REPRESENTAÇÃO - INGRESSOS PARA O SHOW AC/DC -TRADER-INGRID DE OLIVEIRA PINHEIRO (180117-3688FC) | B94: 46054 | C94: 817991 | D94: RICARDO FERREIRA DA COSTA | E94: -1641.74 | F94: EVENTO | G94: 46079 | H94: 80343 | J94: INGRESSOS PARA O SHOW AC/DC | K94: 180117-3688FC | L94: INGRID DE OLIVEIRA PINHEIRO | M94: TRADER | N94: =VLOOKUP(H94,Clientes!B:D,3,) -> BANCO BS2 S/A
A95: =CONCATENATE($J$1,J95,$I$3,M95,$I$3,L95,$I$1,K95,$I$2) -> DESPESA DE REPRESENTAÇÃO - SINAL CAFÉ DA MANHÃ COM CAIADO NO DIA 09/02 NO LOUP-SALES-JOSE ANTONIO DEZENE JUNIOR (AGENDA 40266) | B95: 46054 | C95: 817991 | D95: JOSE ANTONIO DEZENE JUNIOR | E95: -1299.5 | F95: CAFE DA MANHÃ | G95: 46059 | H95: 1170 | J95: SINAL CAFÉ DA MANHÃ COM CAIADO NO DIA 09/02 NO LOUP | K95: AGENDA 40266 | L95: JOSE ANTONIO DEZENE JUNIOR | M95: SALES | N95: =VLOOKUP(H95,Clientes!B:D,3,) -> BGC LIQUIDEZ DTVM LTDA
A96: =CONCATENATE($J$1,J96,$I$3,M96,$I$3,L96,$I$1,K96,$I$2) -> DESPESA DE REPRESENTAÇÃO - LIBERAÇÃO E RETIRADA DAS AMOSTRAS DE CAMISETA - KART -SALES-JOSE ANTONIO DEZENE JUNIOR (AGENDA 40263) | B96: 46054 | C96: 817991 | D96: JOSE ANTONIO DEZENE JUNIOR | E96: -89 | F96: EVENTO | G96: 46063 | H96: 1170 | J96: LIBERAÇÃO E RETIRADA DAS AMOSTRAS DE CAMISETA - KART | K96: AGENDA 40263 | L96: JOSE ANTONIO DEZENE JUNIOR | M96: SALES | N96: =VLOOKUP(H96,Clientes!B:D,3,) -> BGC LIQUIDEZ DTVM LTDA
A97: =CONCATENATE($J$1,J97,$I$3,M97,$I$3,L97,$I$1,K97,$I$2) -> DESPESA DE REPRESENTAÇÃO - DEVOLUÇÃO DO CARTÃO CORPORATIVO-CEO-ERMINIO OLIVI LUCCI (AGENDA 40421) | B97: 46054 | C97: 817991 | D97: ERMINIO OLIVI LUCCI | E97: 286.32 | F97: OUTROS | G97: 46066 | H97: 1170 | J97: DEVOLUÇÃO DO CARTÃO CORPORATIVO | K97: AGENDA 40421 | L97: ERMINIO OLIVI LUCCI | M97: CEO | N97: =VLOOKUP(H97,Clientes!B:D,3,) -> BGC LIQUIDEZ DTVM LTDA
A98: =CONCATENATE($J$1,J98,$I$3,M98,$I$3,L98,$I$1,K98,$I$2) -> DESPESA DE REPRESENTAÇÃO - DEVOLUÇÃO DOS INGRESSOS DO BOX DO RIO OPEN 2026-CEO-FILHO DO ERMINIO (AGENDA 40417) | B98: 46023 | C98: 817991 | D98: ERMINIO OLIVI LUCCI | E98: 868 | F98: EVENTO | G98: 46066 | H98: 1170 | J98: DEVOLUÇÃO DOS INGRESSOS DO BOX DO RIO OPEN 2026 | K98: AGENDA 40417 | L98: FILHO DO ERMINIO | M98: CEO | N98: =VLOOKUP(H98,Clientes!B:D,3,) -> BGC LIQUIDEZ DTVM LTDA | P98: =_xlfn.XLOOKUP(K98,#REF!,#REF!,0,0,1) -> #REF!
A99: =CONCATENATE($J$1,J99,$I$3,M99,$I$3,L99,$I$1,K99,$I$2) -> DESPESA DE REPRESENTAÇÃO - DEVOLUÇÃO DOS INGRESSOS DO BOX DO RIO OPEN 2026-CEO-AMIGO DO FILHO DO ERMINIO (AGENDA 40417) | B99: 46023 | C99: 817991 | D99: ERMINIO OLIVI LUCCI | E99: 868 | F99: EVENTO | G99: 46066 | H99: 1170 | J99: DEVOLUÇÃO DOS INGRESSOS DO BOX DO RIO OPEN 2026 | K99: AGENDA 40417 | L99: AMIGO DO FILHO DO ERMINIO | M99: CEO | N99: =VLOOKUP(H99,Clientes!B:D,3,) -> BGC LIQUIDEZ DTVM LTDA | P99: =_xlfn.XLOOKUP(K99,#REF!,#REF!,0,0,1) -> #REF!
A100: =CONCATENATE($J$1,J100,$I$3,M100,$I$3,L100,$I$1,K100,$I$2) -> DESPESA DE REPRESENTAÇÃO - DEVOLUÇÃO DA HOSPEDAGEM NO FAIRMONT NO RIO DE JANEIRO-CEO-ERMINIO OLIVI LUCCI (AGENDA 40341) | B100: 46054 | C100: 817991 | D100: ERMINIO OLIVI LUCCI | E100: =4664.4/2 -> 2332.2 | F100: HOSPEDAGEM | G100: 46063 | H100: 1170 | J100: DEVOLUÇÃO DA HOSPEDAGEM NO FAIRMONT NO RIO DE JANEIRO | K100: AGENDA 40341 | L100: ERMINIO OLIVI LUCCI | M100: CEO | N100: =VLOOKUP(H100,Clientes!B:D,3,) -> BGC LIQUIDEZ DTVM LTDA
A101: =CONCATENATE($J$1,J101,$I$3,M101,$I$3,L101,$I$1,K101,$I$2) -> DESPESA DE REPRESENTAÇÃO - REUNIÃO TRAUMANN & SCHONFELD-SALES-JOSE ANTONIO DEZENE JUNIOR (E-MAIL 06/03/2026) | B101: 46054 | C101: 817991 | D101: JOSE ANTONIO DEZENE JUNIOR | E101: -5500 | F101: EVENTO | G101: 46054 | H101: 1170 | J101: REUNIÃO TRAUMANN & SCHONFELD | K101: E-MAIL 06/03/2026 | L101: JOSE ANTONIO DEZENE JUNIOR | M101: SALES | N101: =VLOOKUP(H101,Clientes!B:D,3,) -> BGC LIQUIDEZ DTVM LTDA
A102: =CONCATENATE($J$1,J102,$I$3,M102,$I$3,L102,$I$1,K102,$I$2) -> DESPESA DE REPRESENTAÇÃO - FRETE DOCUMENTAÇÃO-ECONOMISTA-FELIPE DE SA TAVARES (E-MAIL 03/03/2026) | B102: 46054 | C102: 817991 | D102: FELIPE DE SA TAVARES | E102: -16.88 | F102: OUTROS | G102: 46065 | H102: 1170 | J102: FRETE DOCUMENTAÇÃO | K102: E-MAIL 03/03/2026 | L102: FELIPE DE SA TAVARES | M102: ECONOMISTA | N102: =VLOOKUP(H102,Clientes!B:D,3,) -> BGC LIQUIDEZ DTVM LTDA
A103: =CONCATENATE($J$1,J103,$I$3,M103,$I$3,L103,$I$1,K103,$I$2) -> DESPESA DE REPRESENTAÇÃO - FRETE DOCUMENTAÇÃO-ECONOMISTA-CARLOS THADEU DE FREITAS GOMES FILHO (E-MAIL 03/03/2026) | B103: 46054 | C103: 817991 | D103: CARLOS THADEU DE FREITAS GOMES FILHO | E103: -16.88 | F103: OUTROS | G103: 46065 | H103: 1170 | J103: FRETE DOCUMENTAÇÃO | K103: E-MAIL 03/03/2026 | L103: CARLOS THADEU DE FREITAS GOMES FILHO | M103: ECONOMISTA | N103: =VLOOKUP(H103,Clientes!B:D,3,) -> BGC LIQUIDEZ DTVM LTDA
A104: =CONCATENATE($J$1,J104,$I$3,M104,$I$3,L104,$I$1,K104,$I$2) -> DESPESA DE REPRESENTAÇÃO - UBER-BROKER-JUAREZ JOAQUIM DE LACERDA (E-MAIL 20/05/2026) | B104: 46054 | C104: 817991 | D104: JUAREZ JOAQUIM DE LACERDA | E104: -359.96 | F104: LOCOMOÇÃO | G104: 46072 | H104: 1170 | J104: UBER | K104: E-MAIL 20/05/2026 | L104: JUAREZ JOAQUIM DE LACERDA | M104: BROKER | N104: =VLOOKUP(H104,Clientes!B:D,3,) -> BGC LIQUIDEZ DTVM LTDA
A105: =CONCATENATE($J$1,J105,$I$3,M105,$I$3,L105,$I$1,K105,$I$2) -> DESPESA DE REPRESENTAÇÃO - UBER-SALES-MARCELLE DA SILVEIRA GIL CADILHE (E-MAIL 20/05/2026) | B105: 46054 | C105: 817991 | D105: JOSE ANTONIO DEZENE JUNIOR | E105: -678.86 | F105: LOCOMOÇÃO | G105: 46080 | H105: 1170 | J105: UBER | K105: E-MAIL 20/05/2026 | L105: MARCELLE DA SILVEIRA GIL CADILHE | M105: SALES | N105: =VLOOKUP(H105,Clientes!B:D,3,) -> BGC LIQUIDEZ DTVM LTDA
A106: =CONCATENATE($J$1,J106,$I$3,M106,$I$3,L106,$I$1,K106,$I$2) -> DESPESA DE REPRESENTAÇÃO - UBER-SALES-MELISSA LEITE FIGUEIREDO ROCHA (E-MAIL 20/05/2026) | B106: 46054 | C106: 817991 | D106: JOSE ANTONIO DEZENE JUNIOR | E106: -69.61 | F106: LOCOMOÇÃO | G106: 46076 | H106: 1170 | J106: UBER | K106: E-MAIL 20/05/2026 | L106: MELISSA LEITE FIGUEIREDO ROCHA | M106: SALES | N106: =VLOOKUP(H106,Clientes!B:D,3,) -> BGC LIQUIDEZ DTVM LTDA
A107: =CONCATENATE($J$1,J107,$I$3,M107,$I$3,L107,$I$1,K107,$I$2) -> DESPESA DE REPRESENTAÇÃO - PASSAGEM SÃO PAULO X RIO DE JANEIRO-CEO-ERMINIO OLIVI LUCCI (AGENDA 40469) | B107: 46054 | C107: 817991 | D107: ERMINIO OLIVI LUCCI | E107: -2579.47 | F107: LOCOMOÇÃO | G107: 46073 | H107: 1170 | J107: PASSAGEM SÃO PAULO X RIO DE JANEIRO | K107: AGENDA 40469 | L107: ERMINIO OLIVI LUCCI | M107: CEO | N107: =VLOOKUP(H107,Clientes!B:D,3,) -> BGC LIQUIDEZ DTVM LTDA
A108: =CONCATENATE($J$1,J108,$I$3,M108,$I$3,L108,$I$1,K108,$I$2) -> DESPESA DE REPRESENTAÇÃO - PASSAGEM BRASILIA X SÃO PAULO-CONSULTOR-RENAN REIS CRUVINEL (AGENDA 40469) | B108: 46054 | C108: 817991 | D108: RENAN REIS CRUVINEL | E108: -1695.81 | F108: LOCOMOÇÃO | G108: 46073 | H108: 1170 | J108: PASSAGEM BRASILIA X SÃO PAULO | K108: AGENDA 40469 | L108: RENAN REIS CRUVINEL | M108: CONSULTOR | N108: =VLOOKUP(H108,Clientes!B:D,3,) -> BGC LIQUIDEZ DTVM LTDA
A109: =CONCATENATE($J$1,J109,$I$3,M109,$I$3,L109,$I$1,K109,$I$2) -> DESPESA DE REPRESENTAÇÃO - ALUGUEL FLAT -BROKER-PAULO GUILHERME MENEZES FELIX (AGENDA 40247) | B109: 46054 | C109: 817991 | D109: PAULO GUILHERME MENEZES FELIX | E109: -4202 | F109: HOSPEDAGEM | G109: 46077 | H109: 1170 | J109: ALUGUEL FLAT | K109: AGENDA 40247 | L109: PAULO GUILHERME MENEZES FELIX | M109: BROKER | N109: =VLOOKUP(H109,Clientes!B:D,3,) -> BGC LIQUIDEZ DTVM LTDA

Sheet MAR
A1: HISTORICO | B1: DATA COMPETENCIA | C1: CONTA CONTABIL | D1: BROKER | E1: VALOR | F1: FORNECEDOR | G1: DATA LANCAMENTO | H1: CLIENTE | I1: ( | J1: DESPESA DE REPRESENTAÇÃO - | K1: CODIGO | L1: CONVIDADO | M1: CARGO DO CONVIDADO | N1: RAZÃO SOCIAL
A2: =CONCATENATE($J$1,J2,$I$3,M2,$I$3,L2,$I$1,K2,$I$2) -> DESPESA DE REPRESENTAÇÃO - HOSPEDAGEM INDIGO NYC FINANCIAL DISTRICT-BROKER-CLAUDIO DE SOUZA PACINI (AGENDA 40538) | B2: 46082 | C2: 817991 | D2: CLAUDIO DE SOUZA PACINI | E2: -1240 | F2: HOSPEDAGEM | G2: 46086 | H2: 1170 | I2: ) | J2: HOSPEDAGEM INDIGO NYC FINANCIAL DISTRICT | K2: AGENDA 40538 | L2: CLAUDIO DE SOUZA PACINI | M2: BROKER | N2: =VLOOKUP(H2,Clientes!B:D,3,) -> BGC LIQUIDEZ DTVM LTDA
A3: =CONCATENATE($J$1,J3,$I$3,M3,$I$3,L3,$I$1,K3,$I$2) -> DESPESA DE REPRESENTAÇÃO - HOSPEDAGEM RADISSON BLU SÃO PAULO -CONSULTORA -CLAUDIA TAVARES FERNANDES (AGENDA 40539) | B3: 46082 | C3: 817991 | D3: CLAUDIA TAVARES FERNANDES | E3: -1629.6 | F3: HOSPEDAGEM | G3: 46086 | H3: 1170 | I3: - | J3: HOSPEDAGEM RADISSON BLU SÃO PAULO | K3: AGENDA 40539 | L3: CLAUDIA TAVARES FERNANDES | M3: CONSULTORA | N3: =VLOOKUP(H3,Clientes!B:D,3,) -> BGC LIQUIDEZ DTVM LTDA
A4: =CONCATENATE($J$1,J4,$I$3,M4,$I$3,L4,$I$1,K4,$I$2) -> DESPESA DE REPRESENTAÇÃO - PASSAGEM GUARULHOS X NOVA YORK -CEO-ERMINIO OLIVI LUCCI (AGENDA 40595) | B4: 46082 | C4: 817991 | D4: ERMINIO OLIVI LUCCI | E4: -5746.98 | F4: LOCOMOÇÃO | G4: 46086 | H4: 1170 | J4: PASSAGEM GUARULHOS X NOVA YORK | K4: AGENDA 40595 | L4: ERMINIO OLIVI LUCCI | M4: CEO | N4: =VLOOKUP(H4,Clientes!B:D,3,) -> BGC LIQUIDEZ DTVM LTDA
A5: =CONCATENATE($J$1,J5,$I$3,M5,$I$3,L5,$I$1,K5,$I$2) -> DESPESA DE REPRESENTAÇÃO - 2/2 ALUGUEL - KART-SALES-JOSE ANTONIO DEZENE JUNIOR (AGENDA 40613) | B5: 46082 | C5: 817991 | D5: JOSE ANTONIO DEZENE JUNIOR | E5: -15950 | F5: EVENTO | G5: 46092 | H5: 1170 | J5: 2/2 ALUGUEL - KART | K5: AGENDA 40613 | L5: JOSE ANTONIO DEZENE JUNIOR | M5: SALES | N5: =VLOOKUP(H5,Clientes!B:D,3,) -> BGC LIQUIDEZ DTVM LTDA
A6: =CONCATENATE($J$1,J6,$I$3,M6,$I$3,L6,$I$1,K6,$I$2) -> DESPESA DE REPRESENTAÇÃO - ALMOÇO-TRADER-MAURO OKUMA LACERDA (120324-3688CM) | B6: 46082 | C6: 817991 | D6: CESAR MARIANO SCARAMBONE MENEZES | E6: -2670.19 | F6: ALMOÇO | G6: 46086 | H6: 12413 | J6: ALMOÇO | K6: 120324-3688CM | L6: MAURO OKUMA LACERDA | M6: TRADER | N6: =VLOOKUP(H6,Clientes!B:D,3,) -> KAPITALO INVESTIMENTOS LTDA
A7: =CONCATENATE($J$1,J7,$I$3,M7,$I$3,L7,$I$1,K7,$I$2) -> DESPESA DE REPRESENTAÇÃO - HAPPY HOUR COM NOMURA-TRADER -CHIRAG GARG (111847-3688RC) | B7: 46082 | C7: 817991 | D7: RAFAEL TENORIO CAVALCANTI | E7: -1258 | F7: EVENTO | G7: 46086 | H7: 1170 | J7: HAPPY HOUR COM NOMURA | K7: 111847-3688RC | L7: CHIRAG GARG | M7: TRADER | N7: =VLOOKUP(H7,Clientes!B:D,3,) -> BGC LIQUIDEZ DTVM LTDA
A8: =CONCATENATE($J$1,J8,$I$3,M8,$I$3,L8,$I$1,K8,$I$2) -> DESPESA DE REPRESENTAÇÃO - ALMOÇO-TRADER -RABINDER SIRA (110546-3688RC) | B8: 46082 | C8: 817991 | D8: RAFAEL TENORIO CAVALCANTI | E8: -1611 | F8: ALMOÇO | G8: 46086 | H8: 18658 | J8: ALMOÇO | K8: 110546-3688RC | L8: RABINDER SIRA | M8: TRADER | N8: =VLOOKUP(H8,Clientes!B:D,3,) -> SCOTIABANK BRASILS/A BANCO MULTIPLO(ANTIGO DRESDNER BANK BR)
A9: =CONCATENATE($J$1,J9,$I$3,M9,$I$3,L9,$I$1,K9,$I$2) -> DESPESA DE REPRESENTAÇÃO - JANTAR-TRADER -IGNACIO ALDUNATE (111451-3688RC) | B9: 46082 | C9: 817991 | D9: RAFAEL TENORIO CAVALCANTI | E9: -1712 | F9: JANTAR | G9: 46086 | H9: 441000 | J9: JANTAR | K9: 111451-3688RC | L9: IGNACIO ALDUNATE | M9: TRADER | N9: =VLOOKUP(H9,Clientes!B:D,3,) -> BANCO RABOBANK INTERNATIONAL BRASIL S/A
A10: =CONCATENATE($J$1,J10,$I$3,M10,$I$3,L10,$I$1,K10,$I$2) -> DESPESA DE REPRESENTAÇÃO - HOSPEDAGEM CLUB QUARTERS HOTEL NY-BROKER-RAFAEL TENORIO CAVALCANTI (AGENDA 40626) | B10: 46082 | C10: 817991 | D10: RAFAEL TENORIO CAVALCANTI | E10: -5865 | F10: HOSPEDAGEM | G10: 46086 | H10: 1170 | J10: HOSPEDAGEM CLUB QUARTERS HOTEL NY | K10: AGENDA 40626 | L10: RAFAEL TENORIO CAVALCANTI | M10: BROKER | N10: =VLOOKUP(H10,Clientes!B:D,3,) -> BGC LIQUIDEZ DTVM LTDA
A11: =CONCATENATE($J$1,J11,$I$3,M11,$I$3,L11,$I$1,K11,$I$2) -> DESPESA DE REPRESENTAÇÃO - JANTAR COM CLIENTE ING BANK-TRADER-EDUARDO CASTRO (112309-3688RC) | B11: 46082 | C11: 817991 | D11: RAFAEL TENORIO CAVALCANTI | E11: -2328 | F11: JANTAR | G11: 46086 | H11: 1170 | J11: JANTAR COM CLIENTE ING BANK | K11: 112309-3688RC | L11: EDUARDO CASTRO | M11: TRADER | N11: =VLOOKUP(H11,Clientes!B:D,3,) -> BGC LIQUIDEZ DTVM LTDA
A12: =CONCATENATE($J$1,J12,$I$3,M12,$I$3,L12,$I$1,K12,$I$2) -> DESPESA DE REPRESENTAÇÃO - ALMOÇO-TRADER-JOAO PEROLIN FREDERICO TRALLI (104821-3688FP) | B12: 46082 | C12: 817991 | D12: FABIO SOARES PFAENDER | E12: -900.49 | F12: ALMOÇO | G12: 46086 | H12: 16705 | J12: ALMOÇO | K12: 104821-3688FP | L12: JOAO PEROLIN FREDERICO TRALLI | M12: TRADER | N12: =VLOOKUP(H12,Clientes!B:D,3,) -> BANCO BRADESCO S/A
A13: =CONCATENATE($J$1,J13,$I$3,M13,$I$3,L13,$I$1,K13,$I$2) -> DESPESA DE REPRESENTAÇÃO - HAPPY HOUR-TRADER-RUBENS SHIN (114441-3688RC) | B13: 46082 | C13: 817991 | D13: RAFAEL TENORIO CAVALCANTI | E13: -5300 | F13: EVENTO | G13: 46086 | H13: 79978 | J13: HAPPY HOUR | K13: 114441-3688RC | L13: RUBENS SHIN | M13: TRADER | N13: =VLOOKUP(H13,Clientes!B:D,3,) -> CREDIT SUISSE (BRASIL) S/A CTVM
A14: =CONCATENATE($J$1,J14,$I$3,M14,$I$3,L14,$I$1,K14,$I$2) -> DESPESA DE REPRESENTAÇÃO - JANTAR-TRADER-LUCAS JOSA (100402-3688AF) | B14: 46082 | C14: 817991 | D14: CLAUDIO DE SOUZA PACINI | E14: -526 | F14: JANTAR | G14: 46086 | H14: 15501 | J14: JANTAR | K14: 100402-3688AF | L14: LUCAS JOSA | M14: TRADER | N14: =VLOOKUP(H14,Clientes!B:D,3,) -> BANCO BTG PACTUAL S/A
A15: =CONCATENATE($J$1,J15,$I$3,M15,$I$3,L15,$I$1,K15,$I$2) -> DESPESA DE REPRESENTAÇÃO - ALUGUEL FLAT -BROKER-CHRISTIANO MARCONDES DE BARROS LIMA (AGENDA 40667) | B15: 46082 | C15: 817991 | D15: CHRISTIANO MARCONDES DE BARROS LIMA | E15: -1337.0475 | F15: HOSPEDAGEM | G15: 46084 | H15: 1170 | J15: ALUGUEL FLAT | K15: AGENDA 40667 | L15: CHRISTIANO MARCONDES DE BARROS LIMA | M15: BROKER | N15: =VLOOKUP(H15,Clientes!B:D,3,) -> BGC LIQUIDEZ DTVM LTDA
... A163: =CONCATENATE($J$1,J163,$I$3,M163,$I$3,L163,$I$1,K163,$I$2) -> DESPESA DE REPRESENTAÇÃO - JANTAR COM RENAN SANTOS E KIM KATAGUIRI NO DIA 09/04 NO LOUP-SALES-JOSE ANTONIO DEZENE JUNIOR (AGENDA 41113) | B163: 46082 | C163: 817991 | D163: JOSE ANTONIO DEZENE JUNIOR | E163: -2147 | F163: JANTAR | G163: 46111 | H163: 1170 | J163: JANTAR COM RENAN SANTOS E KIM KATAGUIRI NO DIA 09/04 NO LOUP | K163: AGENDA 41113 | L163: JOSE ANTONIO DEZENE JUNIOR | M163: SALES | N163: =VLOOKUP(H163,Clientes!B:D,3,) -> BGC LIQUIDEZ DTVM LTDA
A164: =CONCATENATE($J$1,J164,$I$3,M164,$I$3,L164,$I$1,K164,$I$2) -> DESPESA DE REPRESENTAÇÃO - -- () | B164: 46082 | C164: 817991
A165: =CONCATENATE($J$1,J165,$I$3,M165,$I$3,L165,$I$1,K165,$I$2) -> DESPESA DE REPRESENTAÇÃO - -- () | B165: 46082 | C165: 817991
A166: =CONCATENATE($J$1,J166,$I$3,M166,$I$3,L166,$I$1,K166,$I$2) -> DESPESA DE REPRESENTAÇÃO - -- () | B166: 46082 | C166: 817991
A167: =CONCATENATE($J$1,J167,$I$3,M167,$I$3,L167,$I$1,K167,$I$2) -> DESPESA DE REPRESENTAÇÃO - -- () | B167: 46082 | C167: 817991

Sheet ABR
A1: HISTORICO | B1: DATA COMPETENCIA | C1: CONTA CONTABIL | D1: BROKER | E1: VALOR | F1: FORNECEDOR | G1: DATA LANCAMENTO | H1: CLIENTE | I1: ( | J1: DESPESA DE REPRESENTAÇÃO - | K1: CODIGO | L1: CONVIDADO | M1: CARGO DO CONVIDADO | N1: RAZÃO SOCIAL
A2: =CONCATENATE($J$1,J2,$I$3,M2,$I$3,L2,$I$1,K2,$I$2) -> DESPESA DE REPRESENTAÇÃO - COMPRA DE 5 CAMISAS DO BRASIL PARA CLIENTESBROKERWESLEY MARQUES DA SILVA (133624-3688RU | B2: 46113 | C2: 817991 | D2: WESLEY MARQUES DA SILVA | E2: -2203.93 | F2: OUTROS | G2: 46114 | H2: 1170 | J2: COMPRA DE 5 CAMISAS DO BRASIL PARA CLIENTES | K2: 133624-3688RU | L2: WESLEY MARQUES DA SILVA | M2: BROKER | N2: =VLOOKUP(H2,Clientes!B:D,3,) -> BGC LIQUIDEZ DTVM LTDA
A3: =CONCATENATE($J$1,J3,$I$3,M3,$I$3,L3,$I$1,K3,$I$2) -> DESPESA DE REPRESENTAÇÃO - PESONALIZAÇÃO CAMISETAS DO BRASILBROKERWESLEY MARQUES DA SILVA (111714-3688PO | B3: 46113 | C3: 817991 | D3: WESLEY MARQUES DA SILVA | E3: -622.8 | F3: OUTROS | G3: 46134 | H3: 1170 | J3: PESONALIZAÇÃO CAMISETAS DO BRASIL | K3: 111714-3688PO | L3: WESLEY MARQUES DA SILVA | M3: BROKER | N3: =VLOOKUP(H3,Clientes!B:D,3,) -> BGC LIQUIDEZ DTVM LTDA
A4: =CONCATENATE($J$1,J4,$I$3,M4,$I$3,L4,$I$1,K4,$I$2) -> DESPESA DE REPRESENTAÇÃO - ALMOÇOTRADERBRUNO SAVARIS (120157-3688RP | B4: 46113 | C4: 817991 | D4: RODRIGO PENTAGNA | E4: -463 | F4: ALMOÇO | G4: 46114 | H4: 83063 | J4: ALMOÇO | K4: 120157-3688RP | L4: BRUNO SAVARIS | M4: TRADER | N4: =VLOOKUP(H4,Clientes!B:D,3,) -> SCHONFELD STRATEGIC ADVISORS BRAZIL LTDA.
A5: =CONCATENATE($J$1,J5,$I$3,M5,$I$3,L5,$I$1,K5,$I$2) -> DESPESA DE REPRESENTAÇÃO - ALMOÇOTRADERNICOLE BENINNI (144822-3688RP | B5: 46113 | C5: 817991 | D5: RODRIGO PENTAGNA | E5: -966 | F5: ALMOÇO | G5: 46121 | H5: 83074 | J5: ALMOÇO | K5: 144822-3688RP | L5: NICOLE BENINNI | M5: TRADER | N5: =VLOOKUP(H5,Clientes!B:D,3,) -> UBS BRASIL ADMINISTRADORA DE VALORES MOBILIARIOS LTDA
A6: =CONCATENATE($J$1,J6,$I$3,M6,$I$3,L6,$I$1,K6,$I$2) -> DESPESA DE REPRESENTAÇÃO - ALMOÇOTRADERYEONG TAE LEE (101017-3688RF | B6: 46113 | C6: 817991 | D6: RICARDO FERREIRA DA COSTA | E6: -554 | F6: ALMOÇO | G6: 46114 | H6: 43059 | I6: ) | J6: ALMOÇO | K6: 101017-3688RF | L6: YEONG TAE LEE | M6: TRADER | N6: =VLOOKUP(H6,Clientes!B:D,3,) -> BANCO FIBRA S/A
A7: =CONCATENATE($J$1,J7,$I$3,M7,$I$3,L7,$I$1,K7,$I$2) -> DESPESA DE REPRESENTAÇÃO - PASSAGEM SÃO PAULO X BRASÍLIABROKERRICARDO ANDRE VASCONCELOS RAMOS (AGENDA 41173 | B7: 46113 | C7: 817991 | D7: RICARDO ANDRE VASCONCELOS RAMOS | E7: -842.53 | F7: LOCOMOÇÃO | G7: 46120 | H7: 1170 | J7: PASSAGEM SÃO PAULO X BRASÍLIA | K7: AGENDA 41173 | L7: RICARDO ANDRE VASCONCELOS RAMOS | M7: BROKER | N7: =VLOOKUP(H7,Clientes!B:D,3,) -> BGC LIQUIDEZ DTVM LTDA
A8: =CONCATENATE($J$1,J8,$I$3,M8,$I$3,L8,$I$1,K8,$I$2) -> DESPESA DE REPRESENTAÇÃO - COMPRA DE 3 CAMISAS DO BRASIL PARA CLIENTESBROKERRICARDO ANDRE VASCONCELOS RAMOS (133624-3688RU | B8: 46113 | C8: 817991 | D8: RICARDO ANDRE VASCONCELOS RAMOS | E8: -1322.36 | F8: OUTROS | G8: 46114 | H8: 1170 | J8: COMPRA DE 3 CAMISAS DO BRASIL PARA CLIENTES | K8: 133624-3688RU | L8: RICARDO ANDRE VASCONCELOS RAMOS | M8: BROKER | N8: =VLOOKUP(H8,Clientes!B:D,3,) -> BGC LIQUIDEZ DTVM LTDA
A9: =CONCATENATE($J$1,J9,$I$3,M9,$I$3,L9,$I$1,K9,$I$2) -> DESPESA DE REPRESENTAÇÃO - HAPPY HOURTRADERALEXANDRE AUGUSTO B RODRIGUES (090034-3688RR | B9: 46113 | C9: 817991 | D9: RICARDO ANDRE VASCONCELOS RAMOS | E9: -1700 | F9: EVENTO | G9: 46121 | H9: 81565 | J9: HAPPY HOUR | K9: 090034-3688RR | L9: ALEXANDRE AUGUSTO B RODRIGUES | M9: TRADER | N9: =VLOOKUP(H9,Clientes!B:D,3,) -> SPX GESTAO DE RECURSOS LTDA
A10: =CONCATENATE($J$1,J10,$I$3,M10,$I$3,L10,$I$1,K10,$I$2) -> DESPESA DE REPRESENTAÇÃO - INGRESSOS PARA O MANIFESTO MUSICAL SÃO PAULOTRADERCARLOS R DE MENEZES JUNIOR (084826-3688RR | B10: 46113 | C10: 817991 | D10: RICARDO ANDRE VASCONCELOS RAMOS | E10: -2340 | F10: EVENTO | G10: 46121 | H10: 79258 | J10: INGRESSOS PARA O MANIFESTO MUSICAL SÃO PAULO | K10: 084826-3688RR | L10: CARLOS R DE MENEZES JUNIOR | M10: TRADER | N10: =VLOOKUP(H10,Clientes!B:D,3,) -> ITAU UNIBANCO S/A
A11: =CONCATENATE($J$1,J11,$I$3,M11,$I$3,L11,$I$1,K11,$I$2) -> DESPESA DE REPRESENTAÇÃO - HAPPY HOURTRADERALESSANDRO EZEQUIEL JUNIOR (085619-3688RR | B11: 46113 | C11: 817991 | D11: RICARDO ANDRE VASCONCELOS RAMOS | E11: -2962.41 | F11: EVENTO | G11: 46121 | H11: 14479 | J11: HAPPY HOUR | K11: 085619-3688RR | L11: ALESSANDRO EZEQUIEL JUNIOR | M11: TRADER | N11: =VLOOKUP(H11,Clientes!B:D,3,) -> BANCO SANTANDER (BRASIL) S/A
A12: =CONCATENATE($J$1,J12,$I$3,M12,$I$3,L12,$I$1,K12,$I$2) -> DESPESA DE REPRESENTAÇÃO - INGRESSOS SHOW "HISTÓRIAS SÃO PAULO" NO ALLIANZ PARQUETRADERJOAO KHOURI (085411-3688RR | B12: 46113 | C12: 817991 | D12: RICARDO ANDRE VASCONCELOS RAMOS | E12: -2984.96 | F12: EVENTO | G12: 46121 | H12: 144548 | J12: INGRESSOS SHOW "HISTÓRIAS SÃO PAULO" NO ALLIANZ PARQUE | K12: 085411-3688RR | L12: JOAO KHOURI | M12: TRADER | N12: =VLOOKUP(H12,Clientes!B:D,3,) -> ABSOLUTE GESTAO DE INVESTIMENTOS LTDA
A13: =CONCATENATE($J$1,J13,$I$3,M13,$I$3,L13,$I$1,K13,$I$2) -> DESPESA DE REPRESENTAÇÃO - ALMOÇOTRADERCARLOS R DE MENEZES JUNIOR (084637-3688RR | B13: 46113 | C13: 817991 | D13: RICARDO ANDRE VASCONCELOS RAMOS | E13: -562.51 | F13: ALMOÇO | G13: 46121 | H13: 79258 | J13: ALMOÇO | K13: 084637-3688RR | L13: CARLOS R DE MENEZES JUNIOR | M13: TRADER | N13: =VLOOKUP(H13,Clientes!B:D,3,) -> ITAU UNIBANCO S/A
A14: =CONCATENATE($J$1,J14,$I$3,M14,$I$3,L14,$I$1,K14,$I$2) -> DESPESA DE REPRESENTAÇÃO - CAMISAS DO BRASIL PARA CLIENTES TRADERCARLOS R DE MENEZES JUNIOR (104520-3688RR | B14: 46113 | C14: 817991 | D14: RICARDO ANDRE VASCONCELOS RAMOS | E14: -2699.94 | F14: EVENTO | G14: 46121 | H14: 79258 | J14: CAMISAS DO BRASIL PARA CLIENTES | K14: 104520-3688RR | L14: CARLOS R DE MENEZES JUNIOR | M14: TRADER | N14: =VLOOKUP(H14,Clientes!B:D,3,) -> ITAU UNIBANCO S/A
A15: =CONCATENATE($J$1,J15,$I$3,M15,$I$3,L15,$I$1,K15,$I$2) -> DESPESA DE REPRESENTAÇÃO - ALMOÇOTRADERJOAO KHOURI (145714-3688RR | B15: 46113 | C15: 817991 | D15: RICARDO ANDRE VASCONCELOS RAMOS | E15: -461.37 | F15: ALMOÇO | G15: 46128 | H15: 144548 | J15: ALMOÇO | K15: 145714-3688RR | L15: JOAO KHOURI | M15: TRADER | N15: =VLOOKUP(H15,Clientes!B:D,3,) -> ABSOLUTE GESTAO DE INVESTIMENTOS LTDA
A16: =CONCATENATE($J$1,J16,$I$3,M16,$I$3,L16,$I$1,K16,$I$2) -> DESPESA DE REPRESENTAÇÃO - COBERTURA FOTOGRÁFICA KAITAI NO OIZUMI SUSHIBROKERRICARDO ANDRE VASCONCELOS RAMOS (AGENDA 41493 | B16: 46113 | C16: 817991 | D16: RICARDO ANDRE VASCONCELOS RAMOS | E16: -500 | F16: EVENTO | G16: 46129 | H16: 1170 | J16: COBERTURA FOTOGRÁFICA KAITAI NO OIZUMI SUSHI | K16: AGENDA 41493 | L16: RICARDO ANDRE VASCONCELOS RAMOS | M16: BROKER | N16: =VLOOKUP(H16,Clientes!B:D,3,) -> BGC LIQUIDEZ DTVM LTDA
A17: =CONCATENATE($J$1,J17,$I$3,M17,$I$3,L17,$I$1,K17,$I$2) -> DESPESA DE REPRESENTAÇÃO - PESONALIZAÇÃO CAMISETAS DO BRASILBROKERRICARDO ANDRE VASCONCELOS RAMOS (111714-3688PO | B17: 46113 | C17: 817991 | D17: RICARDO ANDRE VASCONCELOS RAMOS | E17: -622.8 | F17: OUTROS | G17: 46134 | H17: 1170 | J17: PESONALIZAÇÃO CAMISETAS DO BRASIL | K17: 111714-3688PO | L17: RICARDO ANDRE VASCONCELOS RAMOS | M17: BROKER | N17: =VLOOKUP(H17,Clientes!B:D,3,) -> BGC LIQUIDEZ DTVM LTDA
A18: =CONCATENATE($J$1,J18,$I$3,M18,$I$3,L18,$I$1,K18,$I$2) -> DESPESA DE REPRESENTAÇÃO - JANTARTRADERHUGO ALVES (090737-3688RR | B18: 46113 | C18: 817991 | D18: RICARDO ANDRE VASCONCELOS RAMOS | E18: -1054.58 | F18: JANTAR | G18: 46134 | H18: 79475 | J18: JANTAR | K18: 090737-3688RR | L18: HUGO ALVES | M18: TRADER | N18: =VLOOKUP(H18,Clientes!B:D,3,) -> CAIXA ECONOMICA FEDERAL
... A114: =CONCATENATE($J$1,J114,$I$3,M114,$I$3,L114,$I$1,K114,$I$2) -> DESPESA DE REPRESENTAÇÃO - ALMOÇOTRADERLEONARDO TARALLO (174553-3688FR | B114: 46113 | C114: 817991 | D114: FELIPE MEIRELLES RACCAH | E114: -406.8 | F114: ALMOÇO | G114: 46142 | H114: 12413 | J114: ALMOÇO | K114: 174553-3688FR | L114: LEONARDO TARALLO | M114: TRADER | N114: =VLOOKUP(H114,Clientes!B:D,3,) -> KAPITALO INVESTIMENTOS LTDA
A115: =CONCATENATE($J$1,J115,$I$3,M115,$I$3,L115,$I$1,K115,$I$2) -> DESPESA DE REPRESENTAÇÃO - ALMOÇO FILIPE SABARÁ E DANILO CAFFAROTRADERDANILO CAFFARO (142203-3688FT | B115: 46113 | C115: 817991 | D115: FELIPE DE SA TAVARES | E115: -1089.32 | F115: ALMOÇO | G115: 46114 | H115: 1170 | I115: - | J115: ALMOÇO FILIPE SABARÁ E DANILO CAFFARO | K115: 142203-3688FT | L115: DANILO CAFFARO | M115: TRADER | N115: =VLOOKUP(H115,Clientes!B:D,3,) -> BGC LIQUIDEZ DTVM LTDA
A116: =CONCATENATE($J$1,J116,$I$3,M116,$I$3,L116,$I$1,K116,$I$2) -> DESPESA DE REPRESENTAÇÃO - CAFÉ DA MANHÃTRADERRODRIGO SANTANA FERREIRA (141120-3688FT | B116: 46113 | C116: 817991 | D116: FELIPE DE SA TAVARES | E116: -2932.35 | F116: CAFÉ DA MANHÃ | G116: 46114 | H116: 14479 | J116: CAFÉ DA MANHÃ | K116: 141120-3688FT | L116: RODRIGO SANTANA FERREIRA | M116: TRADER | N116: =VLOOKUP(H116,Clientes!B:D,3,) -> BANCO SANTANDER (BRASIL) S/A
A117: =CONCATENATE($J$1,J117,$I$3,M117,$I$3,L117,$I$1,K117,$I$2) -> DESPESA DE REPRESENTAÇÃO - CAFÉ DA MANHÃTRADERROGERIO MATTEDI FOLSTER (141813-3688FT | B117: 46113 | C117: 817991 | D117: FELIPE DE SA TAVARES | E117: -187.5 | F117: CAFÉ DA MANHÃ | G117: 46114 | H117: 80375 | J117: CAFÉ DA MANHÃ | K117: 141813-3688FT | L117: ROGERIO MATTEDI FOLSTER | M117: TRADER | N117: =VLOOKUP(H117,Clientes!B:D,3,) -> ITAU UNIBANCO S/A
A118: =CONCATENATE($J$1,J118,$I$3,M118,$I$3,L118,$I$1,K118,$I$2) -> DESPESA DE REPRESENTAÇÃO - PASSAGEM RIO DE JANEIRO X SÃO PAULOBROKERFELIPE DE SA TAVARES (AGENDA 41265 | B118: 46113 | C118: 817991 | D118: FELIPE DE SA TAVARES | E118: -1269.41 | F118: LOCOMOÇÃO | G118: 46122 | H118: 1170 | J118: PASSAGEM RIO DE JANEIRO X SÃO PAULO | K118: AGENDA 41265 | L118: FELIPE DE SA TAVARES | M118: BROKER | N118: =VLOOKUP(H118,Clientes!B:D,3,) -> BGC LIQUIDEZ DTVM LTDA
A119: =CONCATENATE($J$1,J119,$I$3,M119,$I$3,L119,$I$1,K119,$I$2) -> DESPESA DE REPRESENTAÇÃO - ALMOÇOTRADERTHOMAS CITRIN (140515-3688FB | B119: 46113 | C119: 817991 | D119: FELIPE DE ANDRADE BASILE | E119: -1767 | F119: ALMOÇO | G119: 46128 | H119: 81718 | J119: ALMOÇO | K119: 140515-3688FB | L119: THOMAS CITRIN | M119: TRADER | N119: =VLOOKUP(H119,Clientes!B:D,3,) -> QUANTIQUE M3 INVESTMENTS LTDA
A120: =CONCATENATE($J$1,J120,$I$3,M120,$I$3,L120,$I$1,K120,$I$2) -> DESPESA DE REPRESENTAÇÃO - COMPRA DE 4 CAMISAS DO BRASIL PARA CLIENTESBROKERFABIO SOARES PFAENDER (133624-3688RU | B120: 46113 | C120: 817991 | D120: FABIO SOARES PFAENDER | E120: -1763.14 | F120: OUTROS | G120: 46114 | H120: 1170 | J120: COMPRA DE 4 CAMISAS DO BRASIL PARA CLIENTES | K120: 133624-3688RU | L120: FABIO SOARES PFAENDER | M120: BROKER | N120: =VLOOKUP(H120,Clientes!B:D,3,) -> BGC LIQUIDEZ DTVM LTDA
A121: =CONCATENATE($J$1,J121,$I$3,M121,$I$3,L121,$I$1,K121,$I$2) -> DESPESA DE REPRESENTAÇÃO - PASSAGEM RIO DE JANEIRO X SÃO PAULOCEOERMINIO OLIVI LUCCI (AGENDA 41309 | B121: 46113 | C121: 817991 | D121: ERMINIO OLIVI LUCCI | E121: -1057.24 | F121: LOCOMOÇÃO | G121: 46127 | H121: 1170 | J121: PASSAGEM RIO DE JANEIRO X SÃO PAULO | K121: AGENDA 41309 | L121: ERMINIO OLIVI LUCCI | M121: CEO | N121: =VLOOKUP(H121,Clientes!B:D,3,) -> BGC LIQUIDEZ DTVM LTDA
A122: =CONCATENATE($J$1,J122,$I$3,M122,$I$3,L122,$I$1,K122,$I$2) -> DESPESA DE REPRESENTAÇÃO - PASSAGEM RIO DE JANEIRO X SÃO PAULOCEOERMINIO OLIVI LUCCI (AGENDA 41310 | B122: 46113 | C122: 817991 | D122: ERMINIO OLIVI LUCCI | E122: -3588.43 | F122: LOCOMOÇÃO | G122: 46127 | H122: 1170 | J122: PASSAGEM RIO DE JANEIRO X SÃO PAULO | K122: AGENDA 41310 | L122: ERMINIO OLIVI LUCCI | M122: CEO | N122: =VLOOKUP(H122,Clientes!B:D,3,) -> BGC LIQUIDEZ DTVM LTDA
A123: =CONCATENATE($J$1,J123,$I$3,M123,$I$3,L123,$I$1,K123,$I$2) -> DESPESA DE REPRESENTAÇÃO - PASSAGEM SÃO PAULO X MIAMICEOERMINIO OLIVI LUCCI (AGENDA 41643 | B123: 46113 | C123: 817991 | D123: ERMINIO OLIVI LUCCI | E123: -37425.87 | F123: LOCOMOÇÃO | G123: 46142 | H123: 1170 | J123: PASSAGEM SÃO PAULO X MIAMI | K123: AGENDA 41643 | L123: ERMINIO OLIVI LUCCI | M123: CEO | N123: =VLOOKUP(H123,Clientes!B:D,3,) -> BGC LIQUIDEZ DTVM LTDA
A124: =CONCATENATE($J$1,J124,$I$3,M124,$I$3,L124,$I$1,K124,$I$2) -> DESPESA DE REPRESENTAÇÃO - PRESENTE DE ANIVERSARIO DA SECRETARIA ANNA TAPIASSECRETARIAANNA CAROLINA ABRUNHOSA TAPIAS (AGENDA 41176 | B124: 46113 | C124: 817991 | D124: ERMINIO OLIVI LUCCI | E124: -989.9 | F124: OUTROS | G124: 46114 | H124: 1170 | J124: PRESENTE DE ANIVERSARIO DA SECRETARIA ANNA TAPIAS | K124: AGENDA 41176 | L124: ANNA CAROLINA ABRUNHOSA TAPIAS | M124: SECRETARIA | N124: =VLOOKUP(H124,Clientes!B:D,3,) -> BGC LIQUIDEZ DTVM LTDA
A125: =CONCATENATE($J$1,J125,$I$3,M125,$I$3,L125,$I$1,K125,$I$2) -> DESPESA DE REPRESENTAÇÃO - MENSALIDADE DA ASSOCIAÇÃO AO WTC BUSSINESS CLUBCEOERMINIO OLIVI LUCCI (AGENDA 41241 | B125: 46113 | C125: 817991 | D125: ERMINIO OLIVI LUCCI | E125: -2000 | F125: OUTROS | G125: 46132 | H125: 1170 | J125: MENSALIDADE DA ASSOCIAÇÃO AO WTC BUSSINESS CLUB | K125: AGENDA 41241 | L125: ERMINIO OLIVI LUCCI | M125: CEO | N125: =VLOOKUP(H125,Clientes!B:D,3,) -> BGC LIQUIDEZ DTVM LTDA
A126: =CONCATENATE($J$1,J126,$I$3,M126,$I$3,L126,$I$1,K126,$I$2) -> DESPESA DE REPRESENTAÇÃO - HOSPEDAGEM NO HOTEL EM NOVA YORKCEOERMINIO OLIVI LUCCI (AGENDA 41298 | B126: 46113 | C126: 817991 | D126: ERMINIO OLIVI LUCCI | E126: -7853.99 | F126: HOSPEDAGEM | G126: 46119 | H126: 1170 | J126: HOSPEDAGEM NO HOTEL EM NOVA YORK | K126: AGENDA 41298 | L126: ERMINIO OLIVI LUCCI | M126: CEO | N126: =VLOOKUP(H126,Clientes!B:D,3,) -> BGC LIQUIDEZ DTVM LTDA
A127: =CONCATENATE($J$1,J127,$I$3,M127,$I$3,L127,$I$1,K127,$I$2) -> DESPESA DE REPRESENTAÇÃO - HOSPEDAGEM NO HOTEL EM NOVA YORKCEOERMINIO OLIVI LUCCI (AGENDA 41298 | B127: 46113 | C127: 817991 | D127: ERMINIO OLIVI LUCCI | E127: -3185.14 | F127: HOSPEDAGEM | G127: 46119 | H127: 1170 | J127: HOSPEDAGEM NO HOTEL EM NOVA YORK | K127: AGENDA 41298 | L127: ERMINIO OLIVI LUCCI | M127: CEO | N127: =VLOOKUP(H127,Clientes!B:D,3,) -> BGC LIQUIDEZ DTVM LTDA
... A199: =CONCATENATE($J$1,J199,$I$3,M199,$I$3,L199,$I$1,K199,$I$2) -> DESPESA DE REPRESENTAÇÃO - ALMOÇOTRADERANTONIO JOAQUIM DE M ANDRADE (145217-3688AS | B199: 46113 | C199: 817991 | D199: ALEXANDRE BRENO STEVENS | E199: -531 | F199: ALMOÇO | G199: 46134 | H199: 15501 | J199: ALMOÇO | K199: 145217-3688AS | L199: ANTONIO JOAQUIM DE M ANDRADE | M199: TRADER | N199: =VLOOKUP(H199,Clientes!B:D,3,) -> BANCO BTG PACTUAL S/A

Sheet MAI
A1: HISTORICO | B1: DATA COMPETENCIA | C1: CONTA CONTABIL | D1: BROKER | E1: VALOR | F1: FORNECEDOR | G1: DATA LANCAMENTO | H1: CLIENTE | I1: ( | J1: DESPESA DE REPRESENTAÇÃO - | K1: CODIGO | L1: CONVIDADO | M1: CARGO DO CONVIDADO | N1: RAZÃO SOCIAL
A2: =CONCATENATE($J$1,J2,$I$3,M2,$I$3,L2,$I$1,K2,$I$2) -> DESPESA DE REPRESENTAÇÃO - THE UNION HOTEL BRASILIA -BROKER-JUAREZ JOAQUIM DE LACERDA (AGENDA 41649) | B2: 46143 | C2: 817991 | D2: JUAREZ JOAQUIM DE LACERDA | E2: -826.03 | F2: HOSPEDAGEM | G2: 46146 | H2: 1170 | I2: ) | J2: THE UNION HOTEL BRASILIA | K2: AGENDA 41649 | L2: JUAREZ JOAQUIM DE LACERDA | M2: BROKER | N2: =VLOOKUP(H2,Clientes!B:D,3,) -> BGC LIQUIDEZ DTVM LTDA
A3: =CONCATENATE($J$1,J3,$I$3,M3,$I$3,L3,$I$1,K3,$I$2) -> DESPESA DE REPRESENTAÇÃO - HAPPY HOUR -TRADER-LEONARDO MASSAHIKO NAKAJIMA (132145-3688RM) | B3: 46143 | C3: 817991 | D3: RODRIGO MOURA MARQUES | E3: -2915.39 | F3: EVENTO | G3: 46146 | H3: 81501 | I3: - | J3: HAPPY HOUR | K3: 132145-3688RM | L3: LEONARDO MASSAHIKO NAKAJIMA | M3: TRADER | N3: =VLOOKUP(H3,Clientes!B:D,3,) -> PORTO SEGURO INVESTIMENTOS LTDA
A4: =CONCATENATE($J$1,J4,$I$3,M4,$I$3,L4,$I$1,K4,$I$2) -> DESPESA DE REPRESENTAÇÃO - ALMOÇO-TRADER-FREDERIC CAMPOS BROWN (141012-3688AC) | B4: 46143 | C4: 817991 | D4: ALEXANDRE DA COSTA SOARES | E4: -619 | F4: ALMOÇO | G4: 46149 | H4: 79258 | J4: ALMOÇO | K4: 141012-3688AC | L4: FREDERIC CAMPOS BROWN | M4: TRADER | N4: =VLOOKUP(H4,Clientes!B:D,3,) -> ITAU UNIBANCO S/A
A5: =CONCATENATE($J$1,J5,$I$3,M5,$I$3,L5,$I$1,K5,$I$2) -> DESPESA DE REPRESENTAÇÃO - ALMOÇO-TRADER-RAFAEL ASSED (153602-3688BG) | B5: 46143 | C5: 817991 | D5: JOSE MAURICIO GOMES TEIXEIRA | E5: -408 | F5: ALMOÇO | G5: 46149 | H5: 80218 | J5: ALMOÇO | K5: 153602-3688BG | L5: RAFAEL ASSED | M5: TRADER | N5: =VLOOKUP(H5,Clientes!B:D,3,) -> OPPORTUNITY GESTAO DE INVESTIMENTOS E RECURSOS LTDA
A6: =CONCATENATE($J$1,J6,$I$3,M6,$I$3,L6,$I$1,K6,$I$2) -> DESPESA DE REPRESENTAÇÃO - JANTAR-TRADER-GUILHERME ALVES DE PAULA (093425-3688BG) | B6: 46143 | C6: 817991 | D6: JOSE MAURICIO GOMES TEIXEIRA | E6: -828 | F6: JANTAR | G6: 46149 | H6: 81199 | J6: JANTAR | K6: 093425-3688BG | L6: GUILHERME ALVES DE PAULA | M6: TRADER | N6: =VLOOKUP(H6,Clientes!B:D,3,) -> BANCO ORIGINAL S/A
A7: =CONCATENATE($J$1,J7,$I$3,M7,$I$3,L7,$I$1,K7,$I$2) -> DESPESA DE REPRESENTAÇÃO - ALMOÇO -TRADER-SERGIO GUIMARAES (132152-3688RU) | B7: 46143 | C7: 817991 | D7: REINALDO ANDRE URBANO FILHO | E7: -1187.06 | F7: ALMOÇO | G7: 46149 | H7: 79793 | J7: ALMOÇO | K7: 132152-3688RU | L7: SERGIO GUIMARAES | M7: TRADER | N7: =VLOOKUP(H7,Clientes!B:D,3,) -> EMERALD GESTAO DE INVESTIMENTOS SOCIEDADE UNIPESSOAL LTDA
A8: =CONCATENATE($J$1,J8,$I$3,M8,$I$3,L8,$I$1,K8,$I$2) -> DESPESA DE REPRESENTAÇÃO - ALMOÇO ANDBANK -TRADER-EWERTON (132330-3688RU) | B8: 46143 | C8: 817991 | D8: REINALDO ANDRE URBANO FILHO | E8: -1422.33 | F8: ALMOÇO | G8: 46149 | H8: 1170 | J8: ALMOÇO ANDBANK | K8: 132330-3688RU | L8: EWERTON | M8: TRADER | N8: =VLOOKUP(H8,Clientes!B:D,3,) -> BGC LIQUIDEZ DTVM LTDA
A9: =CONCATENATE($J$1,J9,$I$3,M9,$I$3,L9,$I$1,K9,$I$2) -> DESPESA DE REPRESENTAÇÃO - ALMOÇO COM O TESOURO NACIONAL-ECONOMISTA-DANIEL CARDOSO LEAL (083828-3688RR) | B9: 46143 | C9: 817991 | D9: BGC SEGUNDA VOLTA | E9: -1569.49 | F9: ALMOÇO | G9: 46149 | H9: 1170 | J9: ALMOÇO COM O TESOURO NACIONAL | K9: 083828-3688RR | L9: DANIEL CARDOSO LEAL | M9: ECONOMISTA | N9: =VLOOKUP(H9,Clientes!B:D,3,) -> BGC LIQUIDEZ DTVM LTDA
A10: =CONCATENATE($J$1,J10,$I$3,M10,$I$3,L10,$I$1,K10,$I$2) -> DESPESA DE REPRESENTAÇÃO - ALMOÇO-TRADER-BRUNO PEROTTONI (172703-3688JV) | B10: 46143 | C10: 817991 | D10: JOSÉ VERGARA | E10: -1483.72 | F10: ALMOÇO | G10: 46149 | H10: 80753 | J10: ALMOÇO | K10: 172703-3688JV | L10: BRUNO PEROTTONI | M10: TRADER | N10: =VLOOKUP(H10,Clientes!B:D,3,) -> BANCO MORGAN STANLEY S/A
A11: =CONCATENATE($J$1,J11,$I$3,M11,$I$3,L11,$I$1,K11,$I$2) -> DESPESA DE REPRESENTAÇÃO - ALMOÇO-TRADER-PEDRO NUNES (155351-3688GF) | B11: 46143 | C11: 817991 | D11: GUSTAVO D ELBOUX FERRIELLO | E11: -1037 | F11: ALMOÇO | G11: 46149 | H11: 80667 | J11: ALMOÇO | K11: 155351-3688GF | L11: PEDRO NUNES | M11: TRADER | N11: =VLOOKUP(H11,Clientes!B:D,3,) -> ACE CAPITAL GESTORA DE RECURSOS LTDA
A12: =CONCATENATE($J$1,J12,$I$3,M12,$I$3,L12,$I$1,K12,$I$2) -> DESPESA DE REPRESENTAÇÃO - TAXI CENTRO APÓS ALMOÇO COM FUNDAÇÃO TELOS E IDA A HH IPANEMA-BROKER-JUAREZ JOAQUIM DE LACERDA (174618-3688JL) | B12: 46143 | C12: 817991 | D12: JUAREZ JOAQUIM DE LACERDA | E12: -60 | F12: LOCOMOÇÃO | G12: 46149 | H12: 1170 | J12: TAXI CENTRO APÓS ALMOÇO COM FUNDAÇÃO TELOS E IDA A HH IPANEMA | K12: 174618-3688JL | L12: JUAREZ JOAQUIM DE LACERDA | M12: BROKER | N12: =VLOOKUP(H12,Clientes!B:D,3,) -> BGC LIQUIDEZ DTVM LTDA
A13: =CONCATENATE($J$1,J13,$I$3,M13,$I$3,L13,$I$1,K13,$I$2) -> DESPESA DE REPRESENTAÇÃO - TAXI CENTRO X GALEÃO AEROPORTO EM VISITAS A FUNDOS DE PENSÃO RJ-BROKER-JUAREZ JOAQUIM DE LACERDA (171431-3688JL) | B13: 46143 | C13: 817991 | D13: JUAREZ JOAQUIM DE LACERDA | E13: -80 | F13: LOCOMOÇÃO | G13: 46149 | H13: 1170 | J13: TAXI CENTRO X GALEÃO AEROPORTO EM VISITAS A FUNDOS DE PENSÃO RJ | K13: 171431-3688JL | L13: JUAREZ JOAQUIM DE LACERDA | M13: BROKER | N13: =VLOOKUP(H13,Clientes!B:D,3,) -> BGC LIQUIDEZ DTVM LTDA
A14: =CONCATENATE($J$1,J14,$I$3,M14,$I$3,L14,$I$1,K14,$I$2) -> DESPESA DE REPRESENTAÇÃO - TAXI VISITAS A FUNDO DE PENSÃO RJ -BROKER-JUAREZ JOAQUIM DE LACERDA (155829-3688JL) | B14: 46143 | C14: 817991 | D14: JUAREZ JOAQUIM DE LACERDA | E14: -90 | F14: LOCOMOÇÃO | G14: 46149 | H14: 1170 | J14: TAXI VISITAS A FUNDO DE PENSÃO RJ | K14: 155829-3688JL | L14: JUAREZ JOAQUIM DE LACERDA | M14: BROKER | N14: =VLOOKUP(H14,Clientes!B:D,3,) -> BGC LIQUIDEZ DTVM LTDA
A15: =CONCATENATE($J$1,J15,$I$3,M15,$I$3,L15,$I$1,K15,$I$2) -> DESPESA DE REPRESENTAÇÃO - ESTACIONAMENTO EM VISITA A FUNDOS DE PENSÃO RJ -BROKER-JUAREZ JOAQUIM DE LACERDA (153035-3688JL) | B15: 46143 | C15: 817991 | D15: JUAREZ JOAQUIM DE LACERDA | E15: -157 | F15: LOCOMOÇÃO | G15: 46149 | H15: 1170 | J15: ESTACIONAMENTO EM VISITA A FUNDOS DE PENSÃO RJ | K15: 153035-3688JL | L15: JUAREZ JOAQUIM DE LACERDA | M15: BROKER | N15: =VLOOKUP(H15,Clientes!B:D,3,) -> BGC LIQUIDEZ DTVM LTDA
... A204: =CONCATENATE($J$1,J204,$I$3,M204,$I$3,L204,$I$1,K204,$I$2) -> DESPESA DE REPRESENTAÇÃO - UBER-SALES-MELISSA LEITE FIGUEIREDO ROCHA (E-MAIL 22/06/2026) | B204: 46143 | C204: 817991 | D204: JOSE ANTONIO DEZENE JUNIOR | E204: -666.24 | F204: LOCOMOÇÃO | G204: 46168 | H204: 1170 | J204: UBER | K204: E-MAIL 22/06/2026 | L204: MELISSA LEITE FIGUEIREDO ROCHA | M204: SALES | N204: =VLOOKUP(H204,Clientes!B:D,3,) -> BGC LIQUIDEZ DTVM LTDA
A205: =CONCATENATE($J$1,J205,$I$3,M205,$I$3,L205,$I$1,K205,$I$2) -> DESPESA DE REPRESENTAÇÃO - -- () | B205: 46143 | C205: 817991 | N205: =VLOOKUP(H205,Clientes!B:D,3,) -> #N/A
A206: =CONCATENATE($J$1,J206,$I$3,M206,$I$3,L206,$I$1,K206,$I$2) -> DESPESA DE REPRESENTAÇÃO - -- () | B206: 46143 | C206: 817991 | N206: =VLOOKUP(H206,Clientes!B:D,3,) -> #N/A
A207: =CONCATENATE($J$1,J207,$I$3,M207,$I$3,L207,$I$1,K207,$I$2) -> DESPESA DE REPRESENTAÇÃO - -- () | B207: 46143 | C207: 817991 | N207: =VLOOKUP(H207,Clientes!B:D,3,) -> #N/A
A208: =CONCATENATE($J$1,J208,$I$3,M208,$I$3,L208,$I$1,K208,$I$2) -> DESPESA DE REPRESENTAÇÃO - -- () | B208: 46143 | C208: 817991 | N208: =VLOOKUP(H208,Clientes!B:D,3,) -> #N/A
A209: =CONCATENATE($J$1,J209,$I$3,M209,$I$3,L209,$I$1,K209,$I$2) -> DESPESA DE REPRESENTAÇÃO - -- () | B209: 46143 | C209: 817991 | N209: =VLOOKUP(H209,Clientes!B:D,3,) -> #N/A
A210: =CONCATENATE($J$1,J210,$I$3,M210,$I$3,L210,$I$1,K210,$I$2) -> DESPESA DE REPRESENTAÇÃO - -- () | B210: 46143 | C210: 817991 | N210: =VLOOKUP(H210,Clientes!B:D,3,) -> #N/A
A211: =CONCATENATE($J$1,J211,$I$3,M211,$I$3,L211,$I$1,K211,$I$2) -> DESPESA DE REPRESENTAÇÃO - -- () | B211: 46143 | C211: 817991 | N211: =VLOOKUP(H211,Clientes!B:D,3,) -> #N/A
A212: =CONCATENATE($J$1,J212,$I$3,M212,$I$3,L212,$I$1,K212,$I$2) -> DESPESA DE REPRESENTAÇÃO - -- () | B212: 46143 | C212: 817991 | N212: =VLOOKUP(H212,Clientes!B:D,3,) -> #N/A
A213: =CONCATENATE($J$1,J213,$I$3,M213,$I$3,L213,$I$1,K213,$I$2) -> DESPESA DE REPRESENTAÇÃO - -- () | B213: 46143 | C213: 817991 | N213: =VLOOKUP(H213,Clientes!B:D,3,) -> #N/A
A214: =CONCATENATE($J$1,J214,$I$3,M214,$I$3,L214,$I$1,K214,$I$2) -> DESPESA DE REPRESENTAÇÃO - -- () | B214: 46143 | C214: 817991 | N214: =VLOOKUP(H214,Clientes!B:D,3,) -> #N/A
A215: =CONCATENATE($J$1,J215,$I$3,M215,$I$3,L215,$I$1,K215,$I$2) -> DESPESA DE REPRESENTAÇÃO - -- () | B215: 46143 | C215: 817991 | N215: =VLOOKUP(H215,Clientes!B:D,3,) -> #N/A
A216: =CONCATENATE($J$1,J216,$I$3,M216,$I$3,L216,$I$1,K216,$I$2) -> DESPESA DE REPRESENTAÇÃO - -- () | B216: 46143 | C216: 817991 | N216: =VLOOKUP(H216,Clientes!B:D,3,) -> #N/A
... A240: =CONCATENATE($J$1,J240,$I$3,M240,$I$3,L240,$I$1,K240,$I$2) -> DESPESA DE REPRESENTAÇÃO - -- () | B240: 46143 | C240: 817991 | N240: =VLOOKUP(H240,Clientes!B:D,3,) -> #N/A

Sheet JUN
A1: HISTORICO | B1: DATA COMPETENCIA | C1: CONTA CONTABIL | D1: BROKER | E1: VALOR | F1: FORNECEDOR | G1: DATA LANCAMENTO | H1: CLIENTE | I1: ( | J1: DESPESA DE REPRESENTAÇÃO - | K1: CODIGO | L1: CONVIDADO | M1: CARGO DO CONVIDADO | N1: RAZÃO SOCIAL
A2: =CONCATENATE($J$1,J2,$I$3,M2,$I$3,L2,$I$1,K2,$I$2) -> DESPESA DE REPRESENTAÇÃO - VIAGEM NYBROKERPAOLO FRANCA LIDA (143517-3998PI | B2: 46174 | C2: 817991 | D2: PAOLO FRANCA LIDA | E2: -19480.56 | F2: OUTROS | G2: 46184 | H2: 1170 | J2: VIAGEM NY | K2: 143517-3998PI | L2: PAOLO FRANCA LIDA | M2: BROKER | N2: =VLOOKUP(H2,Clientes!B:D,3,) -> BGC LIQUIDEZ DTVM LTDA
A3: =CONCATENATE($J$1,J3,$I$3,M3,$I$3,L3,$I$1,K3,$I$2) -> DESPESA DE REPRESENTAÇÃO - UBERSALESMARCELLE DA SILVEIRA GIL CADILHE (E-MAIL 01/07/2026 | B3: 46174 | C3: 817991 | D3: JOSE ANTONIO DEZENE JUNIOR | E3: -873.25 | F3: LOCOMOÇÃO | G3: 46203 | H3: 1170 | J3: UBER | K3: E-MAIL 01/07/2026 | L3: MARCELLE DA SILVEIRA GIL CADILHE | M3: SALES | N3: =VLOOKUP(H3,Clientes!B:D,3,) -> BGC LIQUIDEZ DTVM LTDA
A4: =CONCATENATE($J$1,J4,$I$3,M4,$I$3,L4,$I$1,K4,$I$2) -> DESPESA DE REPRESENTAÇÃO - UBERSALESMELISSA LEITE FIGUEIREDO ROCHA (E-MAIL 01/07/2026 | B4: 46174 | C4: 817991 | D4: JOSE ANTONIO DEZENE JUNIOR | E4: -162.85 | F4: LOCOMOÇÃO | G4: 46196 | H4: 1170 | J4: UBER | K4: E-MAIL 01/07/2026 | L4: MELISSA LEITE FIGUEIREDO ROCHA | M4: SALES | N4: =VLOOKUP(H4,Clientes!B:D,3,) -> BGC LIQUIDEZ DTVM LTDA
A5: =CONCATENATE($J$1,J5,$I$3,M5,$I$3,L5,$I$1,K5,$I$2) -> DESPESA DE REPRESENTAÇÃO - UBERECONOMISTAFELIPE DE SA TAVARES (E-MAIL 01/07/2026 | B5: 46174 | C5: 817991 | D5: FELIPE DE SA TAVARES | E5: -114.91 | F5: LOCOMOÇÃO | G5: 46184 | H5: 1170 | J5: UBER | K5: E-MAIL 01/07/2026 | L5: FELIPE DE SA TAVARES | M5: ECONOMISTA | N5: =VLOOKUP(H5,Clientes!B:D,3,) -> BGC LIQUIDEZ DTVM LTDA
A6: =CONCATENATE($J$1,J6,$I$3,M6,$I$3,L6,$I$1,K6,$I$2) -> DESPESA DE REPRESENTAÇÃO - TRANSPORTE EXECUTIVO MENSAL DE MAIO CEOERMINIO OLIVI LUCCI (AGENDA 42453 | B6: 46174 | C6: 817991 | D6: ERMINIO OLIVI LUCCI | E6: -2940 | F6: LOCOMOÇÃO | G6: 46183 | H6: 1170 | J6: TRANSPORTE EXECUTIVO MENSAL DE MAIO | K6: AGENDA 42453 | L6: ERMINIO OLIVI LUCCI | M6: CEO | N6: =VLOOKUP(H6,Clientes!B:D,3,) -> BGC LIQUIDEZ DTVM LTDA
A7: =CONCATENATE($J$1,J7,$I$3,M7,$I$3,L7,$I$1,K7,$I$2) -> DESPESA DE REPRESENTAÇÃO - TAXI VOLTA AEROPORTO GRUCEOERMINIO OLIVI LUCCI (AGENDA 42453 | B7: 46174 | C7: 817991 | D7: ERMINIO OLIVI LUCCI | E7: -350 | F7: LOCOMOÇÃO | G7: 46183 | H7: 1170 | J7: TAXI VOLTA AEROPORTO GRU | K7: AGENDA 42453 | L7: ERMINIO OLIVI LUCCI | M7: CEO | N7: =VLOOKUP(H7,Clientes!B:D,3,) -> BGC LIQUIDEZ DTVM LTDA
A8: =CONCATENATE($J$1,J8,$I$3,M8,$I$3,L8,$I$1,K8,$I$2) -> DESPESA DE REPRESENTAÇÃO - TAXI VIAGEM NOVA YORKBROKERPAOLO FRANCA LIDA (172230-3998PI | B8: 46174 | C8: 817991 | D8: PAOLO FRANCA LIDA | E8: -573.87 | F8: LOCOMOÇÃO | G8: 46198 | H8: 1170 | J8: TAXI VIAGEM NOVA YORK | K8: 172230-3998PI | L8: PAOLO FRANCA LIDA | M8: BROKER | N8: =VLOOKUP(H8,Clientes!B:D,3,) -> BGC LIQUIDEZ DTVM LTDA
A9: =CONCATENATE($J$1,J9,$I$3,M9,$I$3,L9,$I$1,K9,$I$2) -> DESPESA DE REPRESENTAÇÃO - TAXI VIAGEM NOVA YORKBROKERPAOLO FRANCA LIDA (172606-3998PI | B9: 46174 | C9: 817991 | D9: PAOLO FRANCA LIDA | E9: -651.42 | F9: LOCOMOÇÃO | G9: 46198 | H9: 1170 | J9: TAXI VIAGEM NOVA YORK | K9: 172606-3998PI | L9: PAOLO FRANCA LIDA | M9: BROKER | N9: =VLOOKUP(H9,Clientes!B:D,3,) -> BGC LIQUIDEZ DTVM LTDA
A10: =CONCATENATE($J$1,J10,$I$3,M10,$I$3,L10,$I$1,K10,$I$2) -> DESPESA DE REPRESENTAÇÃO - TAXI REUNIÃO NO RIO DE JANEIROSALESJOSE ANTONIO DEZENE JUNIOR (102810-3688JD | B10: 46174 | C10: 817991 | D10: JOSE ANTONIO DEZENE JUNIOR | E10: -260 | F10: LOCOMOÇÃO | G10: 46176 | H10: 12413 | J10: TAXI REUNIÃO NO RIO DE JANEIRO | K10: 102810-3688JD | L10: JOSE ANTONIO DEZENE JUNIOR | M10: SALES | N10: =VLOOKUP(H10,Clientes!B:D,3,) -> KAPITALO INVESTIMENTOS LTDA
A11: =CONCATENATE($J$1,J11,$I$3,M11,$I$3,L11,$I$1,K11,$I$2) -> DESPESA DE REPRESENTAÇÃO - TAXI NY AEROPORTO X HOTELECONOMISTAFELIPE DE SA TAVARES (171750-3688FT | B11: 46174 | C11: 817991 | D11: FELIPE DE SA TAVARES | E11: -632.5 | F11: LOCOMOÇÃO | G11: 46184 | H11: 1170 | J11: TAXI NY AEROPORTO X HOTEL | K11: 171750-3688FT | L11: FELIPE DE SA TAVARES | M11: ECONOMISTA | N11: =VLOOKUP(H11,Clientes!B:D,3,) -> BGC LIQUIDEZ DTVM LTDA
A12: =CONCATENATE($J$1,J12,$I$3,M12,$I$3,L12,$I$1,K12,$I$2) -> DESPESA DE REPRESENTAÇÃO - TAXI NYBROKERPAOLO FRANCA LIDA (145623-3998PI | B12: 46174 | C12: 817991 | D12: PAOLO FRANCA LIDA | E12: -217.14 | F12: LOCOMOÇÃO | G12: 46184 | H12: 1170 | J12: TAXI NY | K12: 145623-3998PI | L12: PAOLO FRANCA LIDA | M12: BROKER | N12: =VLOOKUP(H12,Clientes!B:D,3,) -> BGC LIQUIDEZ DTVM LTDA
A13: =CONCATENATE($J$1,J13,$I$3,M13,$I$3,L13,$I$1,K13,$I$2) -> DESPESA DE REPRESENTAÇÃO - TAXI IDA AEROPORTO GRU CEOERMINIO OLIVI LUCCI (AGENDA 42453 | B13: 46174 | C13: 817991 | D13: ERMINIO OLIVI LUCCI | E13: -350 | F13: LOCOMOÇÃO | G13: 46183 | H13: 1170 | J13: TAXI IDA AEROPORTO GRU | K13: AGENDA 42453 | L13: ERMINIO OLIVI LUCCI | M13: CEO | N13: =VLOOKUP(H13,Clientes!B:D,3,) -> BGC LIQUIDEZ DTVM LTDA
... A17: =CONCATENATE($J$1,J17,$I$3,M17,$I$3,L17,$I$1,K17,$I$2) -> DESPESA DE REPRESENTAÇÃO - TAXI AEROPORTOBROKERPAOLO FRANCA LIDA (144605-3998PI | B17: 46174 | C17: 817991 | D17: PAOLO FRANCA LIDA | E17: -672.1 | F17: LOCOMOÇÃO | G17: 46184 | H17: 1170 | J17: TAXI AEROPORTO | K17: 144605-3998PI | L17: PAOLO FRANCA LIDA | M17: BROKER | N17: =VLOOKUP(H17,Clientes!B:D,3,) -> BGC LIQUIDEZ DTVM LTDA
A18: =CONCATENATE($J$1,J18,$I$3,M18,$I$3,L18,$I$1,K18,$I$2) -> DESPESA DE REPRESENTAÇÃO - TAXA DE CANCELAMENTO DE HOSPEDAGEM QUALITY HOTELBROKERGUSTAVO D ELBOUX FERRIELLO (AGENDA 42153 | B18: 46174 | C18: 817991 | D18: GUSTAVO D ELBOUX FERRIELLO | E18: -10 | F18: HOSPEDAGEM | G18: 46174 | H18: 1170 | I18: ) | J18: TAXA DE CANCELAMENTO DE HOSPEDAGEM QUALITY HOTEL | K18: AGENDA 42153 | L18: GUSTAVO D ELBOUX FERRIELLO | M18: BROKER | N18: =VLOOKUP(H18,Clientes!B:D,3,) -> BGC LIQUIDEZ DTVM LTDA
A19: =CONCATENATE($J$1,J19,$I$3,M19,$I$3,L19,$I$1,K19,$I$2) -> DESPESA DE REPRESENTAÇÃO - TARIFA HOTEL ATLANTICO COPACABANA SALESMELISSA LEITE FIGUEIREDO ROCHA (AGENDA 42512 | B19: 46174 | C19: 817991 | D19: JOSE ANTONIO DEZENE JUNIOR | E19: -120.79 | F19: HOSPEDAGEM | G19: 46195 | H19: 1170 | J19: TARIFA HOTEL ATLANTICO COPACABANA | K19: AGENDA 42512 | L19: MELISSA LEITE FIGUEIREDO ROCHA | M19: SALES | N19: =VLOOKUP(H19,Clientes!B:D,3,) -> BGC LIQUIDEZ DTVM LTDA
A20: =CONCATENATE($J$1,J20,$I$3,M20,$I$3,L20,$I$1,K20,$I$2) -> DESPESA DE REPRESENTAÇÃO - REEMBOLSO REFERENTE AOS DOLARES COMPRADOS NO CARTÃO CORPORATIVOCEOERMINIO OLIVI LUCCI (AGENDA 42594 | B20: 46174 | C20: 817991 | D20: ERMINIO OLIVI LUCCI | E20: 451.02 | F20: OUTROS | G20: 46190 | H20: 1170 | J20: REEMBOLSO REFERENTE AOS DOLARES COMPRADOS NO CARTÃO CORPORATIVO | K20: AGENDA 42594 | L20: ERMINIO OLIVI LUCCI | M20: CEO | N20: =VLOOKUP(H20,Clientes!B:D,3,) -> BGC LIQUIDEZ DTVM LTDA
A21: =CONCATENATE($J$1,J21,$I$3,M21,$I$3,L21,$I$1,K21,$I$2) -> DESPESA DE REPRESENTAÇÃO - REEMBOLSO INGRESSO WIMBLEDON DE 2025CEOERMINIO OLIVI LUCCI (AGENDA 42620 | B21: 46174 | C21: 817991 | D21: ERMINIO OLIVI LUCCI | E21: 26391.96 | F21: EVENTO | G21: 46192 | H21: 1170 | J21: REEMBOLSO INGRESSO WIMBLEDON DE 2025 | K21: AGENDA 42620 | L21: ERMINIO OLIVI LUCCI | M21: CEO | N21: =VLOOKUP(H21,Clientes!B:D,3,) -> BGC LIQUIDEZ DTVM LTDA
A22: =CONCATENATE($J$1,J22,$I$3,M22,$I$3,L22,$I$1,K22,$I$2) -> DESPESA DE REPRESENTAÇÃO - PASSAGEM SÃO PAULO X RIO DE JANEIROSALESMELISSA LEITE FIGUEIREDO ROCHA (AGENDA 42303 | B22: 46174 | C22: 817991 | D22: JOSE ANTONIO DEZENE JUNIOR | E22: -2118.67 | F22: LOCOMOÇÃO | G22: 46188 | H22: 1170 | J22: PASSAGEM SÃO PAULO X RIO DE JANEIRO | K22: AGENDA 42303 | L22: MELISSA LEITE FIGUEIREDO ROCHA | M22: SALES | N22: =VLOOKUP(H22,Clientes!B:D,3,) -> BGC LIQUIDEZ DTVM LTDA
A23: =CONCATENATE($J$1,J23,$I$3,M23,$I$3,L23,$I$1,K23,$I$2) -> DESPESA DE REPRESENTAÇÃO - PASSAGEM SÃO PAULO X RIO DE JANEIROSALESMARCELLE DA SILVEIRA GIL CADILHE (AGENDA 42570 | B23: 46174 | C23: 817991 | D23: JOSE ANTONIO DEZENE JUNIOR | E23: -909.3 | F23: LOCOMOÇÃO | G23: 46188 | H23: 1170 | J23: PASSAGEM SÃO PAULO X RIO DE JANEIRO | K23: AGENDA 42570 | L23: MARCELLE DA SILVEIRA GIL CADILHE | M23: SALES | N23: =VLOOKUP(H23,Clientes!B:D,3,) -> BGC LIQUIDEZ DTVM LTDA
A24: =CONCATENATE($J$1,J24,$I$3,M24,$I$3,L24,$I$1,K24,$I$2) -> DESPESA DE REPRESENTAÇÃO - PASSAGEM SÃO PAULO X RIO DE JANEIROBROKERANDRE WATT VIANNA (AGENDA 42570 | B24: 46174 | C24: 817991 | D24: JOSE MAURICIO GOMES TEIXEIRA | E24: -485.84 | F24: LOCOMOÇÃO | G24: 46188 | H24: 1170 | J24: PASSAGEM SÃO PAULO X RIO DE JANEIRO | K24: AGENDA 42570 | L24: ANDRE WATT VIANNA | M24: BROKER | N24: =VLOOKUP(H24,Clientes!B:D,3,) -> BGC LIQUIDEZ DTVM LTDA
A25: =CONCATENATE($J$1,J25,$I$3,M25,$I$3,L25,$I$1,K25,$I$2) -> DESPESA DE REPRESENTAÇÃO - PASSAGEM SÃO PAULO X NY IDABROKERPAOLO FRANCA LIDA (144249-3998PI | B25: 46174 | C25: 817991 | D25: PAOLO FRANCA LIDA | E25: -9031.99 | F25: LOCOMOÇÃO | G25: 46184 | H25: 1170 | J25: PASSAGEM SÃO PAULO X NY IDA | K25: 144249-3998PI | L25: PAOLO FRANCA LIDA | M25: BROKER | N25: =VLOOKUP(H25,Clientes!B:D,3,) -> BGC LIQUIDEZ DTVM LTDA
A26: =CONCATENATE($J$1,J26,$I$3,M26,$I$3,L26,$I$1,K26,$I$2) -> DESPESA DE REPRESENTAÇÃO - PASSAGEM SÃO PAULO X NYBROKERRAFAEL TENORIO CAVALCANTI (105805-3688RC | B26: 46174 | C26: 817991 | D26: RAFAEL TENORIO CAVALCANTI | E26: -7447 | F26: LOCOMOÇÃO | G26: 46176 | H26: 1170 | J26: PASSAGEM SÃO PAULO X NY | K26: 105805-3688RC | L26: RAFAEL TENORIO CAVALCANTI | M26: BROKER | N26: =VLOOKUP(H26,Clientes!B:D,3,) -> BGC LIQUIDEZ DTVM LTDA
A27: =CONCATENATE($J$1,J27,$I$3,M27,$I$3,L27,$I$1,K27,$I$2) -> DESPESA DE REPRESENTAÇÃO - PASSAGEM SÃO PAULO X NYBROKERPAOLO FRANCA LIDA (150817-3998PI | B27: 46174 | C27: 817991 | D27: PAOLO FRANCA LIDA | E27: -8447 | F27: LOCOMOÇÃO | G27: 46184 | H27: 1170 | J27: PASSAGEM SÃO PAULO X NY | K27: 150817-3998PI | L27: PAOLO FRANCA LIDA | M27: BROKER | N27: =VLOOKUP(H27,Clientes!B:D,3,) -> BGC LIQUIDEZ DTVM LTDA
A28: =CONCATENATE($J$1,J28,$I$3,M28,$I$3,L28,$I$1,K28,$I$2) -> DESPESA DE REPRESENTAÇÃO - PASSAGEM SÃO PAULO X BRASÍLIACONSULTORIACLAUDIA TAVARES FERNANDES (AGENDA 42315 | B28: 46174 | C28: 817991 | D28: CLAUDIA TAVARES FERNANDES | E28: -2838.08 | F28: LOCOMOÇÃO | G28: 46183 | H28: 1170 | J28: PASSAGEM SÃO PAULO X BRASÍLIA | K28: AGENDA 42315 | L28: CLAUDIA TAVARES FERNANDES | M28: CONSULTORIA | N28: =VLOOKUP(H28,Clientes!B:D,3,) -> BGC LIQUIDEZ DTVM LTDA
A29: =CONCATENATE($J$1,J29,$I$3,M29,$I$3,L29,$I$1,K29,$I$2) -> DESPESA DE REPRESENTAÇÃO - MENSALIDADE DA ASSOCIAÇÃO AO WTC BUSSINESS CLUBCEOERMINIO OLIVI LUCCI (AGENDA 42293 | B29: 46174 | C29: 817991 | D29: ERMINIO OLIVI LUCCI | E29: -2000 | F29: OUTROS | G29: 46192 | H29: 1170 | J29: MENSALIDADE DA ASSOCIAÇÃO AO WTC BUSSINESS CLUB | K29: AGENDA 42293 | L29: ERMINIO OLIVI LUCCI | M29: CEO | N29: =VLOOKUP(H29,Clientes!B:D,3,) -> BGC LIQUIDEZ DTVM LTDA
A30: =CONCATENATE($J$1,J30,$I$3,M30,$I$3,L30,$I$1,K30,$I$2) -> DESPESA DE REPRESENTAÇÃO - JOGO DE CAMA - FLATBROKERCHRISTIANO MARCONDES DE BARROS LIMA (AGENDA 42648 | B30: 46174 | C30: 817991 | D30: CHRISTIANO MARCONDES DE BARROS LIMA | E30: -103.475 | F30: HOSPEDAGEM | G30: 46199 | H30: 1170 | J30: JOGO DE CAMA - FLAT | K30: AGENDA 42648 | L30: CHRISTIANO MARCONDES DE BARROS LIMA | M30: BROKER | N30: =VLOOKUP(H30,Clientes!B:D,3,) -> BGC LIQUIDEZ DTVM LTDA
... A82: =CONCATENATE($J$1,J82,$I$3,M82,$I$3,L82,$I$1,K82,$I$2) -> DESPESA DE REPRESENTAÇÃO - GARRAFAS EVENTO THE MACALLANTRADERCRISTIANO SOARES (AGENDA 42481 | B82: 46174 | C82: 817991 | D82: RODRIGO PENTAGNA | E82: -990 | F82: EVENTO | G82: 46188 | H82: 81765 | J82: GARRAFAS EVENTO THE MACALLAN | K82: AGENDA 42481 | L82: CRISTIANO SOARES | M82: TRADER | N82: =VLOOKUP(H82,Clientes!B:D,3,) -> UBS AG, LONDON BRANCH NOVO
A83: =CONCATENATE($J$1,J83,$I$3,M83,$I$3,L83,$I$1,K83,$I$2) -> DESPESA DE REPRESENTAÇÃO - GARRAFAS EVENTO THE MACALLANTRADERTOMAS FORTES SOARES QUIEZI (AGENDA 42481 | B83: 46174 | C83: 817991 | D83: ALVARO LUIZ RICOTTA SOARES | E83: =E82/3 -> -330 | F83: EVENTO | G83: 46188 | H83: 16702 | J83: GARRAFAS EVENTO THE MACALLAN | K83: AGENDA 42481 | L83: TOMAS FORTES SOARES QUIEZI | M83: TRADER | N83: =VLOOKUP(H83,Clientes!B:D,3,) -> BANCO BRADESCO S/A
A84: =CONCATENATE($J$1,J84,$I$3,M84,$I$3,L84,$I$1,K84,$I$2) -> DESPESA DE REPRESENTAÇÃO - GARRAFAS EVENTO THE MACALLANTRADERTOMAS FORTES SOARES QUIEZI (AGENDA 42481 | B84: 46174 | C84: 817991 | D84: FRANCISCO JOSE DIAS CARVALHO | E84: -660 | F84: EVENTO | G84: 46188 | H84: 16702 | J84: GARRAFAS EVENTO THE MACALLAN | K84: AGENDA 42481 | L84: TOMAS FORTES SOARES QUIEZI | M84: TRADER | N84: =VLOOKUP(H84,Clientes!B:D,3,) -> BANCO BRADESCO S/A
A85: =CONCATENATE($J$1,J85,$I$3,M85,$I$3,L85,$I$1,K85,$I$2) -> DESPESA DE REPRESENTAÇÃO - FUTEBOLTRADERMICHEL TECLA MICHELUTTI (145946-3998FC | B85: 46174 | C85: 817991 | D85: FRANCISCO JOSE DIAS CARVALHO | E85: -942.8 | F85: EVENTO | G85: 46191 | H85: 82597 | J85: FUTEBOL | K85: 145946-3998FC | L85: MICHEL TECLA MICHELUTTI | M85: TRADER | N85: =VLOOKUP(H85,Clientes!B:D,3,) -> PORTO SEGURO INVESTIMENTOS LTDA
A86: =CONCATENATE($J$1,J86,$I$3,M86,$I$3,L86,$I$1,K86,$I$2) -> DESPESA DE REPRESENTAÇÃO - FUTEBOLTRADERMICHEL TECLA MICHELUTTI (145946-3998FC | B86: 46174 | C86: 817991 | D86: EDUARDO TADEU CARAPIA UTTEMBERG | E86: -942.8 | F86: EVENTO | G86: 46191 | H86: 82597 | J86: FUTEBOL | K86: 145946-3998FC | L86: MICHEL TECLA MICHELUTTI | M86: TRADER | N86: =VLOOKUP(H86,Clientes!B:D,3,) -> PORTO SEGURO INVESTIMENTOS LTDA
A87: =CONCATENATE($J$1,J87,$I$3,M87,$I$3,L87,$I$1,K87,$I$2) -> DESPESA DE REPRESENTAÇÃO - FUTEBOLTRADERMICHEL TECLA MICHELUTTI (145946-3998FC | B87: 46174 | C87: 817991 | D87: DANIEL TEIXEIRA SIQUEIRA GONÇALVES | E87: -942.8 | F87: EVENTO | G87: 46191 | H87: 82597 | J87: FUTEBOL | K87: 145946-3998FC | L87: MICHEL TECLA MICHELUTTI | M87: TRADER | N87: =VLOOKUP(H87,Clientes!B:D,3,) -> PORTO SEGURO INVESTIMENTOS LTDA
A88: =CONCATENATE($J$1,J88,$I$3,M88,$I$3,L88,$I$1,K88,$I$2) -> DESPESA DE REPRESENTAÇÃO - FUTEBOLTRADERMICHEL TECLA MICHELUTTI (145946-3998FC | B88: 46174 | C88: 817991 | D88: CARLOS BASILE | E88: -942.8 | F88: EVENTO | G88: 46191 | H88: 82597 | J88: FUTEBOL | K88: 145946-3998FC | L88: MICHEL TECLA MICHELUTTI | M88: TRADER | N88: =VLOOKUP(H88,Clientes!B:D,3,) -> PORTO SEGURO INVESTIMENTOS LTDA
A89: =CONCATENATE($J$1,J89,$I$3,M89,$I$3,L89,$I$1,K89,$I$2) -> DESPESA DE REPRESENTAÇÃO - FUTEBOLTRADERMICHEL TECLA MICHELUTTI (145946-3998FC | B89: 46174 | C89: 817991 | D89: REINALDO ANDRE URBANO FILHO | E89: -942.8 | F89: EVENTO | G89: 46191 | H89: 82597 | J89: FUTEBOL | K89: 145946-3998FC | L89: MICHEL TECLA MICHELUTTI | M89: TRADER | N89: =VLOOKUP(H89,Clientes!B:D,3,) -> PORTO SEGURO INVESTIMENTOS LTDA
A90: =CONCATENATE($J$1,J90,$I$3,M90,$I$3,L90,$I$1,K90,$I$2) -> DESPESA DE REPRESENTAÇÃO - FRETE DOCUMENTAÇÃOBROKERPAOLO FRANCA LIDA (EMAIL 03/07/2026 | B90: 46174 | C90: 817991 | D90: REINALDO ANDRE URBANO FILHO | E90: -48.27 | F90: OUTROS | G90: 46203 | H90: 1170 | J90: FRETE DOCUMENTAÇÃO | K90: EMAIL 03/07/2026 | L90: PAOLO FRANCA LIDA | M90: BROKER | N90: =VLOOKUP(H90,Clientes!B:D,3,) -> BGC LIQUIDEZ DTVM LTDA
A91: =CONCATENATE($J$1,J91,$I$3,M91,$I$3,L91,$I$1,K91,$I$2) -> DESPESA DE REPRESENTAÇÃO - EVENTO B HOTEL BRASÍLIABROKERANTÔNIO MARTINS NETO (AGENDA 42481 | B91: 46174 | C91: 817991 | D91: ANTÔNIO MARTINS NETO | E91: -2035.6667 | F91: EVENTO | G91: 46188 | H91: 1170 | J91: EVENTO B HOTEL BRASÍLIA | K91: AGENDA 42481 | L91: ANTÔNIO MARTINS NETO | M91: BROKER | N91: =VLOOKUP(H91,Clientes!B:D,3,) -> BGC LIQUIDEZ DTVM LTDA
A92: =CONCATENATE($J$1,J92,$I$3,M92,$I$3,L92,$I$1,K92,$I$2) -> DESPESA DE REPRESENTAÇÃO - EVENTO B HOTEL BRASÍLIABROKERBRENO MELLO DOS SANTOS (AGENDA 42481 | B92: 46174 | C92: 817991 | D92: BRENO MELLO DOS SANTOS | E92: -2035.6667 | F92: EVENTO | G92: 46188 | H92: 1170 | J92: EVENTO B HOTEL BRASÍLIA | K92: AGENDA 42481 | L92: BRENO MELLO DOS SANTOS | M92: BROKER | N92: =VLOOKUP(H92,Clientes!B:D,3,) -> BGC LIQUIDEZ DTVM LTDA
A93: =CONCATENATE($J$1,J93,$I$3,M93,$I$3,L93,$I$1,K93,$I$2) -> DESPESA DE REPRESENTAÇÃO - EVENTO B HOTEL BRASÍLIABROKERFABIO SOARES PFAENDER (AGENDA 42481 | B93: 46174 | C93: 817991 | D93: FABIO SOARES PFAENDER | E93: -2035.6667 | F93: EVENTO | G93: 46188 | H93: 1170 | J93: EVENTO B HOTEL BRASÍLIA | K93: AGENDA 42481 | L93: FABIO SOARES PFAENDER | M93: BROKER | N93: =VLOOKUP(H93,Clientes!B:D,3,) -> BGC LIQUIDEZ DTVM LTDA
A94: =CONCATENATE($J$1,J94,$I$3,M94,$I$3,L94,$I$1,K94,$I$2) -> DESPESA DE REPRESENTAÇÃO - EVENTO B HOTEL BRASÍLIABROKERGUSTAVO D ELBOUX FERRIELLO (AGENDA 42481 | B94: 46174 | C94: 817991 | D94: GUSTAVO D ELBOUX FERRIELLO | E94: -2035.6667 | F94: EVENTO | G94: 46188 | H94: 1170 | J94: EVENTO B HOTEL BRASÍLIA | K94: AGENDA 42481 | L94: GUSTAVO D ELBOUX FERRIELLO | M94: BROKER | N94: =VLOOKUP(H94,Clientes!B:D,3,) -> BGC LIQUIDEZ DTVM LTDA
A95: =CONCATENATE($J$1,J95,$I$3,M95,$I$3,L95,$I$1,K95,$I$2) -> DESPESA DE REPRESENTAÇÃO - EVENTO B HOTEL BRASÍLIABROKERRICARDO ANDRE VASCONCELOS RAMOS (AGENDA 42481 | B95: 46174 | C95: 817991 | D95: RICARDO ANDRE VASCONCELOS RAMOS | E95: -2035.6667 | F95: EVENTO | G95: 46188 | H95: 1170 | J95: EVENTO B HOTEL BRASÍLIA | K95: AGENDA 42481 | L95: RICARDO ANDRE VASCONCELOS RAMOS | M95: BROKER | N95: =VLOOKUP(H95,Clientes!B:D,3,) -> BGC LIQUIDEZ DTVM LTDA
... A97: =CONCATENATE($J$1,J97,$I$3,M97,$I$3,L97,$I$1,K97,$I$2) -> DESPESA DE REPRESENTAÇÃO - EVENTO B HOTEL BRASÍLIABROKERENRICO BORTPLUZO CASSIANO (AGENDA 42481 | B97: 46174 | C97: 817991 | D97: ENRICO BORTPLUZO CASSIANO | E97: -6104 | F97: EVENTO | G97: 46188 | H97: 1170 | J97: EVENTO B HOTEL BRASÍLIA | K97: AGENDA 42481 | L97: ENRICO BORTPLUZO CASSIANO | M97: BROKER | N97: =VLOOKUP(H97,Clientes!B:D,3,) -> BGC LIQUIDEZ DTVM LTDA
A98: =CONCATENATE($J$1,J98,$I$3,M98,$I$3,L98,$I$1,K98,$I$2) -> DESPESA DE REPRESENTAÇÃO - ESTACIONAMENTO AEROPORTO DE CONGONHAS SALESJOSE ANTONIO DEZENE JUNIOR (104251-3688JD | B98: 46174 | C98: 817991 | D98: JOSE ANTONIO DEZENE JUNIOR | E98: -120 | F98: LOCOMOÇÃO | G98: 46176 | H98: 79475 | I98: - | J98: ESTACIONAMENTO AEROPORTO DE CONGONHAS | K98: 104251-3688JD | L98: JOSE ANTONIO DEZENE JUNIOR | M98: SALES | N98: =VLOOKUP(H98,Clientes!B:D,3,) -> CAIXA ECONOMICA FEDERAL
A99: =CONCATENATE($J$1,J99,$I$3,M99,$I$3,L99,$I$1,K99,$I$2) -> DESPESA DE REPRESENTAÇÃO - CONDOMINIO E IPTU - FLATBROKERCHRISTIANO MARCONDES DE BARROS LIMA (AGENDA 42275 | B99: 46174 | C99: 817991 | D99: CHRISTIANO MARCONDES DE BARROS LIMA | E99: -788 | F99: HOSPEDAGEM | G99: 46176 | H99: 1170 | J99: CONDOMINIO E IPTU - FLAT | K99: AGENDA 42275 | L99: CHRISTIANO MARCONDES DE BARROS LIMA | M99: BROKER | N99: =VLOOKUP(H99,Clientes!B:D,3,) -> BGC LIQUIDEZ DTVM LTDA
A100: =CONCATENATE($J$1,J100,$I$3,M100,$I$3,L100,$I$1,K100,$I$2) -> DESPESA DE REPRESENTAÇÃO - CONDOMINIO E IPTU - FLATBROKERJOSE MAURICIO GOMES TEIXEIRA (AGENDA 42275 | B100: 46174 | C100: 817991 | D100: JOSE MAURICIO GOMES TEIXEIRA | E100: -788 | F100: HOSPEDAGEM | G100: 46176 | H100: 1170 | J100: CONDOMINIO E IPTU - FLAT | K100: AGENDA 42275 | L100: JOSE MAURICIO GOMES TEIXEIRA | M100: BROKER | N100: =VLOOKUP(H100,Clientes!B:D,3,) -> BGC LIQUIDEZ DTVM LTDA
A101: =CONCATENATE($J$1,J101,$I$3,M101,$I$3,L101,$I$1,K101,$I$2) -> DESPESA DE REPRESENTAÇÃO - CONDOMINIO E IPTU - FLATGESTORANDRE HALL ACCIOLY (AGENDA 42275 | B101: 46174 | C101: 817991 | D101: LIQUIDEZ-OTHER | E101: -1576 | F101: HOSPEDAGEM | G101: 46176 | H101: 1170 | J101: CONDOMINIO E IPTU - FLAT | K101: AGENDA 42275 | L101: ANDRE HALL ACCIOLY | M101: GESTOR | N101: =VLOOKUP(H101,Clientes!B:D,3,) -> BGC LIQUIDEZ DTVM LTDA
A102: =CONCATENATE($J$1,J102,$I$3,M102,$I$3,L102,$I$1,K102,$I$2) -> DESPESA DE REPRESENTAÇÃO - CONDOMINIO E IPTU - FLATBROKERPAULO GUILHERME MENEZES FELIX (AGENDA 42282 | B102: 46174 | C102: 817991 | D102: PAULO GUILHERME MENEZES FELIX | E102: -977.17 | F102: HOSPEDAGEM | G102: 46197 | H102: 1170 | J102: CONDOMINIO E IPTU - FLAT | K102: AGENDA 42282 | L102: PAULO GUILHERME MENEZES FELIX | M102: BROKER | N102: =VLOOKUP(H102,Clientes!B:D,3,) -> BGC LIQUIDEZ DTVM LTDA
A103: =CONCATENATE($J$1,J103,$I$3,M103,$I$3,L103,$I$1,K103,$I$2) -> DESPESA DE REPRESENTAÇÃO - CARTÃO CORPORATIVO NACIONALCEOERMINIO OLIVI LUCCI (AGENDA 42481 | B103: 46174 | C103: 817991 | D103: ERMINIO OLIVI LUCCI | E103: -45379.84 | F103: OUTROS | G103: 46188 | H103: 1170 | J103: CARTÃO CORPORATIVO NACIONAL | K103: AGENDA 42481 | L103: ERMINIO OLIVI LUCCI | M103: CEO | N103: =VLOOKUP(H103,Clientes!B:D,3,) -> BGC LIQUIDEZ DTVM LTDA
A104: =CONCATENATE($J$1,J104,$I$3,M104,$I$3,L104,$I$1,K104,$I$2) -> DESPESA DE REPRESENTAÇÃO - CARTÃO CORPORATIVO INTERNACIONALCEOERMINIO OLIVI LUCCI (AGENDA 42481 | B104: 46174 | C104: 817991 | D104: ERMINIO OLIVI LUCCI | E104: -14447.58 | F104: OUTROS | G104: 46188 | H104: 1170 | J104: CARTÃO CORPORATIVO INTERNACIONAL | K104: AGENDA 42481 | L104: ERMINIO OLIVI LUCCI | M104: CEO | N104: =VLOOKUP(H104,Clientes!B:D,3,) -> BGC LIQUIDEZ DTVM LTDA
A105: =CONCATENATE($J$1,J105,$I$3,M105,$I$3,L105,$I$1,K105,$I$2) -> DESPESA DE REPRESENTAÇÃO - CAFÉ DA MANHÃPOLÍTICOROMEU ZEMA (AGENDA 42481 | B105: 46174 | C105: 817991 | D105: ALEXANDRE DA COSTA SOARES | E105: -2158.87 | F105: CAFÉ DA MANHÃ | G105: 46188 | H105: 80240 | J105: CAFÉ DA MANHÃ | K105: AGENDA 42481 | L105: ROMEU ZEMA | M105: POLÍTICO | N105: =VLOOKUP(H105,Clientes!B:D,3,) -> KINEA INVESTIMENTOS LTDA
A106: =CONCATENATE($J$1,J106,$I$3,M106,$I$3,L106,$I$1,K106,$I$2) -> DESPESA DE REPRESENTAÇÃO - ALUGUEL FLAT BROKERCHRISTIANO MARCONDES DE BARROS LIMA (AGENDA 42273 | B106: 46174 | C106: 817991 | D106: CHRISTIANO MARCONDES DE BARROS LIMA | E106: -1287.1325 | F106: HOSPEDAGEM | G106: 46176 | H106: 1170 | J106: ALUGUEL FLAT | K106: AGENDA 42273 | L106: CHRISTIANO MARCONDES DE BARROS LIMA | M106: BROKER | N106: =VLOOKUP(H106,Clientes!B:D,3,) -> BGC LIQUIDEZ DTVM LTDA
A107: =CONCATENATE($J$1,J107,$I$3,M107,$I$3,L107,$I$1,K107,$I$2) -> DESPESA DE REPRESENTAÇÃO - ALUGUEL FLAT BROKERJOSE MAURICIO GOMES TEIXEIRA (AGENDA 42273 | B107: 46174 | C107: 817991 | D107: JOSE MAURICIO GOMES TEIXEIRA | E107: -1287.1325 | F107: HOSPEDAGEM | G107: 46176 | H107: 1170 | J107: ALUGUEL FLAT | K107: AGENDA 42273 | L107: JOSE MAURICIO GOMES TEIXEIRA | M107: BROKER | N107: =VLOOKUP(H107,Clientes!B:D,3,) -> BGC LIQUIDEZ DTVM LTDA
A108: =CONCATENATE($J$1,J108,$I$3,M108,$I$3,L108,$I$1,K108,$I$2) -> DESPESA DE REPRESENTAÇÃO - ALUGUEL FLAT GESTORANDRE HALL ACCIOLY (AGENDA 42273 | B108: 46174 | C108: 817991 | D108: LIQUIDEZ-OTHER | E108: -2574.265 | F108: HOSPEDAGEM | G108: 46176 | H108: 1170 | J108: ALUGUEL FLAT | K108: AGENDA 42273 | L108: ANDRE HALL ACCIOLY | M108: GESTOR | N108: =VLOOKUP(H108,Clientes!B:D,3,) -> BGC LIQUIDEZ DTVM LTDA
A109: =CONCATENATE($J$1,J109,$I$3,M109,$I$3,L109,$I$1,K109,$I$2) -> DESPESA DE REPRESENTAÇÃO - ALUGUEL FLAT BROKERPAULO GUILHERME MENEZES FELIX (AGENDA 42279 | B109: 46174 | C109: 817991 | D109: PAULO GUILHERME MENEZES FELIX | E109: -4244.83 | F109: HOSPEDAGEM | G109: 46197 | H109: 1170 | J109: ALUGUEL FLAT | K109: AGENDA 42279 | L109: PAULO GUILHERME MENEZES FELIX | M109: BROKER | N109: =VLOOKUP(H109,Clientes!B:D,3,) -> BGC LIQUIDEZ DTVM LTDA
A110: =CONCATENATE($J$1,J110,$I$3,M110,$I$3,L110,$I$1,K110,$I$2) -> DESPESA DE REPRESENTAÇÃO - ALMOÇO RUBAYAT RJ 20/05 COM A FUTURASALESJOSE ANTONIO DEZENE JUNIOR (AGENDA 42337 | B110: 46174 | C110: 817991 | D110: JOSE ANTONIO DEZENE JUNIOR | E110: -3932.4 | F110: ALMOÇO | G110: 46176 | H110: 1170 | J110: ALMOÇO RUBAYAT RJ 20/05 COM A FUTURA | K110: AGENDA 42337 | L110: JOSE ANTONIO DEZENE JUNIOR | M110: SALES | N110: =VLOOKUP(H110,Clientes!B:D,3,) -> BGC LIQUIDEZ DTVM LTDA
... A207: =CONCATENATE($J$1,J207,$I$3,M207,$I$3,L207,$I$1,K207,$I$2) -> DESPESA DE REPRESENTAÇÃO - ALMOÇOTRADERGEOGE MAIA (154427-3998EC | B207: 46174 | C207: 817991 | D207: ENRICO BORTPLUZO CASSIANO | E207: -508 | F207: ALMOÇO | G207: 46198 | H207: 82361 | J207: ALMOÇO | K207: 154427-3998EC | L207: GEOGE MAIA | M207: TRADER | N207: =VLOOKUP(H207,Clientes!B:D,3,) -> RIZA GESTORA DE RECURSOS LTDA

Sheet JUL
A1: HISTORICO | B1: DATA COMPETENCIA | C1: CONTA CONTABIL | D1: BROKER | E1: VALOR | F1: FORNECEDOR | G1: DATA LANCAMENTO | H1: CLIENTE | I1: ( | J1: DESPESA DE REPRESENTAÇÃO - | K1: CODIGO | L1: CONVIDADO | M1: CARGO DO CONVIDADO | N1: RAZÃO SOCIAL
A2: =CONCATENATE($J$1,J2,$I$3,M2,$I$3,L2,$I$1,K2,$I$2) -> DESPESA DE REPRESENTAÇÃO - PASSAGEM SÃO PAULO X RIO DE JANEIRO - CEO - ERMINIO OLIVI LUCCI (AGENDA 42636) | B2: 46204 | C2: 817991 | D2: ERMINIO OLIVI LUCCI | E2: -572.91 | F2: LOCOMOÇÃO | G2: 46204 | H2: 1170 | I2: ) | J2: PASSAGEM SÃO PAULO X RIO DE JANEIRO | K2: AGENDA 42636 | L2: ERMINIO OLIVI LUCCI | M2: CEO | N2: =VLOOKUP(H2,Clientes!B:D,3,) -> BGC LIQUIDEZ DTVM LTDA
A3: =CONCATENATE($J$1,J3,$I$3,M3,$I$3,L3,$I$1,K3,$I$2) -> DESPESA DE REPRESENTAÇÃO - PASSAGEM SÃO PAULO X BRASÍLIA - CONSULTORA - CLAUDIA TAVARES FERNANDES (AGENDA 42636) | B3: 46204 | C3: 817991 | D3: CLAUDIA TAVARES FERNANDES | E3: -2431.97 | F3: LOCOMOÇÃO | G3: 46204 | H3: 1170 | I3: - | J3: PASSAGEM SÃO PAULO X BRASÍLIA | K3: AGENDA 42636 | L3: CLAUDIA TAVARES FERNANDES | M3: CONSULTORA | N3: =VLOOKUP(H3,Clientes!B:D,3,) -> BGC LIQUIDEZ DTVM LTDA
A4: =CONCATENATE($J$1,J4,$I$3,M4,$I$3,L4,$I$1,K4,$I$2) -> DESPESA DE REPRESENTAÇÃO - PASSAGEM SÃO PAULO X BRASÍLIA - CONSULTOR - RENAN REIS CRUVINEL (AGENDA 42636) | B4: 46204 | C4: 817991 | D4: RENAN REIS CRUVINEL | E4: -2218.13 | F4: LOCOMOÇÃO | G4: 46204 | H4: 1170 | J4: PASSAGEM SÃO PAULO X BRASÍLIA | K4: AGENDA 42636 | L4: RENAN REIS CRUVINEL | M4: CONSULTOR | N4: =VLOOKUP(H4,Clientes!B:D,3,) -> BGC LIQUIDEZ DTVM LTDA
A5: =CONCATENATE($J$1,J5,$I$3,M5,$I$3,L5,$I$1,K5,$I$2) -> DESPESA DE REPRESENTAÇÃO - HOTEL RADISSON BLU SÃO PAULO - CONSULTORA - CLAUDIA TAVARES FERNANDES (AGENDA 42638) | B5: 46204 | C5: 817991 | D5: CLAUDIA TAVARES FERNANDES | E5: -1467.25 | F5: HOSPEDAGEM | G5: 46204 | H5: 1170 | J5: HOTEL RADISSON BLU SÃO PAULO | K5: AGENDA 42638 | L5: CLAUDIA TAVARES FERNANDES | M5: CONSULTORA | N5: =VLOOKUP(H5,Clientes!B:D,3,) -> BGC LIQUIDEZ DTVM LTDA
A6: =CONCATENATE($J$1,J6,$I$3,M6,$I$3,L6,$I$1,K6,$I$2) -> DESPESA DE REPRESENTAÇÃO - HOTEL RADISSON BLU SÃO PAULO - CONSULTOR - RENAN REIS CRUVINEL (AGENDA 42638) | B6: 46204 | C6: 817991 | D6: RENAN REIS CRUVINEL | E6: -1467.25 | F6: HOSPEDAGEM | G6: 46204 | H6: 1170 | J6: HOTEL RADISSON BLU SÃO PAULO | K6: AGENDA 42638 | L6: RENAN REIS CRUVINEL | M6: CONSULTOR | N6: =VLOOKUP(H6,Clientes!B:D,3,) -> BGC LIQUIDEZ DTVM LTDA
A7: =CONCATENATE($J$1,J7,$I$3,M7,$I$3,L7,$I$1,K7,$I$2) -> DESPESA DE REPRESENTAÇÃO - ALMOÇO - TRADER - RENANN DAVID (174431-3998FC) | B7: 46204 | C7: 817991 | D7: FRANCISCO JOSE DIAS CARVALHO | E7: -511.21 | F7: ALMOÇO | G7: 46205 | H7: 81643 | J7: ALMOÇO | K7: 174431-3998FC | L7: RENANN DAVID | M7: TRADER | N7: =VLOOKUP(H7,Clientes!B:D,3,) -> BANCO SUMITOMO MITSUI BRASILEIRO S/A
A8: =CONCATENATE($J$1,J8,$I$3,M8,$I$3,L8,$I$1,K8,$I$2) -> DESPESA DE REPRESENTAÇÃO - JANTAR - TRADER - RODRIGO MOREIRA DE ASSIS (102151-3998RP) | B8: 46204 | C8: 817991 | D8: RODRIGO PENTAGNA | E8: -2359 | F8: JANTAR | G8: 46205 | H8: 83119 | J8: JANTAR | K8: 102151-3998RP | L8: RODRIGO MOREIRA DE ASSIS | M8: TRADER | N8: =VLOOKUP(H8,Clientes!B:D,3,) -> UBS BRASIL ADMINISTRADORA DE VALORES MOBILIARIOS LTDA
A9: =CONCATENATE($J$1,J9,$I$3,M9,$I$3,L9,$I$1,K9,$I$2) -> DESPESA DE REPRESENTAÇÃO - ALMOÇO - TRADER - FILIPE SANTOS (155939-3998RU) | B9: 46204 | C9: 817991 | D9: REINALDO ANDRE URBANO FILHO | E9: -3525.6 | F9: ALMOÇO | G9: 46205 | H9: 79956 | J9: ALMOÇO | K9: 155939-3998RU | L9: FILIPE SANTOS | M9: TRADER | N9: =VLOOKUP(H9,Clientes!B:D,3,) -> SUL AMERICA INVESTIMENTOS GESTORA DE RECURSOS S/A
A10: =CONCATENATE($J$1,J10,$I$3,M10,$I$3,L10,$I$1,K10,$I$2) -> DESPESA DE REPRESENTAÇÃO - ALMOÇO - TRADER - RICARDO ESPINDOLA (154442-3998RU) | B10: 46204 | C10: 817991 | D10: REINALDO ANDRE URBANO FILHO | E10: -238.09 | F10: ALMOÇO | G10: 46205 | H10: 81500 | J10: ALMOÇO | K10: 154442-3998RU | L10: RICARDO ESPINDOLA | M10: TRADER | N10: =VLOOKUP(H10,Clientes!B:D,3,) -> PORTO SEGURO INVESTIMENTOS LTDA
A11: =CONCATENATE($J$1,J11,$I$3,M11,$I$3,L11,$I$1,K11,$I$2) -> DESPESA DE REPRESENTAÇÃO - ALMOÇO - TRADER - GABRIEL DA MOTTA MELLO (160420-3998RU) | B11: 46204 | C11: 817991 | D11: REINALDO ANDRE URBANO FILHO | E11: -847.5 | F11: ALMOÇO | G11: 46205 | H11: 12395 | J11: ALMOÇO | K11: 160420-3998RU | L11: GABRIEL DA MOTTA MELLO | M11: TRADER | N11: =VLOOKUP(H11,Clientes!B:D,3,) -> AZ QUEST INVESTIMENTOS LTDA
A12: =CONCATENATE($J$1,J12,$I$3,M12,$I$3,L12,$I$1,K12,$I$2) -> DESPESA DE REPRESENTAÇÃO - ALMOÇO - TRADER - GABRIEL DA MOTTA MELLO (160420-3998RU) | B12: 46204 | C12: 817991 | D12: DANIEL TEIXEIRA SIQUEIRA GONÇALVES | E12: -847.5 | F12: ALMOÇO | G12: 46205 | H12: 12395 | J12: ALMOÇO | K12: 160420-3998RU | L12: GABRIEL DA MOTTA MELLO | M12: TRADER | N12: =VLOOKUP(H12,Clientes!B:D,3,) -> AZ QUEST INVESTIMENTOS LTDA
A13: =CONCATENATE($J$1,J13,$I$3,M13,$I$3,L13,$I$1,K13,$I$2) -> DESPESA DE REPRESENTAÇÃO - ALMOÇO - TRADER - GABRIEL DA MOTTA MELLO (160420-3998RU) | B13: 46204 | C13: 817991 | D13: GUSTAVO D ELBOUX FERRIELLO | E13: -847.5 | F13: ALMOÇO | G13: 46205 | H13: 12395 | J13: ALMOÇO | K13: 160420-3998RU | L13: GABRIEL DA MOTTA MELLO | M13: TRADER | N13: =VLOOKUP(H13,Clientes!B:D,3,) -> AZ QUEST INVESTIMENTOS LTDA
A14: =CONCATENATE($J$1,J14,$I$3,M14,$I$3,L14,$I$1,K14,$I$2) -> DESPESA DE REPRESENTAÇÃO - JANTAR - TRADER - BRUNO BUDANT PEROTTONI (112011-3998JV) | B14: 46204 | C14: 817991 | D14: JOSÉ VERGARA | E14: -1604.79 | F14: JANTAR | G14: 46205 | H14: 81794 | J14: JANTAR | K14: 112011-3998JV | L14: BRUNO BUDANT PEROTTONI | M14: TRADER | N14: =VLOOKUP(H14,Clientes!B:D,3,) -> BRAZA BANK S/A BANCO DE CAMBIO
A15: =CONCATENATE($J$1,J15,$I$3,M15,$I$3,L15,$I$1,K15,$I$2) -> DESPESA DE REPRESENTAÇÃO - JANTAR - TRADER - BRUNO BUDANT PEROTTONI (105906-3998JV) | B15: 46204 | C15: 817991 | D15: JOSÉ VERGARA | E15: -348.7 | F15: JANTAR | G15: 46205 | H15: 81794 | J15: JANTAR | K15: 105906-3998JV | L15: BRUNO BUDANT PEROTTONI | M15: TRADER | N15: =VLOOKUP(H15,Clientes!B:D,3,) -> BRAZA BANK S/A BANCO DE CAMBIO
... A161: =CONCATENATE($J$1,J161,$I$3,M161,$I$3,L161,$I$1,K161,$I$2) -> DESPESA DE REPRESENTAÇÃO - CURSO TESOURO DIRETO SAINT PAUL - ECONOMISTA - FELIPE DE SA TAVARES (AGENDA 43070) | B161: 46204 | C161: 817991 | D161: BGC SEGUNDA VOLTA | E161: -69888 | F161: OUTROS | G161: 46234 | H161: 1170 | J161: CURSO TESOURO DIRETO SAINT PAUL | K161: AGENDA 43070 | L161: FELIPE DE SA TAVARES | M161: ECONOMISTA | N161: =VLOOKUP(H161,Clientes!B:D,3,) -> BGC LIQUIDEZ DTVM LTDA

Sheet AGO
A1: HISTORICO | B1: DATA COMPETENCIA | C1: CONTA CONTABIL | D1: BROKER | E1: VALOR | F1: FORNECEDOR | G1: DATA LANCAMENTO | H1: CLIENTE | I1: ( | J1: DESPESA DE REPRESENTAÇÃO - | K1: CODIGO | L1: CONVIDADO | M1: CARGO DO CONVIDADO | N1: RAZÃO SOCIAL
A2: =CONCATENATE($J$1,J2,$I$3,M2,$I$3,L2,$I$1,K2,$I$2) -> DESPESA DE REPRESENTAÇÃO - AJUSTE REFERENTE AOS INGRESSOS PARA O JOGO ROLAND GARROS (DEBITAR DOS BROKERS) - TRADER - SEBASTIEN MACULAN (AGENDA 42481) | B2: 46235 | C2: 817991 | D2: ERMINIO OLIVI LUCCI | E2: 28135.5 | F2: EVENTO | G2: 46188 | H2: 1170 | I2: ) | J2: AJUSTE REFERENTE AOS INGRESSOS PARA O JOGO ROLAND GARROS (DEBITAR DOS BROKERS) | K2: AGENDA 42481 | L2: SEBASTIEN MACULAN | M2: TRADER | N2: =VLOOKUP(H2,Clientes!B:D,3,) -> BGC LIQUIDEZ DTVM LTDA
A3: =CONCATENATE($J$1,J3,$I$3,M3,$I$3,L3,$I$1,K3,$I$2) -> DESPESA DE REPRESENTAÇÃO - INGRESSOS PARA O JOGO ROLAND GARROS - TRADER - SEBASTIEN MACULAN (AGENDA 42481) | B3: 46235 | C3: 817991 | D3: DANIEL TEIXEIRA SIQUEIRA GONÇALVES | E3: -14067.75 | F3: EVENTO | G3: 46188 | H3: 79258 | I3: - | J3: INGRESSOS PARA O JOGO ROLAND GARROS | K3: AGENDA 42481 | L3: SEBASTIEN MACULAN | M3: TRADER | N3: =VLOOKUP(H3,Clientes!B:D,3,) -> ITAU UNIBANCO S/A
A4: =CONCATENATE($J$1,J4,$I$3,M4,$I$3,L4,$I$1,K4,$I$2) -> DESPESA DE REPRESENTAÇÃO - INGRESSOS PARA O JOGO ROLAND GARROS - TRADER - SEBASTIEN MACULAN (AGENDA 42481) | B4: 46235 | C4: 817991 | D4: RICARDO ANDRE VASCONCELOS RAMOS | E4: -14067.75 | F4: EVENTO | G4: 46188 | H4: 79258 | J4: INGRESSOS PARA O JOGO ROLAND GARROS | K4: AGENDA 42481 | L4: SEBASTIEN MACULAN | M4: TRADER | N4: =VLOOKUP(H4,Clientes!B:D,3,) -> ITAU UNIBANCO S/A
A5: =CONCATENATE($J$1,J5,$I$3,M5,$I$3,L5,$I$1,K5,$I$2) -> DESPESA DE REPRESENTAÇÃO - HOTEL RADISSON RED CAMPINAS - CONSULTORA - CLAUDIA TAVARES FERNANDES (AGENDA 43217) | B5: 46235 | C5: 817991 | D5: CLAUDIA TAVARES FERNANDES | E5: -892.5 | F5: HOSPEDAGEM | G5: 46239 | H5: 1170 | J5: HOTEL RADISSON RED CAMPINAS | K5: AGENDA 43217 | L5: CLAUDIA TAVARES FERNANDES | M5: CONSULTORA | N5: =VLOOKUP(H5,Clientes!B:D,3,) -> BGC LIQUIDEZ DTVM LTDA
A6: =CONCATENATE($J$1,J6,$I$3,M6,$I$3,L6,$I$1,K6,$I$2) -> DESPESA DE REPRESENTAÇÃO - PASSAGEM BRASÍLIA X SÃO PAULO - CONSULTORA - CLAUDIA TAVARES FERNANDES (AGENDA 43218) | B6: 46235 | C6: 817991 | D6: CLAUDIA TAVARES FERNANDES | E6: -2215.44 | F6: LOCOMOÇÃO | G6: 46239 | H6: 1170 | J6: PASSAGEM BRASÍLIA X SÃO PAULO | K6: AGENDA 43218 | L6: CLAUDIA TAVARES FERNANDES | M6: CONSULTORA | N6: =VLOOKUP(H6,Clientes!B:D,3,) -> BGC LIQUIDEZ DTVM LTDA
A7: =CONCATENATE($J$1,J7,$I$3,M7,$I$3,L7,$I$1,K7,$I$2) -> DESPESA DE REPRESENTAÇÃO - PASSAGEM BRASÍLIA X SÃO PAULO - CONSULTOR - RENAN REIS CRUVINEL (AGENDA 43218) | B7: 46235 | C7: 817991 | D7: RENAN REIS CRUVINEL | E7: -2213.61 | F7: LOCOMOÇÃO | G7: 46239 | H7: 1170 | J7: PASSAGEM BRASÍLIA X SÃO PAULO | K7: AGENDA 43218 | L7: RENAN REIS CRUVINEL | M7: CONSULTOR | N7: =VLOOKUP(H7,Clientes!B:D,3,) -> BGC LIQUIDEZ DTVM LTDA
A8: =CONCATENATE($J$1,J8,$I$3,M8,$I$3,L8,$I$1,K8,$I$2) -> DESPESA DE REPRESENTAÇÃO - PASSAGEM BRASÍLIA X SÃO PAULO - CONSULTORA - CLAUDIA TAVARES FERNANDES (AGENDA 43218) | B8: 46235 | C8: 817991 | D8: CLAUDIA TAVARES FERNANDES | E8: -1605.3 | F8: LOCOMOÇÃO | G8: 46239 | H8: 1170 | J8: PASSAGEM BRASÍLIA X SÃO PAULO | K8: AGENDA 43218 | L8: CLAUDIA TAVARES FERNANDES | M8: CONSULTORA | N8: =VLOOKUP(H8,Clientes!B:D,3,) -> BGC LIQUIDEZ DTVM LTDA
A9: =CONCATENATE($J$1,J9,$I$3,M9,$I$3,L9,$I$1,K9,$I$2) -> DESPESA DE REPRESENTAÇÃO - PASSAGEM BRASÍLIA X SÃO PAULO - CONSULTOR - RENAN REIS CRUVINEL (AGENDA 43218) | B9: 46235 | C9: 817991 | D9: RENAN REIS CRUVINEL | E9: -1036.88 | F9: LOCOMOÇÃO | G9: 46239 | H9: 1170 | J9: PASSAGEM BRASÍLIA X SÃO PAULO | K9: AGENDA 43218 | L9: RENAN REIS CRUVINEL | M9: CONSULTOR | N9: =VLOOKUP(H9,Clientes!B:D,3,) -> BGC LIQUIDEZ DTVM LTDA
A10: =CONCATENATE($J$1,J10,$I$3,M10,$I$3,L10,$I$1,K10,$I$2) -> DESPESA DE REPRESENTAÇÃO - JANTAR - TRADER - BRUNO ACETOZE SCHIAVINATO (164011-3998PI) | B10: 46235 | C10: 817991 | D10: PAOLO FRANCA LIDA | E10: -2213 | F10: JANTAR | G10: 46240 | H10: 14479 | J10: JANTAR | K10: 164011-3998PI | L10: BRUNO ACETOZE SCHIAVINATO | M10: TRADER | N10: =VLOOKUP(H10,Clientes!B:D,3,) -> BANCO SANTANDER (BRASIL) S/A
A11: =CONCATENATE($J$1,J11,$I$3,M11,$I$3,L11,$I$1,K11,$I$2) -> DESPESA DE REPRESENTAÇÃO - ALMOÇO - TRADER - RODRIGO BRENDON (095304-3998EC) | B11: 46235 | C11: 817991 | D11: ENRICO BORTPLUZO CASSIANO | E11: -682 | F11: ALMOÇO | G11: 46240 | H11: 82467 | J11: ALMOÇO | K11: 095304-3998EC | L11: RODRIGO BRENDON | M11: TRADER | N11: =VLOOKUP(H11,Clientes!B:D,3,) -> BRAM - BRADESCO ASSET MANAGEMENT S/A DTVM
A12: =CONCATENATE($J$1,J12,$I$3,M12,$I$3,L12,$I$1,K12,$I$2) -> DESPESA DE REPRESENTAÇÃO - ALMOÇO - TRADER - MAURO OKUMA LACERDA (105829-3998EA) | B12: 46235 | C12: 817991 | D12: EDRAS DURAES D ANUNCIACAO | E12: -795 | F12: ALMOÇO | G12: 46240 | H12: 12413 | J12: ALMOÇO | K12: 105829-3998EA | L12: MAURO OKUMA LACERDA | M12: TRADER | N12: =VLOOKUP(H12,Clientes!B:D,3,) -> KAPITALO INVESTIMENTOS LTDA
A13: =CONCATENATE($J$1,J13,$I$3,M13,$I$3,L13,$I$1,K13,$I$2) -> DESPESA DE REPRESENTAÇÃO - ALMOÇO - TRADER - MAURO OKUMA LACERDA (105829-3998EA) | B13: 46235 | C13: 817991 | D13: FERNANDA CORVELLO BUTRICO | E13: -795 | F13: ALMOÇO | G13: 46240 | H13: 12413 | J13: ALMOÇO | K13: 105829-3998EA | L13: MAURO OKUMA LACERDA | M13: TRADER | N13: =VLOOKUP(H13,Clientes!B:D,3,) -> KAPITALO INVESTIMENTOS LTDA
A14: =CONCATENATE($J$1,J14,$I$3,M14,$I$3,L14,$I$1,K14,$I$2) -> DESPESA DE REPRESENTAÇÃO - ALMOÇO - TRADER - YAN FALCO (140457-3998EC) | B14: 46235 | C14: 817991 | D14: ENRICO BORTPLUZO CASSIANO | E14: -1165 | F14: ALMOÇO | G14: 46240 | H14: 79806 | J14: ALMOÇO | K14: 140457-3998EC | L14: YAN FALCO | M14: TRADER | N14: =VLOOKUP(H14,Clientes!B:D,3,) -> ITAU UNIBANCO S/A
A15: =CONCATENATE($J$1,J15,$I$3,M15,$I$3,L15,$I$1,K15,$I$2) -> DESPESA DE REPRESENTAÇÃO - ALMOÇO - TRADER - FELIPE NOVAES GARCIA (145408-3998AS) | B15: 46235 | C15: 817991 | D15: ALEXANDRE BRENO STEVENS | E15: -908 | F15: ALMOÇO | G15: 46240 | H15: 80573 | J15: ALMOÇO | K15: 145408-3998AS | L15: FELIPE NOVAES GARCIA | M15: TRADER | N15: =VLOOKUP(H15,Clientes!B:D,3,) -> BANCO C6 S/A
... A32: =CONCATENATE($J$1,J32,$I$3,M32,$I$3,L32,$I$1,K32,$I$2) -> DESPESA DE REPRESENTAÇÃO - ALUGUEL FLAT - GESTOR - ANDRE HALL ACCIOLY (AGENDA 43318) | B32: 46235 | C32: 817991 | D32: LIQUIDEZ-OTHER | E32: -2756.91 | F32: HOSPEDAGEM | G32: 46241 | H32: 1170 | J32: ALUGUEL FLAT | K32: AGENDA 43318 | L32: ANDRE HALL ACCIOLY | M32: GESTOR | N32: =VLOOKUP(H32,Clientes!B:D,3,) -> BGC LIQUIDEZ DTVM LTDA
A33: =CONCATENATE($J$1,J33,$I$3,M33,$I$3,L33,$I$1,K33,$I$2) -> DESPESA DE REPRESENTAÇÃO - ALUGUEL FLAT - BROKER - CHRISTIANO MARCONDES DE BARROS LIMA (AGENDA 43318) | B33: 46235 | C33: 817991 | D33: CHRISTIANO MARCONDES DE BARROS LIMA | E33: =E35/2 -> -843.1825 | F33: HOSPEDAGEM | G33: 46241 | H33: 1170 | J33: ALUGUEL FLAT | K33: AGENDA 43318 | L33: CHRISTIANO MARCONDES DE BARROS LIMA | M33: BROKER | N33: =VLOOKUP(H33,Clientes!B:D,3,) -> BGC LIQUIDEZ DTVM LTDA
A34: =CONCATENATE($J$1,J34,$I$3,M34,$I$3,L34,$I$1,K34,$I$2) -> DESPESA DE REPRESENTAÇÃO - ALUGUEL FLAT - BROKER - JOSE MAURICIO GOMES TEIXEIRA (AGENDA 43318) | B34: 46235 | C34: 817991 | D34: JOSE MAURICIO GOMES TEIXEIRA | E34: -843.1825 | F34: HOSPEDAGEM | G34: 46241 | H34: 1170 | J34: ALUGUEL FLAT | K34: AGENDA 43318 | L34: JOSE MAURICIO GOMES TEIXEIRA | M34: BROKER | N34: =VLOOKUP(H34,Clientes!B:D,3,) -> BGC LIQUIDEZ DTVM LTDA
A35: =CONCATENATE($J$1,J35,$I$3,M35,$I$3,L35,$I$1,K35,$I$2) -> DESPESA DE REPRESENTAÇÃO - ALUGUEL FLAT - GESTOR - ANDRE HALL ACCIOLY (AGENDA 43318) | B35: 46235 | C35: 817991 | D35: LIQUIDEZ-OTHER | E35: -1686.365 | F35: HOSPEDAGEM | G35: 46241 | H35: 1170 | J35: ALUGUEL FLAT | K35: AGENDA 43318 | L35: ANDRE HALL ACCIOLY | M35: GESTOR | N35: =VLOOKUP(H35,Clientes!B:D,3,) -> BGC LIQUIDEZ DTVM LTDA
A36: =CONCATENATE($J$1,J36,$I$3,M36,$I$3,L36,$I$1,K36,$I$2) -> DESPESA DE REPRESENTAÇÃO - REEMBOLSO REFERENTE AOS INGRESSOS DO JOGO ROLAND GARROS QUE FOI COMPRADO NO CARTÃO CORPORATIVO EM JUNHO E FORAM CANCELADOS - CEO - ERMINIO OLIVI LUCCI (AGENDA 43519) | B36: 46235 | C36: 817991 | D36: ERMINIO OLIVI LUCCI | E36: 23539.2 | F36: EVENTO | G36: 46244 | H36: 1170 | J36: REEMBOLSO REFERENTE AOS INGRESSOS DO JOGO ROLAND GARROS QUE FOI COMPRADO NO CARTÃO CORPORATIVO EM JUNHO E FORAM CANCELADOS | K36: AGENDA 43519 | L36: ERMINIO OLIVI LUCCI | M36: CEO | N36: =VLOOKUP(H36,Clientes!B:D,3,) -> BGC LIQUIDEZ DTVM LTDA
A37: =CONCATENATE($J$1,J37,$I$3,M37,$I$3,L37,$I$1,K37,$I$2) -> DESPESA DE REPRESENTAÇÃO - HOTEL PROMENADE PALLADIUM - TRADER - ERIC CHA-HUA (AGENDA 43374) | B37: 46235 | C37: 817991 | D37: CLAUDIO DE SOUZA PACINI | E37: -2644 | F37: HOSPEDAGEM | G37: 46246 | H37: 1170 | J37: HOTEL PROMENADE PALLADIUM | K37: AGENDA 43374 | L37: ERIC CHA-HUA | M37: TRADER | N37: =VLOOKUP(H37,Clientes!B:D,3,) -> BGC LIQUIDEZ DTVM LTDA
A38: =CONCATENATE($J$1,J38,$I$3,M38,$I$3,L38,$I$1,K38,$I$2) -> DESPESA DE REPRESENTAÇÃO - HOTEL RADISSON BLU SÃO PAULO - TRADER - FINNIAN THORNTON (AGENDA 43374) | B38: 46235 | C38: 817991 | D38: CLAUDIO DE SOUZA PACINI | E38: -2835.82 | F38: HOSPEDAGEM | G38: 46246 | H38: 1170 | J38: HOTEL RADISSON BLU SÃO PAULO | K38: AGENDA 43374 | L38: FINNIAN THORNTON | M38: TRADER | N38: =VLOOKUP(H38,Clientes!B:D,3,) -> BGC LIQUIDEZ DTVM LTDA
A39: =CONCATENATE($J$1,J39,$I$3,M39,$I$3,L39,$I$1,K39,$I$2) -> DESPESA DE REPRESENTAÇÃO - HOTEL PROMENADE PALLADIUM - TRADER - FINNIAN THORNTON (AGENDA 43374) | B39: 46235 | C39: 817991 | D39: CLAUDIO DE SOUZA PACINI | E39: -5288 | F39: HOSPEDAGEM | G39: 46246 | H39: 1170 | J39: HOTEL PROMENADE PALLADIUM | K39: AGENDA 43374 | L39: FINNIAN THORNTON | M39: TRADER | N39: =VLOOKUP(H39,Clientes!B:D,3,) -> BGC LIQUIDEZ DTVM LTDA
A40: =CONCATENATE($J$1,J40,$I$3,M40,$I$3,L40,$I$1,K40,$I$2) -> DESPESA DE REPRESENTAÇÃO - HOTEL RADISSON BLU SÃO PAULO - BROKER - CLAUDIO DE SOUZA PACINI (AGENDA 43374) | B40: 46235 | C40: 817991 | D40: CLAUDIO DE SOUZA PACINI | E40: -4422.81 | F40: HOSPEDAGEM | G40: 46246 | H40: 1170 | J40: HOTEL RADISSON BLU SÃO PAULO | K40: AGENDA 43374 | L40: CLAUDIO DE SOUZA PACINI | M40: BROKER | N40: =VLOOKUP(H40,Clientes!B:D,3,) -> BGC LIQUIDEZ DTVM LTDA
A41: =CONCATENATE($J$1,J41,$I$3,M41,$I$3,L41,$I$1,K41,$I$2) -> DESPESA DE REPRESENTAÇÃO - ALMOÇO - TRADER - PAULO DIEGO CETIN (082255-3998PI) | B41: 46235 | C41: 817991 | D41: PAOLO FRANCA LIDA | E41: -2258 | F41: ALMOÇO | G41: 46247 | H41: 95007 | J41: ALMOÇO | K41: 082255-3998PI | L41: PAULO DIEGO CETIN | M41: TRADER | N41: =VLOOKUP(H41,Clientes!B:D,3,) -> BANCO BNP PARIBAS BRASIL S/A
A42: =CONCATENATE($J$1,J42,$I$3,M42,$I$3,L42,$I$1,K42,$I$2) -> DESPESA DE REPRESENTAÇÃO - JANTAR - TRADER - RAFAEL PIROLO MADI (082155-3998PI) | B42: 46235 | C42: 817991 | D42: PAOLO FRANCA LIDA | E42: -1500 | F42: JANTAR | G42: 46247 | H42: 95007 | J42: JANTAR | K42: 082155-3998PI | L42: RAFAEL PIROLO MADI | M42: TRADER | N42: =VLOOKUP(H42,Clientes!B:D,3,) -> BANCO BNP PARIBAS BRASIL S/A
A43: =CONCATENATE($J$1,J43,$I$3,M43,$I$3,L43,$I$1,K43,$I$2) -> DESPESA DE REPRESENTAÇÃO - ALMOÇO - TRADER - MARCELO BRAGA COVO (122130-3998CL) | B43: 46235 | C43: 817991 | D43: CHRISTIANO MARCONDES DE BARROS LIMA | E43: -1767 | F43: ALMOÇO | G43: 46247 | H43: 80111 | J43: ALMOÇO | K43: 122130-3998CL | L43: MARCELO BRAGA COVO | M43: TRADER | N43: =VLOOKUP(H43,Clientes!B:D,3,) -> IBIUNA GESTAO DE RECURSOS LTDA
A44: =CONCATENATE($J$1,J44,$I$3,M44,$I$3,L44,$I$1,K44,$I$2) -> DESPESA DE REPRESENTAÇÃO - ALMOÇO - TRADER - FELIPE LOPES DE SOUZA (170741-3998AS) | B44: 46235 | C44: 817991 | D44: ALEXANDRE BRENO STEVENS | E44: -554 | F44: ALMOÇO | G44: 46247 | H44: 15501 | J44: ALMOÇO | K44: 170741-3998AS | L44: FELIPE LOPES DE SOUZA | M44: TRADER | N44: =VLOOKUP(H44,Clientes!B:D,3,) -> BANCO BTG PACTUAL S/A
A45: =CONCATENATE($J$1,J45,$I$3,M45,$I$3,L45,$I$1,K45,$I$2) -> DESPESA DE REPRESENTAÇÃO - ALMOÇO - TRADER - GUSTAVO MAZIERO (173708-3998RP) | B45: 46235 | C45: 817991 | D45: RODRIGO PENTAGNA | E45: -522 | F45: ALMOÇO | G45: 46247 | H45: 82841 | J45: ALMOÇO | K45: 173708-3998RP | L45: GUSTAVO MAZIERO | M45: TRADER | N45: =VLOOKUP(H45,Clientes!B:D,3,) -> LOGOS GESTAO DE RECURSOS LTDA.
... A158: =CONCATENATE($J$1,J158,$I$3,M158,$I$3,L158,$I$1,K158,$I$2) -> DESPESA DE REPRESENTAÇÃO - SERVIÇO DE ENTREGA E RETIRADA - BROKER - JUAREZ JOAQUIM DE LACERDA (AGENDA 43781) | B158: 46235 | C158: 817991 | D158: JUAREZ JOAQUIM DE LACERDA | E158: -40 | F158: OUTROS | G158: 46259 | H158: 1170 | J158: SERVIÇO DE ENTREGA E RETIRADA | K158: AGENDA 43781 | L158: JUAREZ JOAQUIM DE LACERDA | M158: BROKER | N158: =VLOOKUP(H158,Clientes!B:D,3,) -> BGC LIQUIDEZ DTVM LTDA

Sheet SET
A1: HISTORICO | B1: DATA COMPETENCIA | C1: CONTA CONTABIL | D1: BROKER | E1: VALOR | F1: FORNECEDOR | G1: DATA LANCAMENTO | H1: CLIENTE | I1: ( | J1: DESPESA DE REPRESENTAÇÃO - | K1: CODIGO | L1: CONVIDADO | M1: CARGO DO CONVIDADO | N1: RAZÃO SOCIAL
A2: =CONCATENATE($J$1,J2,$I$3,M2,$I$3,L2,$I$1,K2,$I$2) -> DESPESA DE REPRESENTAÇÃO - HAPPY HOUR COM CLIENTES EM JOGO DA COPA NO D'BRESCIA 24/06 - - (AGENDA 41306) | B2: 46266 | C2: 817991 | E2: -6170 | F2: EVENTO | G2: 46120 | H2: 1170 | I2: ) | J2: HAPPY HOUR COM CLIENTES EM JOGO DA COPA NO D'BRESCIA 24/06 | K2: AGENDA 41306 | N2: =VLOOKUP(H2,Clientes!B:D,3,) -> BGC LIQUIDEZ DTVM LTDA
A3: =CONCATENATE($J$1,J3,$I$3,M3,$I$3,L3,$I$1,K3,$I$2) -> DESPESA DE REPRESENTAÇÃO - HOTEL RADISSON BLU SÃO PAULO - CONSULTORIA - CLAUDIA TAVARES FERNANDES (AGENDA 43761) | B3: 46266 | C3: 817991 | D3: CLAUDIA TAVARES FERNANDES | E3: -2026.5 | F3: HOSPEDAGEM | G3: 46267 | H3: 1170 | I3: - | J3: HOTEL RADISSON BLU SÃO PAULO | K3: AGENDA 43761 | L3: CLAUDIA TAVARES FERNANDES | M3: CONSULTORIA | N3: =VLOOKUP(H3,Clientes!B:D,3,) -> BGC LIQUIDEZ DTVM LTDA | O3: =_xlfn.XLOOKUP(D3,'[1]Matriz Brokers'!$C:$C,'[1]Matriz Brokers'!$C:$C,0,0,1) -> 0
A4: =CONCATENATE($J$1,J4,$I$3,M4,$I$3,L4,$I$1,K4,$I$2) -> DESPESA DE REPRESENTAÇÃO - PASSAGEM BRASÍLIA X SÃO PAULO - CONSULTORIA - CLAUDIA TAVARES FERNANDES (AGENDA 43762) | B4: 46266 | C4: 817991 | D4: CLAUDIA TAVARES FERNANDES | E4: -2180.89 | F4: LOCOMOÇÃO | G4: 46267 | H4: 1170 | J4: PASSAGEM BRASÍLIA X SÃO PAULO | K4: AGENDA 43762 | L4: CLAUDIA TAVARES FERNANDES | M4: CONSULTORIA | N4: =VLOOKUP(H4,Clientes!B:D,3,) -> BGC LIQUIDEZ DTVM LTDA | O4: =_xlfn.XLOOKUP(D4,'[1]Matriz Brokers'!$C:$C,'[1]Matriz Brokers'!$C:$C,0,0,1) -> 0
A5: =CONCATENATE($J$1,J5,$I$3,M5,$I$3,L5,$I$1,K5,$I$2) -> DESPESA DE REPRESENTAÇÃO - PASSAGEM BRASÍLIA X SÃO PAULO - CONSULTORIA - CLAUDIA TAVARES FERNANDES (AGENDA 43762) | B5: 46266 | C5: 817991 | D5: CLAUDIA TAVARES FERNANDES | E5: -904.72 | F5: LOCOMOÇÃO | G5: 46267 | H5: 1170 | J5: PASSAGEM BRASÍLIA X SÃO PAULO | K5: AGENDA 43762 | L5: CLAUDIA TAVARES FERNANDES | M5: CONSULTORIA | N5: =VLOOKUP(H5,Clientes!B:D,3,) -> BGC LIQUIDEZ DTVM LTDA | O5: =_xlfn.XLOOKUP(D5,'[1]Matriz Brokers'!$C:$C,'[1]Matriz Brokers'!$C:$C,0,0,1) -> 0
A6: =CONCATENATE($J$1,J6,$I$3,M6,$I$3,L6,$I$1,K6,$I$2) -> DESPESA DE REPRESENTAÇÃO - PASSAGEM BRASÍLIA X SÃO PAULO - CONSULTORIA - RENAN REIS CRUVINEL (AGENDA 43762) | B6: 46266 | C6: 817991 | D6: RENAN REIS CRUVINEL | E6: -1766.76 | F6: LOCOMOÇÃO | G6: 46267 | H6: 1170 | J6: PASSAGEM BRASÍLIA X SÃO PAULO | K6: AGENDA 43762 | L6: RENAN REIS CRUVINEL | M6: CONSULTORIA | N6: =VLOOKUP(H6,Clientes!B:D,3,) -> BGC LIQUIDEZ DTVM LTDA | O6: =_xlfn.XLOOKUP(D6,'[1]Matriz Brokers'!$C:$C,'[1]Matriz Brokers'!$C:$C,0,0,1) -> 0
A7: =CONCATENATE($J$1,J7,$I$3,M7,$I$3,L7,$I$1,K7,$I$2) -> DESPESA DE REPRESENTAÇÃO - JANTAR - TRADER - JOAO PEDRO BESSA LIMA OLIVEIRA (175411-4120PI) | B7: 46266 | C7: 817991 | D7: PAOLO FRANCA LIDA | E7: -6777 | F7: JANTAR | G7: 46268 | H7: 81771 | J7: JANTAR | K7: 175411-4120PI | L7: JOAO PEDRO BESSA LIMA OLIVEIRA | M7: TRADER | N7: =VLOOKUP(H7,Clientes!B:D,3,) -> BANCO JP MORGAN S/A | O7: =_xlfn.XLOOKUP(D7,'[1]Matriz Brokers'!$C:$C,'[1]Matriz Brokers'!$C:$C,0,0,1) -> PAOLO FRANCA LIDA
A8: =CONCATENATE($J$1,J8,$I$3,M8,$I$3,L8,$I$1,K8,$I$2) -> DESPESA DE REPRESENTAÇÃO - PASSAGEM SÃO PAULO X MIAMI - CEO - ERMINIO OLIVI LUCCI (AGENDA 43845) | B8: 46266 | C8: 817991 | D8: ERMINIO OLIVI LUCCI | E8: -33010.21 | F8: LOCOMOÇÃO | G8: 46266 | H8: 1170 | J8: PASSAGEM SÃO PAULO X MIAMI | K8: AGENDA 43845 | L8: ERMINIO OLIVI LUCCI | M8: CEO | N8: =VLOOKUP(H8,Clientes!B:D,3,) -> BGC LIQUIDEZ DTVM LTDA | O8: =_xlfn.XLOOKUP(D8,'[1]Matriz Brokers'!$C:$C,'[1]Matriz Brokers'!$C:$C,0,0,1) -> ERMINIO OLIVI LUCCI
A9: =CONCATENATE($J$1,J9,$I$3,M9,$I$3,L9,$I$1,K9,$I$2) -> DESPESA DE REPRESENTAÇÃO - JANTAR - TRADER - ANDRE BENDIT (175624-4120PI) | B9: 46266 | C9: 817991 | D9: PAOLO FRANCA LIDA | E9: -1430 | F9: JANTAR | G9: 46268 | H9: 81972 | J9: JANTAR | K9: 175624-4120PI | L9: ANDRE BENDIT | M9: TRADER | N9: =VLOOKUP(H9,Clientes!B:D,3,) -> BANCO RABOBANK INTERNATIONAL BRASIL S/A | O9: =_xlfn.XLOOKUP(D9,'[1]Matriz Brokers'!$C:$C,'[1]Matriz Brokers'!$C:$C,0,0,1) -> PAOLO FRANCA LIDA
A10: =CONCATENATE($J$1,J10,$I$3,M10,$I$3,L10,$I$1,K10,$I$2) -> DESPESA DE REPRESENTAÇÃO - ALMOÇO - TRADER - ROMULO MAGALHAES BRASIL (175727-4120FB) | B10: 46266 | C10: 817991 | D10: FERNANDA CORVELLO BUTRICO | E10: -2401.25 | F10: ALMOÇO | G10: 46268 | H10: 79805 | J10: ALMOÇO | K10: 175727-4120FB | L10: ROMULO MAGALHAES BRASIL | M10: TRADER | N10: =VLOOKUP(H10,Clientes!B:D,3,) -> ITAU UNIBANCO S/A | O10: =_xlfn.XLOOKUP(D10,'[1]Matriz Brokers'!$C:$C,'[1]Matriz Brokers'!$C:$C,0,0,1) -> FERNANDA CORVELLO BUTRICO
A11: =CONCATENATE($J$1,J11,$I$3,M11,$I$3,L11,$I$1,K11,$I$2) -> DESPESA DE REPRESENTAÇÃO - ALMOÇO - TRADER - JOÃO AGUIAR (171220-4120EC) | B11: 46266 | C11: 817991 | D11: ENRICO BORTPLUZO CASSIANO | E11: -1238 | F11: ALMOÇO | G11: 46268 | H11: 82781 | J11: ALMOÇO | K11: 171220-4120EC | L11: JOÃO AGUIAR | M11: TRADER | N11: =VLOOKUP(H11,Clientes!B:D,3,) -> BTG PACTUAL ASSET MANAGEMENT SA DTVM | O11: =_xlfn.XLOOKUP(D11,'[1]Matriz Brokers'!$C:$C,'[1]Matriz Brokers'!$C:$C,0,0,1) -> ENRICO BORTPLUZO CASSIANO
A12: =CONCATENATE($J$1,J12,$I$3,M12,$I$3,L12,$I$1,K12,$I$2) -> DESPESA DE REPRESENTAÇÃO - CAFÉ DA MANHÃ - TRADER - CHRISTIAN FARICELLI (183709-4120FT) | B12: 46266 | C12: 817991 | D12: FELIPE DE SA TAVARES | E12: -201.14 | F12: CAFÉ DA MANHÃ | G12: 46268 | H12: 144548 | J12: CAFÉ DA MANHÃ | K12: 183709-4120FT | L12: CHRISTIAN FARICELLI | M12: TRADER | N12: =VLOOKUP(H12,Clientes!B:D,3,) -> ABSOLUTE GESTAO DE INVESTIMENTOS LTDA | O12: =_xlfn.XLOOKUP(D12,'[1]Matriz Brokers'!$C:$C,'[1]Matriz Brokers'!$C:$C,0,0,1) -> FELIPE DE SA TAVARES
A13: =CONCATENATE($J$1,J13,$I$3,M13,$I$3,L13,$I$1,K13,$I$2) -> DESPESA DE REPRESENTAÇÃO - JANTAR - ECONOMISTA - PEDRO FLORES (173355-4120FT) | B13: 46266 | C13: 817991 | D13: FELIPE DE SA TAVARES | E13: -972.93 | F13: JANTAR | G13: 46268 | H13: 81565 | J13: JANTAR | K13: 173355-4120FT | L13: PEDRO FLORES | M13: ECONOMISTA | N13: =VLOOKUP(H13,Clientes!B:D,3,) -> SPX GESTAO DE RECURSOS LTDA | O13: =_xlfn.XLOOKUP(D13,'[1]Matriz Brokers'!$C:$C,'[1]Matriz Brokers'!$C:$C,0,0,1) -> FELIPE DE SA TAVARES
A14: =CONCATENATE($J$1,J14,$I$3,M14,$I$3,L14,$I$1,K14,$I$2) -> DESPESA DE REPRESENTAÇÃO - ALMOÇO - TRADER - RODRIGO MELLO (181701-4120FT) | B14: 46266 | C14: 817991 | D14: FELIPE DE SA TAVARES | E14: -201.52 | F14: ALMOÇO | G14: 46268 | H14: 81344 | J14: ALMOÇO | K14: 181701-4120FT | L14: RODRIGO MELLO | M14: TRADER | N14: =VLOOKUP(H14,Clientes!B:D,3,) -> TENAX CAPITAL LTDA | O14: =_xlfn.XLOOKUP(D14,'[1]Matriz Brokers'!$C:$C,'[1]Matriz Brokers'!$C:$C,0,0,1) -> FELIPE DE SA TAVARES
A15: =CONCATENATE($J$1,J15,$I$3,M15,$I$3,L15,$I$1,K15,$I$2) -> DESPESA DE REPRESENTAÇÃO - UBER VISITA CLIENTES APRESENTAÇÃO ECONOMISTA - ECONOMISTA - CARLOS THADEU DE FREITAS GOMES FILHO (112748-4120CF) | B15: 46266 | C15: 817991 | D15: CARLOS THADEU DE FREITAS GOMES FILHO | E15: -173.98 | F15: LOCOMOÇÃO | G15: 46268 | H15: 83024 | J15: UBER VISITA CLIENTES APRESENTAÇÃO ECONOMISTA | K15: 112748-4120CF | L15: CARLOS THADEU DE FREITAS GOMES FILHO | M15: ECONOMISTA | N15: =VLOOKUP(H15,Clientes!B:D,3,) -> ITAU UNIBANCO ASSET MANAGEMENT LTDA | O15: =_xlfn.XLOOKUP(D15,'[1]Matriz Brokers'!$C:$C,'[1]Matriz Brokers'!$C:$C,0,0,1) -> CARLOS THADEU DE FREITAS GOMES FILHO
... A63: =CONCATENATE($J$1,J63,$I$3,M63,$I$3,L63,$I$1,K63,$I$2) -> DESPESA DE REPRESENTAÇÃO - JANTAR - TRADER - ROBERIO SOARES NUNES (080830-4120PI) | B63: 46266 | C63: 817991 | D63: PAOLO FRANCA LIDA | E63: -359 | F63: JANTAR | G63: 46275 | H63: 79798 | J63: JANTAR | K63: 080830-4120PI | L63: ROBERIO SOARES NUNES | M63: TRADER | N63: =VLOOKUP(H63,Clientes!B:D,3,) -> ITAU UNIBANCO S/A | O63: =_xlfn.XLOOKUP(D63,'[1]Matriz Brokers'!$C:$C,'[1]Matriz Brokers'!$C:$C,0,0,1) -> PAOLO FRANCA LIDA
A64: =CONCATENATE($J$1,J64,$I$3,M64,$I$3,L64,$I$1,K64,$I$2) -> DESPESA DE REPRESENTAÇÃO - 1/2 EVENTO KAITAI NO OIZUMI SUSHI - BROKER - HAMILTON DEL MONACO FILHO (AGENDA 44081) | B64: 46266 | C64: 817991 | D64: HAMILTON DEL MONACO FILHO | E64: -25230 | F64: EVENTO | G64: 46276 | H64: =_xlfn.XLOOKUP(SET!L64,Clientes!E:E,Clientes!B:B,0,0,1) -> 1170 | J64: 1/2 EVENTO KAITAI NO OIZUMI SUSHI | K64: AGENDA 44081 | L64: HAMILTON DEL MONACO FILHO | M64: =_xlfn.XLOOKUP(L64,Clientes!E:E,Clientes!F:F,0,0,1) -> BROKER | N64: =VLOOKUP(H64,Clientes!B:D,3,) -> BGC LIQUIDEZ DTVM LTDA | O64: =_xlfn.XLOOKUP(D64,'[1]Matriz Brokers'!$C:$C,'[1]Matriz Brokers'!$C:$C,0,0,1) -> HAMILTON DEL MONACO FILHO
A65: =CONCATENATE($J$1,J65,$I$3,M65,$I$3,L65,$I$1,K65,$I$2) -> DESPESA DE REPRESENTAÇÃO - CARTÃO CORPORATIVO NACIONAL - CEO - ERMINIO OLIVI LUCCI (AGENDA 44121) | B65: 46266 | C65: 817991 | D65: ERMINIO OLIVI LUCCI | E65: -6903.1 | F65: OUTROS | G65: 46280 | H65: =_xlfn.XLOOKUP(SET!L65,Clientes!E:E,Clientes!B:B,0,0,1) -> 1170 | J65: CARTÃO CORPORATIVO NACIONAL | K65: AGENDA 44121 | L65: ERMINIO OLIVI LUCCI | M65: =_xlfn.XLOOKUP(L65,Clientes!E:E,Clientes!F:F,0,0,1) -> CEO | N65: =VLOOKUP(H65,Clientes!B:D,3,) -> BGC LIQUIDEZ DTVM LTDA | O65: =_xlfn.XLOOKUP(D65,'[1]Matriz Brokers'!$C:$C,'[1]Matriz Brokers'!$C:$C,0,0,1) -> ERMINIO OLIVI LUCCI
A66: =CONCATENATE($J$1,J66,$I$3,M66,$I$3,L66,$I$1,K66,$I$2) -> DESPESA DE REPRESENTAÇÃO - CARTÃO CORPORATIVO INTERNACIONAL - CEO - ERMINIO OLIVI LUCCI (AGENDA 44121) | B66: 46266 | C66: 817991 | D66: ERMINIO OLIVI LUCCI | E66: -29308.4 | F66: OUTROS | G66: 46280 | H66: =_xlfn.XLOOKUP(SET!L66,Clientes!E:E,Clientes!B:B,0,0,1) -> 1170 | J66: CARTÃO CORPORATIVO INTERNACIONAL | K66: AGENDA 44121 | L66: ERMINIO OLIVI LUCCI | M66: =_xlfn.XLOOKUP(L66,Clientes!E:E,Clientes!F:F,0,0,1) -> CEO | N66: =VLOOKUP(H66,Clientes!B:D,3,) -> BGC LIQUIDEZ DTVM LTDA | O66: =_xlfn.XLOOKUP(D66,'[1]Matriz Brokers'!$C:$C,'[1]Matriz Brokers'!$C:$C,0,0,1) -> ERMINIO OLIVI LUCCI
A67: =CONCATENATE($J$1,J67,$I$3,M67,$I$3,L67,$I$1,K67,$I$2) -> DESPESA DE REPRESENTAÇÃO - ALMOÇO NO LOUP COM SIMONE TEBET - SALES - JOSE ANTONIO DEZENE JUNIOR (AGENDA 44121) | B67: 46266 | C67: 817991 | D67: JOSE ANTONIO DEZENE JUNIOR | E67: -4423.95 | F67: ALMOÇO | G67: 46280 | H67: =_xlfn.XLOOKUP(SET!L67,Clientes!E:E,Clientes!B:B,0,0,1) -> 1170 | J67: ALMOÇO NO LOUP COM SIMONE TEBET | K67: AGENDA 44121 | L67: JOSE ANTONIO DEZENE JUNIOR | M67: =_xlfn.XLOOKUP(L67,Clientes!E:E,Clientes!F:F,0,0,1) -> SALES | N67: =VLOOKUP(H67,Clientes!B:D,3,) -> BGC LIQUIDEZ DTVM LTDA | O67: =_xlfn.XLOOKUP(D67,'[1]Matriz Brokers'!$C:$C,'[1]Matriz Brokers'!$C:$C,0,0,1) -> JOSE ANTONIO DEZENE JUNIOR
A68: =CONCATENATE($J$1,J68,$I$3,M68,$I$3,L68,$I$1,K68,$I$2) -> DESPESA DE REPRESENTAÇÃO - PASSAGEM SÃO PAULO X RIO DE JANEIRO - BROKER - GUSTAVO D ELBOUX FERRIELLO (AGENDA 43944) | B68: 46266 | C68: 817991 | D68: GUSTAVO D ELBOUX FERRIELLO | E68: -1312 | F68: LOCOMOÇÃO | G68: 46280 | H68: =_xlfn.XLOOKUP(SET!L68,Clientes!E:E,Clientes!B:B,0,0,1) -> 1170 | J68: PASSAGEM SÃO PAULO X RIO DE JANEIRO | K68: AGENDA 43944 | L68: GUSTAVO D ELBOUX FERRIELLO | M68: =_xlfn.XLOOKUP(L68,Clientes!E:E,Clientes!F:F,0,0,1) -> BROKER | N68: =VLOOKUP(H68,Clientes!B:D,3,) -> BGC LIQUIDEZ DTVM LTDA | O68: =_xlfn.XLOOKUP(D68,'[1]Matriz Brokers'!$C:$C,'[1]Matriz Brokers'!$C:$C,0,0,1) -> GUSTAVO D ELBOUX FERRIELLO
A69: =CONCATENATE($J$1,J69,$I$3,M69,$I$3,L69,$I$1,K69,$I$2) -> DESPESA DE REPRESENTAÇÃO - PASSAGEM SÃO PAULO X RIO DE JANEIRO - BROKER - FERNANDA CORVELLO BUTRICO (AGENDA 43944) | B69: 46266 | C69: 817991 | D69: FERNANDA CORVELLO BUTRICO | E69: -1498.83 | F69: LOCOMOÇÃO | G69: 46280 | H69: =_xlfn.XLOOKUP(SET!L69,Clientes!E:E,Clientes!B:B,0,0,1) -> 1170 | J69: PASSAGEM SÃO PAULO X RIO DE JANEIRO | K69: AGENDA 43944 | L69: FERNANDA CORVELLO BUTRICO | M69: =_xlfn.XLOOKUP(L69,Clientes!E:E,Clientes!F:F,0,0,1) -> BROKER | N69: =VLOOKUP(H69,Clientes!B:D,3,) -> BGC LIQUIDEZ DTVM LTDA | O69: =_xlfn.XLOOKUP(D69,'[1]Matriz Brokers'!$C:$C,'[1]Matriz Brokers'!$C:$C,0,0,1) -> FERNANDA CORVELLO BUTRICO
A70: =CONCATENATE($J$1,J70,$I$3,M70,$I$3,L70,$I$1,K70,$I$2) -> DESPESA DE REPRESENTAÇÃO - PASSAGEM SÃO PAULO X RIO DE JANEIRO - ECONOMISTA - FELIPE DE SA TAVARES (AGENDA 43944) | B70: 46266 | C70: 817991 | D70: FELIPE DE SA TAVARES | E70: -1305.02 | F70: LOCOMOÇÃO | G70: 46280 | H70: =_xlfn.XLOOKUP(SET!L70,Clientes!E:E,Clientes!B:B,0,0,1) -> 1170 | J70: PASSAGEM SÃO PAULO X RIO DE JANEIRO | K70: AGENDA 43944 | L70: FELIPE DE SA TAVARES | M70: =_xlfn.XLOOKUP(L70,Clientes!E:E,Clientes!F:F,0,0,1) -> ECONOMISTA | N70: =VLOOKUP(H70,Clientes!B:D,3,) -> BGC LIQUIDEZ DTVM LTDA | O70: =_xlfn.XLOOKUP(D70,'[1]Matriz Brokers'!$C:$C,'[1]Matriz Brokers'!$C:$C,0,0,1) -> FELIPE DE SA TAVARES
A71: =CONCATENATE($J$1,J71,$I$3,M71,$I$3,L71,$I$1,K71,$I$2) -> DESPESA DE REPRESENTAÇÃO - PASSAGEM SÃO PAULO X BRASÍLIA - SALES - MARCELLE DA SILVEIRA GIL CADILHE (AGENDA 43944) | B71: 46266 | C71: 817991 | D71: JOSE ANTONIO DEZENE JUNIOR | E71: -3104.41 | F71: LOCOMOÇÃO | G71: 46280 | H71: =_xlfn.XLOOKUP(SET!L71,Clientes!E:E,Clientes!B:B,0,0,1) -> 1170 | J71: PASSAGEM SÃO PAULO X BRASÍLIA | K71: AGENDA 43944 | L71: MARCELLE DA SILVEIRA GIL CADILHE | M71: =_xlfn.XLOOKUP(L71,Clientes!E:E,Clientes!F:F,0,0,1) -> SALES | N71: =VLOOKUP(H71,Clientes!B:D,3,) -> BGC LIQUIDEZ DTVM LTDA | O71: =_xlfn.XLOOKUP(D71,'[1]Matriz Brokers'!$C:$C,'[1]Matriz Brokers'!$C:$C,0,0,1) -> JOSE ANTONIO DEZENE JUNIOR
A72: =CONCATENATE($J$1,J72,$I$3,M72,$I$3,L72,$I$1,K72,$I$2) -> DESPESA DE REPRESENTAÇÃO - PASSAGEM SÃO PAULO X RIO DE JANEIRO - BROKER - CHRISTIANO MARCONDES DE BARROS LIMA (AGENDA 43944) | B72: 46266 | C72: 817991 | D72: CHRISTIANO MARCONDES DE BARROS LIMA | E72: -269.15 | F72: LOCOMOÇÃO | G72: 46280 | H72: =_xlfn.XLOOKUP(SET!L72,Clientes!E:E,Clientes!B:B,0,0,1) -> 1170 | J72: PASSAGEM SÃO PAULO X RIO DE JANEIRO | K72: AGENDA 43944 | L72: CHRISTIANO MARCONDES DE BARROS LIMA | M72: =_xlfn.XLOOKUP(L72,Clientes!E:E,Clientes!F:F,0,0,1) -> BROKER | N72: =VLOOKUP(H72,Clientes!B:D,3,) -> BGC LIQUIDEZ DTVM LTDA | O72: =_xlfn.XLOOKUP(D72,'[1]Matriz Brokers'!$C:$C,'[1]Matriz Brokers'!$C:$C,0,0,1) -> CHRISTIANO MARCONDES DE BARROS LIMA
A73: =CONCATENATE($J$1,J73,$I$3,M73,$I$3,L73,$I$1,K73,$I$2) -> DESPESA DE REPRESENTAÇÃO - PASSAGEM SÃO PAULO X RIO DE JANEIRO - BROKER - CHRISTIANO MARCONDES DE BARROS LIMA (AGENDA 43944) | B73: 46266 | C73: 817991 | D73: CHRISTIANO MARCONDES DE BARROS LIMA | E73: -828.67 | F73: LOCOMOÇÃO | G73: 46280 | H73: =_xlfn.XLOOKUP(SET!L73,Clientes!E:E,Clientes!B:B,0,0,1) -> 1170 | J73: PASSAGEM SÃO PAULO X RIO DE JANEIRO | K73: AGENDA 43944 | L73: CHRISTIANO MARCONDES DE BARROS LIMA | M73: =_xlfn.XLOOKUP(L73,Clientes!E:E,Clientes!F:F,0,0,1) -> BROKER | N73: =VLOOKUP(H73,Clientes!B:D,3,) -> BGC LIQUIDEZ DTVM LTDA | O73: =_xlfn.XLOOKUP(D73,'[1]Matriz Brokers'!$C:$C,'[1]Matriz Brokers'!$C:$C,0,0,1) -> CHRISTIANO MARCONDES DE BARROS LIMA
A74: =CONCATENATE($J$1,J74,$I$3,M74,$I$3,L74,$I$1,K74,$I$2) -> DESPESA DE REPRESENTAÇÃO - PASSAGEM SÃO PAULO X RIO DE JANEIRO - BROKER - RODRIGO ZARKO VITAL BRASIL (AGENDA 43944) | B74: 46266 | C74: 817991 | D74: CHRISTIANO MARCONDES DE BARROS LIMA | E74: -953.92 | F74: LOCOMOÇÃO | G74: 46280 | H74: =_xlfn.XLOOKUP(SET!L74,Clientes!E:E,Clientes!B:B,0,0,1) -> 1170 | J74: PASSAGEM SÃO PAULO X RIO DE JANEIRO | K74: AGENDA 43944 | L74: RODRIGO ZARKO VITAL BRASIL | M74: =_xlfn.XLOOKUP(L74,Clientes!E:E,Clientes!F:F,0,0,1) -> BROKER | N74: =VLOOKUP(H74,Clientes!B:D,3,) -> BGC LIQUIDEZ DTVM LTDA | O74: =_xlfn.XLOOKUP(D74,'[1]Matriz Brokers'!$C:$C,'[1]Matriz Brokers'!$C:$C,0,0,1) -> CHRISTIANO MARCONDES DE BARROS LIMA
A75: =CONCATENATE($J$1,J75,$I$3,M75,$I$3,L75,$I$1,K75,$I$2) -> DESPESA DE REPRESENTAÇÃO - PASSAGEM SÃO PAULO X RIO DE JANEIRO - BROKER - JOSE MAURICIO GOMES TEIXEIRA (AGENDA 43944) | B75: 46266 | C75: 817991 | D75: JOSE MAURICIO GOMES TEIXEIRA | E75: -548.13 | F75: LOCOMOÇÃO | G75: 46280 | H75: =_xlfn.XLOOKUP(SET!L75,Clientes!E:E,Clientes!B:B,0,0,1) -> 1170 | J75: PASSAGEM SÃO PAULO X RIO DE JANEIRO | K75: AGENDA 43944 | L75: JOSE MAURICIO GOMES TEIXEIRA | M75: =_xlfn.XLOOKUP(L75,Clientes!E:E,Clientes!F:F,0,0,1) -> BROKER | N75: =VLOOKUP(H75,Clientes!B:D,3,) -> BGC LIQUIDEZ DTVM LTDA | O75: =_xlfn.XLOOKUP(D75,'[1]Matriz Brokers'!$C:$C,'[1]Matriz Brokers'!$C:$C,0,0,1) -> JOSE MAURICIO GOMES TEIXEIRA
... A81: =CONCATENATE($J$1,J81,$I$3,M81,$I$3,L81,$I$1,K81,$I$2) -> DESPESA DE REPRESENTAÇÃO - ALMOÇO - TRADER - GUILHERME PACHECO (100626-4185GF) | B81: 46266 | C81: 817991 | D81: GUSTAVO D ELBOUX FERRIELLO | E81: -2762.3 | F81: ALMOÇO | G81: 46282 | H81: =_xlfn.XLOOKUP(SET!L81,Clientes!E:E,Clientes!B:B,0,0,1) -> 15781 | J81: ALMOÇO | K81: 100626-4185GF | L81: GUILHERME PACHECO | M81: =_xlfn.XLOOKUP(L81,Clientes!E:E,Clientes!F:F,0,0,1) -> TRADER | N81: =VLOOKUP(H81,Clientes!B:D,3,) -> BANCO SAFRA S/A | O81: =_xlfn.XLOOKUP(D81,'[1]Matriz Brokers'!$C:$C,'[1]Matriz Brokers'!$C:$C,0,0,1) -> GUSTAVO D ELBOUX FERRIELLO
A82: =CONCATENATE($J$1,J82,$I$3,M82,$I$3,L82,$I$1,K82,$I$2) -> DESPESA DE REPRESENTAÇÃO - HAPPY HOUR - TRADER - GUILHERME NOGUEIRA (163110-4185EC) | B82: 46266 | C82: 817991 | D82: ENRICO BORTPLUZO CASSIANO | E82: -1975 | F82: EVENTO | G82: 46282 | H82: 83024 | J82: HAPPY HOUR | K82: 163110-4185EC | L82: GUILHERME NOGUEIRA | M82: TRADER | N82: =VLOOKUP(H82,Clientes!B:D,3,) -> ITAU UNIBANCO ASSET MANAGEMENT LTDA | O82: =_xlfn.XLOOKUP(D82,'[1]Matriz Brokers'!$C:$C,'[1]Matriz Brokers'!$C:$C,0,0,1) -> ENRICO BORTPLUZO CASSIANO
A83: =CONCATENATE($J$1,J83,$I$3,M83,$I$3,L83,$I$1,K83,$I$2) -> DESPESA DE REPRESENTAÇÃO - ALMOÇO - TRADER - GABRIEL GODOY CAMILO (091054-4185PI) | B83: 46266 | C83: 817991 | D83: PAOLO FRANCA LIDA | E83: -1377 | F83: ALMOÇO | G83: 46282 | H83: =_xlfn.XLOOKUP(SET!L83,Clientes!E:E,Clientes!B:B,0,0,1) -> 79407 | J83: ALMOÇO | K83: 091054-4185PI | L83: GABRIEL GODOY CAMILO | M83: =_xlfn.XLOOKUP(L83,Clientes!E:E,Clientes!F:F,0,0,1) -> TRADER | N83: =VLOOKUP(H83,Clientes!B:D,3,) -> BANCO MORGAN STANLEY S/A | O83: =_xlfn.XLOOKUP(D83,'[1]Matriz Brokers'!$C:$C,'[1]Matriz Brokers'!$C:$C,0,0,1) -> PAOLO FRANCA LIDA
A84: =CONCATENATE($J$1,J84,$I$3,M84,$I$3,L84,$I$1,K84,$I$2) -> DESPESA DE REPRESENTAÇÃO - ALMOÇO COM WARREN BRASIL - TRADER - GABRIEL KRAUSS (173143-4185EC) | B84: 46266 | C84: 817991 | D84: ENRICO BORTPLUZO CASSIANO | E84: -422 | F84: ALMOÇO | G84: 46282 | H84: 1170 | J84: ALMOÇO COM WARREN BRASIL | K84: 173143-4185EC | L84: GABRIEL KRAUSS | M84: TRADER | N84: =VLOOKUP(H84,Clientes!B:D,3,) -> BGC LIQUIDEZ DTVM LTDA | O84: =_xlfn.XLOOKUP(D84,'[1]Matriz Brokers'!$C:$C,'[1]Matriz Brokers'!$C:$C,0,0,1) -> ENRICO BORTPLUZO CASSIANO
A85: =CONCATENATE($J$1,J85,$I$3,M85,$I$3,L85,$I$1,K85,$I$2) -> DESPESA DE REPRESENTAÇÃO - ALMOÇO - TRADER - ANDRE ELIAS VAZQUEZ FADUL (135940-4185JT) | B85: 46266 | C85: 817991 | D85: JOSE MAURICIO GOMES TEIXEIRA | E85: -1156 | F85: ALMOÇO | G85: 46282 | H85: =_xlfn.XLOOKUP(SET!L85,Clientes!E:E,Clientes!B:B,0,0,1) -> 81767 | J85: ALMOÇO | K85: 135940-4185JT | L85: ANDRE ELIAS VAZQUEZ FADUL | M85: =_xlfn.XLOOKUP(L85,Clientes!E:E,Clientes!F:F,0,0,1) -> TRADER | N85: =VLOOKUP(H85,Clientes!B:D,3,) -> SAFRA DISTRIBUIDORA DE TITULOS E VALORES MOBILIARIOS LTDA. | O85: =_xlfn.XLOOKUP(D85,'[1]Matriz Brokers'!$C:$C,'[1]Matriz Brokers'!$C:$C,0,0,1) -> JOSE MAURICIO GOMES TEIXEIRA
A86: =CONCATENATE($J$1,J86,$I$3,M86,$I$3,L86,$I$1,K86,$I$2) -> DESPESA DE REPRESENTAÇÃO - ALMOÇO - TRADER - CARLOS R DE MENEZES JUNIOR (143538-4185RR) | B86: 46266 | C86: 817991 | D86: RICARDO ANDRE VASCONCELOS RAMOS | E86: -1759.41 | F86: ALMOÇO | G86: 46282 | H86: =_xlfn.XLOOKUP(SET!L86,Clientes!E:E,Clientes!B:B,0,0,1) -> 79258 | J86: ALMOÇO | K86: 143538-4185RR | L86: CARLOS R DE MENEZES JUNIOR | M86: =_xlfn.XLOOKUP(L86,Clientes!E:E,Clientes!F:F,0,0,1) -> TRADER | N86: =VLOOKUP(H86,Clientes!B:D,3,) -> ITAU UNIBANCO S/A | O86: =_xlfn.XLOOKUP(D86,'[1]Matriz Brokers'!$C:$C,'[1]Matriz Brokers'!$C:$C,0,0,1) -> RICARDO ANDRE VASCONCELOS RAMOS
A87: =CONCATENATE($J$1,J87,$I$3,M87,$I$3,L87,$I$1,K87,$I$2) -> DESPESA DE REPRESENTAÇÃO - JANTAR - TRADER - BRUNO B PEROTTONI (124518-4185JV) | B87: 46266 | C87: 817991 | D87: JOSÉ VERGARA | E87: -1523.78 | F87: JANTAR | G87: 46282 | H87: =_xlfn.XLOOKUP(SET!L87,Clientes!E:E,Clientes!B:B,0,0,1) -> 81794 | J87: JANTAR | K87: 124518-4185JV | L87: BRUNO B PEROTTONI | M87: =_xlfn.XLOOKUP(L87,Clientes!E:E,Clientes!F:F,0,0,1) -> TRADER | N87: =VLOOKUP(H87,Clientes!B:D,3,) -> BRAZA BANK S/A BANCO DE CAMBIO | O87: =_xlfn.XLOOKUP(D87,'[1]Matriz Brokers'!$C:$C,'[1]Matriz Brokers'!$C:$C,0,0,1) -> JOSÉ VERGARA
A88: =CONCATENATE($J$1,J88,$I$3,M88,$I$3,L88,$I$1,K88,$I$2) -> DESPESA DE REPRESENTAÇÃO - ALMOÇO - TRADER - LUCAS TERAMOSSI (124459-4185RC) | B88: 46266 | C88: 817991 | D88: RAFAEL TENORIO CAVALCANTI | E88: -1306 | F88: ALMOÇO | G88: 46282 | H88: 79978 | J88: ALMOÇO | K88: 124459-4185RC | L88: LUCAS TERAMOSSI | M88: TRADER | N88: =VLOOKUP(H88,Clientes!B:D,3,) -> CREDIT SUISSE (BRASIL) S/A CTVM | O88: =_xlfn.XLOOKUP(D88,'[1]Matriz Brokers'!$C:$C,'[1]Matriz Brokers'!$C:$C,0,0,1) -> RAFAEL TENORIO CAVALCANTI
A89: =CONCATENATE($J$1,J89,$I$3,M89,$I$3,L89,$I$1,K89,$I$2) -> DESPESA DE REPRESENTAÇÃO - JANTAR - TRADER - GUSTAVO MENDES (083907-4120VP) | B89: 46266 | C89: 817991 | D89: ALEXANDRE DA COSTA SOARES | E89: -1134 | F89: JANTAR | G89: 46282 | H89: K | J89: JANTAR | K89: 083907-4120VP | L89: GUSTAVO MENDES | M89: TRADER | N89: =VLOOKUP(H89,Clientes!B:D,3,) -> #N/A | O89: =_xlfn.XLOOKUP(D89,'[1]Matriz Brokers'!$C:$C,'[1]Matriz Brokers'!$C:$C,0,0,1) -> ALEXANDRE DA COSTA SOARES
A90: =CONCATENATE($J$1,J90,$I$3,M90,$I$3,L90,$I$1,K90,$I$2) -> DESPESA DE REPRESENTAÇÃO - ALMOÇO - TRADER - LEONARDO (143129-4120RR) | B90: 46266 | C90: 817991 | D90: RICARDO ANDRE VASCONCELOS RAMOS | E90: -682.52 | F90: ALMOÇO | G90: 46282 | H90: 82963 | J90: ALMOÇO | K90: 143129-4120RR | L90: LEONARDO | M90: TRADER | N90: =VLOOKUP(H90,Clientes!B:D,3,) -> BANCO DAYCOVAL S/A | O90: =_xlfn.XLOOKUP(D90,'[1]Matriz Brokers'!$C:$C,'[1]Matriz Brokers'!$C:$C,0,0,1) -> RICARDO ANDRE VASCONCELOS RAMOS
A91: =CONCATENATE($J$1,J91,$I$3,M91,$I$3,L91,$I$1,K91,$I$2) -> DESPESA DE REPRESENTAÇÃO - JANTAR - TRADER - PEDRO REIS (093815-4120MP) | B91: 46266 | C91: 817991 | D91: MARYLIA CARVALHO PONCE | E91: -1672.4 | F91: JANTAR | G91: 46282 | H91: 12413 | J91: JANTAR | K91: 093815-4120MP | L91: PEDRO REIS | M91: TRADER | N91: =VLOOKUP(H91,Clientes!B:D,3,) -> KAPITALO INVESTIMENTOS LTDA | O91: =_xlfn.XLOOKUP(D91,'[1]Matriz Brokers'!$C:$C,'[1]Matriz Brokers'!$C:$C,0,0,1) -> MARYLIA CARVALHO PONCE
A92: =CONCATENATE($J$1,J92,$I$3,M92,$I$3,L92,$I$1,K92,$I$2) -> DESPESA DE REPRESENTAÇÃO - JANTAR - TRADER - ERISON RODRIGUES DE SOUZA (170510-4185AS) | B92: 46266 | C92: 817991 | D92: ANDRE FERREIRA DOS SANTOS | E92: -881.4 | F92: JANTAR | G92: 46282 | H92: =_xlfn.XLOOKUP(SET!L92,Clientes!E:E,Clientes!B:B,0,0,1) -> 80111 | J92: JANTAR | K92: 170510-4185AS | L92: ERISON RODRIGUES DE SOUZA | M92: =_xlfn.XLOOKUP(L92,Clientes!E:E,Clientes!F:F,0,0,1) -> TRADER | N92: =VLOOKUP(H92,Clientes!B:D,3,) -> IBIUNA GESTAO DE RECURSOS LTDA | O92: =_xlfn.XLOOKUP(D92,'[1]Matriz Brokers'!$C:$C,'[1]Matriz Brokers'!$C:$C,0,0,1) -> ANDRE FERREIRA DOS SANTOS
A93: =CONCATENATE($J$1,J93,$I$3,M93,$I$3,L93,$I$1,K93,$I$2) -> DESPESA DE REPRESENTAÇÃO - ALMOÇO - TRADER - RENAN (162247-4120RU) | B93: 46266 | C93: 817991 | D93: REINALDO ANDRE URBANO FILHO | E93: -1243.15 | F93: ALMOÇO | G93: 46282 | H93: 82963 | J93: ALMOÇO | K93: 162247-4120RU | L93: RENAN | M93: TRADER | N93: =VLOOKUP(H93,Clientes!B:D,3,) -> BANCO DAYCOVAL S/A | O93: =_xlfn.XLOOKUP(D93,'[1]Matriz Brokers'!$C:$C,'[1]Matriz Brokers'!$C:$C,0,0,1) -> REINALDO ANDRE URBANO FILHO
A94: =CONCATENATE($J$1,J94,$I$3,M94,$I$3,L94,$I$1,K94,$I$2) -> DESPESA DE REPRESENTAÇÃO - ALMOÇO - TRADER - RAFAEL PAIVA POPPE DO VALLE (162450-4120RU) | B94: 46266 | C94: 817991 | D94: REINALDO ANDRE URBANO FILHO | E94: -562.79 | F94: ALMOÇO | G94: 46282 | H94: =_xlfn.XLOOKUP(SET!L94,Clientes!E:E,Clientes!B:B,0,0,1) -> 12413 | J94: ALMOÇO | K94: 162450-4120RU | L94: RAFAEL PAIVA POPPE DO VALLE | M94: =_xlfn.XLOOKUP(L94,Clientes!E:E,Clientes!F:F,0,0,1) -> TRADER | N94: =VLOOKUP(H94,Clientes!B:D,3,) -> KAPITALO INVESTIMENTOS LTDA | O94: =_xlfn.XLOOKUP(D94,'[1]Matriz Brokers'!$C:$C,'[1]Matriz Brokers'!$C:$C,0,0,1) -> REINALDO ANDRE URBANO FILHO
A95: =CONCATENATE($J$1,J95,$I$3,M95,$I$3,L95,$I$1,K95,$I$2) -> DESPESA DE REPRESENTAÇÃO - JANTAR - TRADER - BRUNO ACETOZE SCHIAVINATO (090803-4185PI) | B95: 46266 | C95: 817991 | D95: PAOLO FRANCA LIDA | E95: -2153 | F95: JANTAR | G95: 46282 | H95: =_xlfn.XLOOKUP(SET!L95,Clientes!E:E,Clientes!B:B,0,0,1) -> 14479 | J95: JANTAR | K95: 090803-4185PI | L95: BRUNO ACETOZE SCHIAVINATO | M95: =_xlfn.XLOOKUP(L95,Clientes!E:E,Clientes!F:F,0,0,1) -> TRADER | N95: =VLOOKUP(H95,Clientes!B:D,3,) -> BANCO SANTANDER (BRASIL) S/A | O95: =_xlfn.XLOOKUP(D95,'[1]Matriz Brokers'!$C:$C,'[1]Matriz Brokers'!$C:$C,0,0,1) -> PAOLO FRANCA LIDA
A96: =CONCATENATE($J$1,J96,$I$3,M96,$I$3,L96,$I$1,K96,$I$2) -> DESPESA DE REPRESENTAÇÃO - JANTAR - TRADER - KAUE GUIMARAES CHINELLATO (100306-4120RC) | B96: 46266 | C96: 817991 | D96: RAFAEL TENORIO CAVALCANTI | E96: -1042 | F96: JANTAR | G96: 46282 | H96: =_xlfn.XLOOKUP(SET!L96,Clientes!E:E,Clientes!B:B,0,0,1) -> 14334 | J96: JANTAR | K96: 100306-4120RC | L96: KAUE GUIMARAES CHINELLATO | M96: =_xlfn.XLOOKUP(L96,Clientes!E:E,Clientes!F:F,0,0,1) -> TRADER | N96: =VLOOKUP(H96,Clientes!B:D,3,) -> BANCO SOCIETE GENERALE BRASIL S/A | O96: =_xlfn.XLOOKUP(D96,'[1]Matriz Brokers'!$C:$C,'[1]Matriz Brokers'!$C:$C,0,0,1) -> RAFAEL TENORIO CAVALCANTI
A97: =CONCATENATE($J$1,J97,$I$3,M97,$I$3,L97,$I$1,K97,$I$2) -> DESPESA DE REPRESENTAÇÃO - JANTAR - TRADER - HENRIQUE TEIXEIRA CASTAGNET (105111-4120FC) | B97: 46266 | C97: 817991 | D97: FRANCISCO JOSE DIAS CARVALHO | E97: -7444.19 | F97: JANTAR | G97: 46282 | H97: =_xlfn.XLOOKUP(SET!L97,Clientes!E:E,Clientes!B:B,0,0,1) -> 83577 | J97: JANTAR | K97: 105111-4120FC | L97: HENRIQUE TEIXEIRA CASTAGNET | M97: =_xlfn.XLOOKUP(L97,Clientes!E:E,Clientes!F:F,0,0,1) -> TRADER | N97: =VLOOKUP(H97,Clientes!B:D,3,) -> BANCO MIZUHO DO BRASIL S/A | O97: =_xlfn.XLOOKUP(D97,'[1]Matriz Brokers'!$C:$C,'[1]Matriz Brokers'!$C:$C,0,0,1) -> FRANCISCO JOSE DIAS CARVALHO
A98: =CONCATENATE($J$1,J98,$I$3,M98,$I$3,L98,$I$1,K98,$I$2) -> DESPESA DE REPRESENTAÇÃO - ALMOÇO - TRADER - GUSTAVO (162930-4120RU) | B98: 46266 | C98: 817991 | D98: REINALDO ANDRE URBANO FILHO | E98: -1557.59 | F98: ALMOÇO | G98: 46282 | H98: 12395 | J98: ALMOÇO | K98: 162930-4120RU | L98: GUSTAVO | M98: TRADER | N98: =VLOOKUP(H98,Clientes!B:D,3,) -> AZ QUEST INVESTIMENTOS LTDA | O98: =_xlfn.XLOOKUP(D98,'[1]Matriz Brokers'!$C:$C,'[1]Matriz Brokers'!$C:$C,0,0,1) -> REINALDO ANDRE URBANO FILHO
A99: =CONCATENATE($J$1,J99,$I$3,M99,$I$3,L99,$I$1,K99,$I$2) -> DESPESA DE REPRESENTAÇÃO - ALMOÇO - TRADER - MICHEL TECLA MICHELUTTI (162620-4120RU) | B99: 46266 | C99: 817991 | D99: REINALDO ANDRE URBANO FILHO | E99: -2622 | F99: ALMOÇO | G99: 46282 | H99: =_xlfn.XLOOKUP(SET!L99,Clientes!E:E,Clientes!B:B,0,0,1) -> 82597 | J99: ALMOÇO | K99: 162620-4120RU | L99: MICHEL TECLA MICHELUTTI | M99: =_xlfn.XLOOKUP(L99,Clientes!E:E,Clientes!F:F,0,0,1) -> TRADER | N99: =VLOOKUP(H99,Clientes!B:D,3,) -> PORTO SEGURO INVESTIMENTOS LTDA | O99: =_xlfn.XLOOKUP(D99,'[1]Matriz Brokers'!$C:$C,'[1]Matriz Brokers'!$C:$C,0,0,1) -> REINALDO ANDRE URBANO FILHO
A100: =CONCATENATE($J$1,J100,$I$3,M100,$I$3,L100,$I$1,K100,$I$2) -> DESPESA DE REPRESENTAÇÃO - HAPPY HOUR - TRADER - BRUNO SILVA CARVALHO (142721-4120GF) | B100: 46266 | C100: 817991 | D100: GUSTAVO D ELBOUX FERRIELLO | E100: -2267.82 | F100: EVENTO | G100: 46282 | H100: =_xlfn.XLOOKUP(SET!L100,Clientes!E:E,Clientes!B:B,0,0,1) -> 82639 | J100: HAPPY HOUR | K100: 142721-4120GF | L100: BRUNO SILVA CARVALHO | M100: =_xlfn.XLOOKUP(L100,Clientes!E:E,Clientes!F:F,0,0,1) -> TRADER | N100: =VLOOKUP(H100,Clientes!B:D,3,) -> SAFRA ASSET CORRETORA DE TITULOS E VALORES MOBILIARIOS S.A. | O100: =_xlfn.XLOOKUP(D100,'[1]Matriz Brokers'!$C:$C,'[1]Matriz Brokers'!$C:$C,0,0,1) -> GUSTAVO D ELBOUX FERRIELLO
A101: =CONCATENATE($J$1,J101,$I$3,M101,$I$3,L101,$I$1,K101,$I$2) -> DESPESA DE REPRESENTAÇÃO - JANTAR - TRADER - THALITA SOARES (093325-4120RC) | B101: 46266 | C101: 817991 | D101: RAFAEL TENORIO CAVALCANTI | E101: -1758 | F101: JANTAR | G101: 46282 | H101: 80749 | J101: JANTAR | K101: 093325-4120RC | L101: THALITA SOARES | M101: TRADER | N101: =VLOOKUP(H101,Clientes!B:D,3,) -> BANCO XP S/A | O101: =_xlfn.XLOOKUP(D101,'[1]Matriz Brokers'!$C:$C,'[1]Matriz Brokers'!$C:$C,0,0,1) -> RAFAEL TENORIO CAVALCANTI
A102: =CONCATENATE($J$1,J102,$I$3,M102,$I$3,L102,$I$1,K102,$I$2) -> DESPESA DE REPRESENTAÇÃO - HAPPY HOUR - TRADER - RODRIGO NOVARETTI (093506-4120RC) | B102: 46266 | C102: 817991 | D102: RAFAEL TENORIO CAVALCANTI | E102: -832 | F102: EVENTO | G102: 46282 | H102: 14479 | J102: HAPPY HOUR | K102: 093506-4120RC | L102: RODRIGO NOVARETTI | M102: TRADER | N102: =VLOOKUP(H102,Clientes!B:D,3,) -> BANCO SANTANDER (BRASIL) S/A | O102: =_xlfn.XLOOKUP(D102,'[1]Matriz Brokers'!$C:$C,'[1]Matriz Brokers'!$C:$C,0,0,1) -> RAFAEL TENORIO CAVALCANTI
A103: =CONCATENATE($J$1,J103,$I$3,M103,$I$3,L103,$I$1,K103,$I$2) -> DESPESA DE REPRESENTAÇÃO - ALUGUEL FLAT - BROKER - CHRISTIANO MARCONDES DE BARROS LIMA (AGENDA 44042) | B103: 46266 | C103: 817991 | D103: CHRISTIANO MARCONDES DE BARROS LIMA | E103: -1378.455 | F103: HOSPEDAGEM | G103: 46273 | H103: 1170 | J103: ALUGUEL FLAT | K103: AGENDA 44042 | L103: CHRISTIANO MARCONDES DE BARROS LIMA | M103: BROKER | N103: =VLOOKUP(H103,Clientes!B:D,3,) -> BGC LIQUIDEZ DTVM LTDA | O103: =_xlfn.XLOOKUP(D103,'[1]Matriz Brokers'!$C:$C,'[1]Matriz Brokers'!$C:$C,0,0,1) -> CHRISTIANO MARCONDES DE BARROS LIMA
A104: =CONCATENATE($J$1,J104,$I$3,M104,$I$3,L104,$I$1,K104,$I$2) -> DESPESA DE REPRESENTAÇÃO - ALUGUEL FLAT - BROKER - JOSE MAURICIO GOMES TEIXEIRA (AGENDA 44042) | B104: 46266 | C104: 817991 | D104: JOSE MAURICIO GOMES TEIXEIRA | E104: -1378.455 | F104: HOSPEDAGEM | G104: 46273 | H104: 1170 | J104: ALUGUEL FLAT | K104: AGENDA 44042 | L104: JOSE MAURICIO GOMES TEIXEIRA | M104: BROKER | N104: =VLOOKUP(H104,Clientes!B:D,3,) -> BGC LIQUIDEZ DTVM LTDA | O104: =_xlfn.XLOOKUP(D104,'[1]Matriz Brokers'!$C:$C,'[1]Matriz Brokers'!$C:$C,0,0,1) -> JOSE MAURICIO GOMES TEIXEIRA
A105: =CONCATENATE($J$1,J105,$I$3,M105,$I$3,L105,$I$1,K105,$I$2) -> DESPESA DE REPRESENTAÇÃO - ALUGUEL FLAT - GESTOR - ANDRE HALL ACCIOLY (AGENDA 44042) | B105: 46266 | C105: 817991 | D105: LIQUIDEZ-OTHER | E105: -2756.91 | F105: HOSPEDAGEM | G105: 46273 | H105: 1170 | J105: ALUGUEL FLAT | K105: AGENDA 44042 | L105: ANDRE HALL ACCIOLY | M105: GESTOR | N105: =VLOOKUP(H105,Clientes!B:D,3,) -> BGC LIQUIDEZ DTVM LTDA | O105: =_xlfn.XLOOKUP(D105,'[1]Matriz Brokers'!$C:$C,'[1]Matriz Brokers'!$C:$C,0,0,1) -> LIQUIDEZ-OTHER
A106: =CONCATENATE($J$1,J106,$I$3,M106,$I$3,L106,$I$1,K106,$I$2) -> DESPESA DE REPRESENTAÇÃO - ALUGUEL FLAT - BROKER - CHRISTIANO MARCONDES DE BARROS LIMA (AGENDA 44043) | B106: 46266 | C106: 817991 | D106: CHRISTIANO MARCONDES DE BARROS LIMA | E106: -843.1825 | F106: HOSPEDAGEM | G106: 46273 | H106: 1170 | J106: ALUGUEL FLAT | K106: AGENDA 44043 | L106: CHRISTIANO MARCONDES DE BARROS LIMA | M106: BROKER | N106: =VLOOKUP(H106,Clientes!B:D,3,) -> BGC LIQUIDEZ DTVM LTDA | O106: =_xlfn.XLOOKUP(D106,'[1]Matriz Brokers'!$C:$C,'[1]Matriz Brokers'!$C:$C,0,0,1) -> CHRISTIANO MARCONDES DE BARROS LIMA
A107: =CONCATENATE($J$1,J107,$I$3,M107,$I$3,L107,$I$1,K107,$I$2) -> DESPESA DE REPRESENTAÇÃO - ALUGUEL FLAT - BROKER - JOSE MAURICIO GOMES TEIXEIRA (AGENDA 44043) | B107: 46266 | C107: 817991 | D107: JOSE MAURICIO GOMES TEIXEIRA | E107: -843.1825 | F107: HOSPEDAGEM | G107: 46273 | H107: 1170 | J107: ALUGUEL FLAT | K107: AGENDA 44043 | L107: JOSE MAURICIO GOMES TEIXEIRA | M107: BROKER | N107: =VLOOKUP(H107,Clientes!B:D,3,) -> BGC LIQUIDEZ DTVM LTDA | O107: =_xlfn.XLOOKUP(D107,'[1]Matriz Brokers'!$C:$C,'[1]Matriz Brokers'!$C:$C,0,0,1) -> JOSE MAURICIO GOMES TEIXEIRA
A108: =CONCATENATE($J$1,J108,$I$3,M108,$I$3,L108,$I$1,K108,$I$2) -> DESPESA DE REPRESENTAÇÃO - ALUGUEL FLAT - GESTOR - ANDRE HALL ACCIOLY (AGENDA 44043) | B108: 46266 | C108: 817991 | D108: LIQUIDEZ-OTHER | E108: -1686.365 | F108: HOSPEDAGEM | G108: 46273 | H108: 1170 | J108: ALUGUEL FLAT | K108: AGENDA 44043 | L108: ANDRE HALL ACCIOLY | M108: GESTOR | N108: =VLOOKUP(H108,Clientes!B:D,3,) -> BGC LIQUIDEZ DTVM LTDA | O108: =_xlfn.XLOOKUP(D108,'[1]Matriz Brokers'!$C:$C,'[1]Matriz Brokers'!$C:$C,0,0,1) -> LIQUIDEZ-OTHER
A109: =CONCATENATE($J$1,J109,$I$3,M109,$I$3,L109,$I$1,K109,$I$2) -> DESPESA DE REPRESENTAÇÃO - ALMOÇO - TRADER - WILLIAM JUGEICK BUSSI (164847-3688RU) | B109: 46266 | C109: 817991 | D109: REINALDO ANDRE URBANO FILHO | E109: -1874.67 | F109: ALMOÇO | G109: 46282 | H109: =_xlfn.XLOOKUP(SET!L109,Clientes!E:E,Clientes!B:B,0,0,1) -> 79852 | J109: ALMOÇO | K109: 164847-3688RU | L109: WILLIAM JUGEICK BUSSI | M109: =_xlfn.XLOOKUP(L109,Clientes!E:E,Clientes!F:F,0,0,1) -> TRADER | N109: =VLOOKUP(H109,Clientes!B:D,3,) -> SANTANDER BRASIL GESTAO DE RECURSOS LTDA | O109: =_xlfn.XLOOKUP(D109,'[1]Matriz Brokers'!$C:$C,'[1]Matriz Brokers'!$C:$C,0,0,1) -> REINALDO ANDRE URBANO FILHO
A110: =CONCATENATE($J$1,J110,$I$3,M110,$I$3,L110,$I$1,K110,$I$2) -> DESPESA DE REPRESENTAÇÃO - ALMOÇO - TRADER - JOAO JABBOUR (172127-3998RU) | B110: 46266 | C110: 817991 | D110: REINALDO ANDRE URBANO FILHO | E110: -1897.27 | F110: ALMOÇO | G110: 46282 | H110: =_xlfn.XLOOKUP(SET!L110,Clientes!E:E,Clientes!B:B,0,0,1) -> 79793 | J110: ALMOÇO | K110: 172127-3998RU | L110: JOAO JABBOUR | M110: =_xlfn.XLOOKUP(L110,Clientes!E:E,Clientes!F:F,0,0,1) -> TRADER | N110: =VLOOKUP(H110,Clientes!B:D,3,) -> EMERALD GESTAO DE INVESTIMENTOS SOCIEDADE UNIPESSOAL LTDA | O110: =_xlfn.XLOOKUP(D110,'[1]Matriz Brokers'!$C:$C,'[1]Matriz Brokers'!$C:$C,0,0,1) -> REINALDO ANDRE URBANO FILHO
A111: =CONCATENATE($J$1,J111,$I$3,M111,$I$3,L111,$I$1,K111,$I$2) -> DESPESA DE REPRESENTAÇÃO - HOTEL EM NOVA YORK - CEO - ERMINIO OLIVI LUCCI (AGENDA 44216) | B111: 46266 | C111: 817991 | D111: ERMINIO OLIVI LUCCI | E111: -20498.11 | F111: HOSPEDAGEM | G111: 46283 | H111: =_xlfn.XLOOKUP(SET!L111,Clientes!E:E,Clientes!B:B,0,0,1) -> 1170 | J111: HOTEL EM NOVA YORK | K111: AGENDA 44216 | L111: ERMINIO OLIVI LUCCI | M111: =_xlfn.XLOOKUP(L111,Clientes!E:E,Clientes!F:F,0,0,1) -> CEO | N111: =VLOOKUP(H111,Clientes!B:D,3,) -> BGC LIQUIDEZ DTVM LTDA | O111: =_xlfn.XLOOKUP(D111,'[1]Matriz Brokers'!$C:$C,'[1]Matriz Brokers'!$C:$C,0,0,1) -> ERMINIO OLIVI LUCCI
A112: =CONCATENATE($J$1,J112,$I$3,M112,$I$3,L112,$I$1,K112,$I$2) -> DESPESA DE REPRESENTAÇÃO - PASSAGEM MIAMI X NOVA YORK - CEO - ERMINIO OLIVI LUCCI (AGENDA 44216) | B112: 46266 | C112: 817991 | D112: ERMINIO OLIVI LUCCI | E112: -2017.02 | F112: LOCOMOÇÃO | G112: 46283 | H112: =_xlfn.XLOOKUP(SET!L112,Clientes!E:E,Clientes!B:B,0,0,1) -> 1170 | J112: PASSAGEM MIAMI X NOVA YORK | K112: AGENDA 44216 | L112: ERMINIO OLIVI LUCCI | M112: =_xlfn.XLOOKUP(L112,Clientes!E:E,Clientes!F:F,0,0,1) -> CEO | N112: =VLOOKUP(H112,Clientes!B:D,3,) -> BGC LIQUIDEZ DTVM LTDA | O112: =_xlfn.XLOOKUP(D112,'[1]Matriz Brokers'!$C:$C,'[1]Matriz Brokers'!$C:$C,0,0,1) -> ERMINIO OLIVI LUCCI
A113: =CONCATENATE($J$1,J113,$I$3,M113,$I$3,L113,$I$1,K113,$I$2) -> DESPESA DE REPRESENTAÇÃO - TAXI - CEO - ERMINIO OLIVI LUCCI (AGENDA 44216) | B113: 46266 | C113: 817991 | D113: ERMINIO OLIVI LUCCI | E113: -5580 | F113: LOCOMOÇÃO | G113: 46283 | H113: =_xlfn.XLOOKUP(SET!L113,Clientes!E:E,Clientes!B:B,0,0,1) -> 1170 | J113: TAXI | K113: AGENDA 44216 | L113: ERMINIO OLIVI LUCCI | M113: =_xlfn.XLOOKUP(L113,Clientes!E:E,Clientes!F:F,0,0,1) -> CEO | N113: =VLOOKUP(H113,Clientes!B:D,3,) -> BGC LIQUIDEZ DTVM LTDA | O113: =_xlfn.XLOOKUP(D113,'[1]Matriz Brokers'!$C:$C,'[1]Matriz Brokers'!$C:$C,0,0,1) -> ERMINIO OLIVI LUCCI
A114: =CONCATENATE($J$1,J114,$I$3,M114,$I$3,L114,$I$1,K114,$I$2) -> DESPESA DE REPRESENTAÇÃO - TAXI CASA X AEROPORTO - CEO - ERMINIO OLIVI LUCCI (AGENDA 44216) | B114: 46266 | C114: 817991 | D114: ERMINIO OLIVI LUCCI | E114: -350 | F114: LOCOMOÇÃO | G114: 46283 | H114: =_xlfn.XLOOKUP(SET!L114,Clientes!E:E,Clientes!B:B,0,0,1) -> 1170 | J114: TAXI CASA X AEROPORTO | K114: AGENDA 44216 | L114: ERMINIO OLIVI LUCCI | M114: =_xlfn.XLOOKUP(L114,Clientes!E:E,Clientes!F:F,0,0,1) -> CEO | N114: =VLOOKUP(H114,Clientes!B:D,3,) -> BGC LIQUIDEZ DTVM LTDA | O114: =_xlfn.XLOOKUP(D114,'[1]Matriz Brokers'!$C:$C,'[1]Matriz Brokers'!$C:$C,0,0,1) -> ERMINIO OLIVI LUCCI
A115: =CONCATENATE($J$1,J115,$I$3,M115,$I$3,L115,$I$1,K115,$I$2) -> DESPESA DE REPRESENTAÇÃO - TAXI AEROPORTO X CASA - CEO - ERMINIO OLIVI LUCCI (AGENDA 44216) | B115: 46266 | C115: 817991 | D115: ERMINIO OLIVI LUCCI | E115: -350 | F115: LOCOMOÇÃO | G115: 46283 | H115: =_xlfn.XLOOKUP(SET!L115,Clientes!E:E,Clientes!B:B,0,0,1) -> 1170 | J115: TAXI AEROPORTO X CASA | K115: AGENDA 44216 | L115: ERMINIO OLIVI LUCCI | M115: =_xlfn.XLOOKUP(L115,Clientes!E:E,Clientes!F:F,0,0,1) -> CEO | N115: =VLOOKUP(H115,Clientes!B:D,3,) -> BGC LIQUIDEZ DTVM LTDA | O115: =_xlfn.XLOOKUP(D115,'[1]Matriz Brokers'!$C:$C,'[1]Matriz Brokers'!$C:$C,0,0,1) -> ERMINIO OLIVI LUCCI
A116: =CONCATENATE($J$1,J116,$I$3,M116,$I$3,L116,$I$1,K116,$I$2) -> DESPESA DE REPRESENTAÇÃO - MENSALIDADE DA ASSOCIAÇÃO AO WTC BUSSINESS CLUB - CEO - ERMINIO OLIVI LUCCI (AGENDA 43970) | B116: 46266 | C116: 817991 | D116: ERMINIO OLIVI LUCCI | E116: -2000 | F116: OUTROS | G116: 46286 | H116: 1170 | J116: MENSALIDADE DA ASSOCIAÇÃO AO WTC BUSSINESS CLUB | K116: AGENDA 43970 | L116: ERMINIO OLIVI LUCCI | M116: CEO | N116: =VLOOKUP(H116,Clientes!B:D,3,) -> BGC LIQUIDEZ DTVM LTDA | O116: =_xlfn.XLOOKUP(D116,'[1]Matriz Brokers'!$C:$C,'[1]Matriz Brokers'!$C:$C,0,0,1) -> ERMINIO OLIVI LUCCI
A117: =CONCATENATE($J$1,J117,$I$3,M117,$I$3,L117,$I$1,K117,$I$2) -> DESPESA DE REPRESENTAÇÃO - PASSAGEM SÃO PAULO X MIAMI - CEO - ERMINIO OLIVI LUCCI (AGENDA 44209) | B117: 46266 | C117: 817991 | D117: ERMINIO OLIVI LUCCI | E117: -29812.48 | F117: LOCOMOÇÃO | G117: 46287 | H117: =_xlfn.XLOOKUP(SET!L117,Clientes!E:E,Clientes!B:B,0,0,1) -> 1170 | J117: PASSAGEM SÃO PAULO X MIAMI | K117: AGENDA 44209 | L117: ERMINIO OLIVI LUCCI | M117: =_xlfn.XLOOKUP(L117,Clientes!E:E,Clientes!F:F,0,0,1) -> CEO | N117: =VLOOKUP(H117,Clientes!B:D,3,) -> BGC LIQUIDEZ DTVM LTDA | O117: =_xlfn.XLOOKUP(D117,'[1]Matriz Brokers'!$C:$C,'[1]Matriz Brokers'!$C:$C,0,0,1) -> ERMINIO OLIVI LUCCI
A118: =CONCATENATE($J$1,J118,$I$3,M118,$I$3,L118,$I$1,K118,$I$2) -> DESPESA DE REPRESENTAÇÃO - PASSAGEM SÃO PAULO X RIO DE JANEIRO - CONSULTORIA - CLAUDIA TAVARES FERNANDES (AGENDA 44185) | B118: 46266 | C118: 817991 | D118: CLAUDIA TAVARES FERNANDES | E118: -2462.07 | F118: LOCOMOÇÃO | G118: 46288 | H118: =_xlfn.XLOOKUP(SET!L118,Clientes!E:E,Clientes!B:B,0,0,1) -> 1170 | J118: PASSAGEM SÃO PAULO X RIO DE JANEIRO | K118: AGENDA 44185 | L118: CLAUDIA TAVARES FERNANDES | M118: =_xlfn.XLOOKUP(L118,Clientes!E:E,Clientes!F:F,0,0,1) -> CONSULTORIA | N118: =VLOOKUP(H118,Clientes!B:D,3,) -> BGC LIQUIDEZ DTVM LTDA | O118: =_xlfn.XLOOKUP(D118,'[1]Matriz Brokers'!$C:$C,'[1]Matriz Brokers'!$C:$C,0,0,1) -> 0
A119: =CONCATENATE($J$1,J119,$I$3,M119,$I$3,L119,$I$1,K119,$I$2) -> DESPESA DE REPRESENTAÇÃO - HOTEL EM CURITIBA BRISTOL CENTRO CIVICO - BROKER - JOSÉ VERGARA (AGENDA 44186) | B119: 46266 | C119: 817991 | D119: JOSÉ VERGARA | E119: -304.5 | F119: HOSPEDAGEM | G119: 46288 | H119: =_xlfn.XLOOKUP(SET!L119,Clientes!E:E,Clientes!B:B,0,0,1) -> 1170 | J119: HOTEL EM CURITIBA BRISTOL CENTRO CIVICO | K119: AGENDA 44186 | L119: JOSÉ VERGARA | M119: =_xlfn.XLOOKUP(L119,Clientes!E:E,Clientes!F:F,0,0,1) -> BROKER | N119: =VLOOKUP(H119,Clientes!B:D,3,) -> BGC LIQUIDEZ DTVM LTDA | O119: =_xlfn.XLOOKUP(D119,'[1]Matriz Brokers'!$C:$C,'[1]Matriz Brokers'!$C:$C,0,0,1) -> JOSÉ VERGARA
A120: =CONCATENATE($J$1,J120,$I$3,M120,$I$3,L120,$I$1,K120,$I$2) -> DESPESA DE REPRESENTAÇÃO - JANTAR - TRADER - PEDRO BOHANA (110502-4185MP) | B120: 46266 | C120: 817991 | D120: MARYLIA CARVALHO PONCE | E120: -1908.57 | F120: JANTAR | G120: 46289 | H120: 82706 | J120: JANTAR | K120: 110502-4185MP | L120: PEDRO BOHANA | M120: TRADER | N120: =VLOOKUP(H120,Clientes!B:D,3,) -> BANCO XP S/A | O120: =_xlfn.XLOOKUP(D120,'[1]Matriz Brokers'!$C:$C,'[1]Matriz Brokers'!$C:$C,0,0,1) -> MARYLIA CARVALHO PONCE
A121: =CONCATENATE($J$1,J121,$I$3,M121,$I$3,L121,$I$1,K121,$I$2) -> DESPESA DE REPRESENTAÇÃO - ALMOÇO - TRADER - GIOVANNE TELES (164040-4185AM) | B121: 46266 | C121: 817991 | D121: ANTÔNIO MARTINS NETO | E121: -1934.56 | F121: ALMOÇO | G121: 46289 | H121: =_xlfn.XLOOKUP(SET!L121,Clientes!E:E,Clientes!B:B,0,0,1) -> 14479 | J121: ALMOÇO | K121: 164040-4185AM | L121: GIOVANNE TELES | M121: =_xlfn.XLOOKUP(L121,Clientes!E:E,Clientes!F:F,0,0,1) -> TRADER | N121: =VLOOKUP(H121,Clientes!B:D,3,) -> BANCO SANTANDER (BRASIL) S/A | O121: =_xlfn.XLOOKUP(D121,'[1]Matriz Brokers'!$C:$C,'[1]Matriz Brokers'!$C:$C,0,0,1) -> ANTÔNIO MARTINS NETO
A122: =CONCATENATE($J$1,J122,$I$3,M122,$I$3,L122,$I$1,K122,$I$2) -> DESPESA DE REPRESENTAÇÃO - ALMOÇO COM POSSÍVEIS CONTRATAÇÕES - BROKER - RICARDO ANDRE VASCONCELOS RAMOS (095707-4185RR) | B122: 46266 | C122: 817991 | D122: RICARDO ANDRE VASCONCELOS RAMOS | E122: -1037.9 | F122: ALMOÇO | G122: 46289 | H122: =_xlfn.XLOOKUP(SET!L122,Clientes!E:E,Clientes!B:B,0,0,1) -> 1170 | J122: ALMOÇO COM POSSÍVEIS CONTRATAÇÕES | K122: 095707-4185RR | L122: RICARDO ANDRE VASCONCELOS RAMOS | M122: =_xlfn.XLOOKUP(L122,Clientes!E:E,Clientes!F:F,0,0,1) -> BROKER | N122: =VLOOKUP(H122,Clientes!B:D,3,) -> BGC LIQUIDEZ DTVM LTDA | O122: =_xlfn.XLOOKUP(D122,'[1]Matriz Brokers'!$C:$C,'[1]Matriz Brokers'!$C:$C,0,0,1) -> RICARDO ANDRE VASCONCELOS RAMOS
A123: =CONCATENATE($J$1,J123,$I$3,M123,$I$3,L123,$I$1,K123,$I$2) -> DESPESA DE REPRESENTAÇÃO - ALMOÇO - TRADER - LEONARDO MACHADO (175804-4185MP) | B123: 46266 | C123: 817991 | D123: MARYLIA CARVALHO PONCE | E123: -206.3 | F123: ALMOÇO | G123: 46289 | H123: 80111 | J123: ALMOÇO | K123: 175804-4185MP | L123: LEONARDO MACHADO | M123: TRADER | N123: =VLOOKUP(H123,Clientes!B:D,3,) -> IBIUNA GESTAO DE RECURSOS LTDA | O123: =_xlfn.XLOOKUP(D123,'[1]Matriz Brokers'!$C:$C,'[1]Matriz Brokers'!$C:$C,0,0,1) -> MARYLIA CARVALHO PONCE
A124: =CONCATENATE($J$1,J124,$I$3,M124,$I$3,L124,$I$1,K124,$I$2) -> DESPESA DE REPRESENTAÇÃO - ALMOÇO - TRADER - HENRIQUE KASTEN PEINADO (170323-4185AM) | B124: 46266 | C124: 817991 | D124: ANTÔNIO MARTINS NETO | E124: -1136.1 | F124: ALMOÇO | G124: 46289 | H124: =_xlfn.XLOOKUP(SET!L124,Clientes!E:E,Clientes!B:B,0,0,1) -> 80958 | J124: ALMOÇO | K124: 170323-4185AM | L124: HENRIQUE KASTEN PEINADO | M124: =_xlfn.XLOOKUP(L124,Clientes!E:E,Clientes!F:F,0,0,1) -> TRADER | N124: =VLOOKUP(H124,Clientes!B:D,3,) -> ITAU UNIBANCO ASSET - OPTIMUS | O124: =_xlfn.XLOOKUP(D124,'[1]Matriz Brokers'!$C:$C,'[1]Matriz Brokers'!$C:$C,0,0,1) -> ANTÔNIO MARTINS NETO
A125: =CONCATENATE($J$1,J125,$I$3,M125,$I$3,L125,$I$1,K125,$I$2) -> DESPESA DE REPRESENTAÇÃO - ALMOÇO - TRADER - KRISTOPHER K HOMEM M ROBINSON (165719-4185AM) | B125: 46266 | C125: 817991 | D125: ANTÔNIO MARTINS NETO | E125: -1323.23 | F125: ALMOÇO | G125: 46289 | H125: =_xlfn.XLOOKUP(SET!L125,Clientes!E:E,Clientes!B:B,0,0,1) -> 80386 | J125: ALMOÇO | K125: 165719-4185AM | L125: KRISTOPHER K HOMEM M ROBINSON | M125: =_xlfn.XLOOKUP(L125,Clientes!E:E,Clientes!F:F,0,0,1) -> TRADER | N125: =VLOOKUP(H125,Clientes!B:D,3,) -> LEGACY CAPITAL GESTORA DE RECURSOS LTDA | O125: =_xlfn.XLOOKUP(D125,'[1]Matriz Brokers'!$C:$C,'[1]Matriz Brokers'!$C:$C,0,0,1) -> ANTÔNIO MARTINS NETO
A126: =CONCATENATE($J$1,J126,$I$3,M126,$I$3,L126,$I$1,K126,$I$2) -> DESPESA DE REPRESENTAÇÃO - ALMOÇO COM CLIENTE POLIGONO - TRADER - GUILHERME RIBEIRO (141240-4185DG) | B126: 46266 | C126: 817991 | D126: DANIEL TEIXEIRA SIQUEIRA GONÇALVES | E126: -670.09 | F126: ALMOÇO | G126: 46289 | H126: 1170 | J126: ALMOÇO COM CLIENTE POLIGONO | K126: 141240-4185DG | L126: GUILHERME RIBEIRO | M126: TRADER | N126: =VLOOKUP(H126,Clientes!B:D,3,) -> BGC LIQUIDEZ DTVM LTDA | O126: =_xlfn.XLOOKUP(D126,'[1]Matriz Brokers'!$C:$C,'[1]Matriz Brokers'!$C:$C,0,0,1) -> DANIEL TEIXEIRA SIQUEIRA GONÇALVES
A127: =CONCATENATE($J$1,J127,$I$3,M127,$I$3,L127,$I$1,K127,$I$2) -> DESPESA DE REPRESENTAÇÃO - HAPPY HOUR - TRADER - FABIO LUIZ SALAS MARANHO (095759-4185AA) | B127: 46266 | C127: 817991 | D127: ANTONIO AGIZ FILHO | E127: -1132 | F127: EVENTO | G127: 46289 | H127: =_xlfn.XLOOKUP(SET!L127,Clientes!E:E,Clientes!B:B,0,0,1) -> 80650 | J127: HAPPY HOUR | K127: 095759-4185AA | L127: FABIO LUIZ SALAS MARANHO | M127: =_xlfn.XLOOKUP(L127,Clientes!E:E,Clientes!F:F,0,0,1) -> TRADER | N127: =VLOOKUP(H127,Clientes!B:D,3,) -> BANCO SOFISA S/A | O127: =_xlfn.XLOOKUP(D127,'[1]Matriz Brokers'!$C:$C,'[1]Matriz Brokers'!$C:$C,0,0,1) -> ANTONIO AGIZ FILHO
A128: =CONCATENATE($J$1,J128,$I$3,M128,$I$3,L128,$I$1,K128,$I$2) -> DESPESA DE REPRESENTAÇÃO - ALMOÇO COM RJI - TRADER - MARIANA SOARES (152822-4185RM) | B128: 46266 | C128: 817991 | D128: RODRIGO MOURA MARQUES | E128: -495.39 | F128: ALMOÇO | G128: 46289 | H128: 1170 | J128: ALMOÇO COM RJI | K128: 152822-4185RM | L128: MARIANA SOARES | M128: TRADER | N128: =VLOOKUP(H128,Clientes!B:D,3,) -> BGC LIQUIDEZ DTVM LTDA | O128: =_xlfn.XLOOKUP(D128,'[1]Matriz Brokers'!$C:$C,'[1]Matriz Brokers'!$C:$C,0,0,1) -> RODRIGO MOURA MARQUES
A129: =CONCATENATE($J$1,J129,$I$3,M129,$I$3,L129,$I$1,K129,$I$2) -> DESPESA DE REPRESENTAÇÃO - ALMOÇO - TRADER - MATHIAS CLERC (165958-4185AM) | B129: 46266 | C129: 817991 | D129: ANTÔNIO MARTINS NETO | E129: -459.91 | F129: ALMOÇO | G129: 46289 | H129: =_xlfn.XLOOKUP(SET!L129,Clientes!E:E,Clientes!B:B,0,0,1) -> 82467 | J129: ALMOÇO | K129: 165958-4185AM | L129: MATHIAS CLERC | M129: =_xlfn.XLOOKUP(L129,Clientes!E:E,Clientes!F:F,0,0,1) -> TRADER | N129: =VLOOKUP(H129,Clientes!B:D,3,) -> BRAM - BRADESCO ASSET MANAGEMENT S/A DTVM | O129: =_xlfn.XLOOKUP(D129,'[1]Matriz Brokers'!$C:$C,'[1]Matriz Brokers'!$C:$C,0,0,1) -> ANTÔNIO MARTINS NETO
A130: =CONCATENATE($J$1,J130,$I$3,M130,$I$3,L130,$I$1,K130,$I$2) -> DESPESA DE REPRESENTAÇÃO - ALMOÇO - TRADER - RICARDO LEOPOLDO (135933-4185EC) | B130: 46266 | C130: 817991 | D130: ENRICO BORTPLUZO CASSIANO | E130: -1191 | F130: ALMOÇO | G130: 46289 | H130: 82597 | J130: ALMOÇO | K130: 135933-4185EC | L130: RICARDO LEOPOLDO | M130: TRADER | N130: =VLOOKUP(H130,Clientes!B:D,3,) -> PORTO SEGURO INVESTIMENTOS LTDA | O130: =_xlfn.XLOOKUP(D130,'[1]Matriz Brokers'!$C:$C,'[1]Matriz Brokers'!$C:$C,0,0,1) -> ENRICO BORTPLUZO CASSIANO
A131: =CONCATENATE($J$1,J131,$I$3,M131,$I$3,L131,$I$1,K131,$I$2) -> DESPESA DE REPRESENTAÇÃO - 3 INGRESSOS PARA SHOW DO SEAL EM 28/11 - TRADER - ISABELA PAIVA RITZMANN (081223-4185PI) | B131: 46266 | C131: 817991 | D131: PAOLO FRANCA LIDA | E131: -5839 | F131: EVENTO | G131: 46289 | H131: =_xlfn.XLOOKUP(SET!L131,Clientes!E:E,Clientes!B:B,0,0,1) -> 79455 | J131: 3 INGRESSOS PARA SHOW DO SEAL EM 28/11 | K131: 081223-4185PI | L131: ISABELA PAIVA RITZMANN | M131: =_xlfn.XLOOKUP(L131,Clientes!E:E,Clientes!F:F,0,0,1) -> TRADER | N131: =VLOOKUP(H131,Clientes!B:D,3,) -> ITAU UNIBANCO S/A | O131: =_xlfn.XLOOKUP(D131,'[1]Matriz Brokers'!$C:$C,'[1]Matriz Brokers'!$C:$C,0,0,1) -> PAOLO FRANCA LIDA
A132: =CONCATENATE($J$1,J132,$I$3,M132,$I$3,L132,$I$1,K132,$I$2) -> DESPESA DE REPRESENTAÇÃO - - 0 - () | B132: 46266 | C132: 817991 | H132: =_xlfn.XLOOKUP(SET!L132,Clientes!E:E,Clientes!B:B,0,0,1) -> 0 | M132: =_xlfn.XLOOKUP(L132,Clientes!E:E,Clientes!F:F,0,0,1) -> 0 | N132: =VLOOKUP(H132,Clientes!B:D,3,) -> #N/A | O132: =_xlfn.XLOOKUP(D132,'[1]Matriz Brokers'!$C:$C,'[1]Matriz Brokers'!$C:$C,0,0,1) -> 0
A133: =CONCATENATE($J$1,J133,$I$3,M133,$I$3,L133,$I$1,K133,$I$2) -> DESPESA DE REPRESENTAÇÃO - - 0 - () | B133: 46266 | C133: 817991 | H133: =_xlfn.XLOOKUP(SET!L133,Clientes!E:E,Clientes!B:B,0,0,1) -> 0 | M133: =_xlfn.XLOOKUP(L133,Clientes!E:E,Clientes!F:F,0,0,1) -> 0 | N133: =VLOOKUP(H133,Clientes!B:D,3,) -> #N/A | O133: =_xlfn.XLOOKUP(D133,'[1]Matriz Brokers'!$C:$C,'[1]Matriz Brokers'!$C:$C,0,0,1) -> 0
A134: =CONCATENATE($J$1,J134,$I$3,M134,$I$3,L134,$I$1,K134,$I$2) -> DESPESA DE REPRESENTAÇÃO - - 0 - () | B134: 46266 | C134: 817991 | H134: =_xlfn.XLOOKUP(SET!L134,Clientes!E:E,Clientes!B:B,0,0,1) -> 0 | M134: =_xlfn.XLOOKUP(L134,Clientes!E:E,Clientes!F:F,0,0,1) -> 0 | N134: =VLOOKUP(H134,Clientes!B:D,3,) -> #N/A | O134: =_xlfn.XLOOKUP(D134,'[1]Matriz Brokers'!$C:$C,'[1]Matriz Brokers'!$C:$C,0,0,1) -> 0
A135: =CONCATENATE($J$1,J135,$I$3,M135,$I$3,L135,$I$1,K135,$I$2) -> DESPESA DE REPRESENTAÇÃO - - 0 - () | B135: 46266 | C135: 817991 | H135: =_xlfn.XLOOKUP(SET!L135,Clientes!E:E,Clientes!B:B,0,0,1) -> 0 | M135: =_xlfn.XLOOKUP(L135,Clientes!E:E,Clientes!F:F,0,0,1) -> 0 | N135: =VLOOKUP(H135,Clientes!B:D,3,) -> #N/A | O135: =_xlfn.XLOOKUP(D135,'[1]Matriz Brokers'!$C:$C,'[1]Matriz Brokers'!$C:$C,0,0,1) -> 0
A136: =CONCATENATE($J$1,J136,$I$3,M136,$I$3,L136,$I$1,K136,$I$2) -> DESPESA DE REPRESENTAÇÃO - - 0 - () | B136: 46266 | C136: 817991 | H136: =_xlfn.XLOOKUP(SET!L136,Clientes!E:E,Clientes!B:B,0,0,1) -> 0 | M136: =_xlfn.XLOOKUP(L136,Clientes!E:E,Clientes!F:F,0,0,1) -> 0 | N136: =VLOOKUP(H136,Clientes!B:D,3,) -> #N/A | O136: =_xlfn.XLOOKUP(D136,'[1]Matriz Brokers'!$C:$C,'[1]Matriz Brokers'!$C:$C,0,0,1) -> 0
A137: =CONCATENATE($J$1,J137,$I$3,M137,$I$3,L137,$I$1,K137,$I$2) -> DESPESA DE REPRESENTAÇÃO - - 0 - () | B137: 46266 | C137: 817991 | H137: =_xlfn.XLOOKUP(SET!L137,Clientes!E:E,Clientes!B:B,0,0,1) -> 0 | M137: =_xlfn.XLOOKUP(L137,Clientes!E:E,Clientes!F:F,0,0,1) -> 0 | N137: =VLOOKUP(H137,Clientes!B:D,3,) -> #N/A | O137: =_xlfn.XLOOKUP(D137,'[1]Matriz Brokers'!$C:$C,'[1]Matriz Brokers'!$C:$C,0,0,1) -> 0
A138: =CONCATENATE($J$1,J138,$I$3,M138,$I$3,L138,$I$1,K138,$I$2) -> DESPESA DE REPRESENTAÇÃO - - 0 - () | B138: 46266 | C138: 817991 | H138: =_xlfn.XLOOKUP(SET!L138,Clientes!E:E,Clientes!B:B,0,0,1) -> 0 | M138: =_xlfn.XLOOKUP(L138,Clientes!E:E,Clientes!F:F,0,0,1) -> 0 | N138: =VLOOKUP(H138,Clientes!B:D,3,) -> #N/A | O138: =_xlfn.XLOOKUP(D138,'[1]Matriz Brokers'!$C:$C,'[1]Matriz Brokers'!$C:$C,0,0,1) -> 0
A139: =CONCATENATE($J$1,J139,$I$3,M139,$I$3,L139,$I$1,K139,$I$2) -> DESPESA DE REPRESENTAÇÃO - - 0 - () | B139: 46266 | C139: 817991 | H139: =_xlfn.XLOOKUP(SET!L139,Clientes!E:E,Clientes!B:B,0,0,1) -> 0 | M139: =_xlfn.XLOOKUP(L139,Clientes!E:E,Clientes!F:F,0,0,1) -> 0 | N139: =VLOOKUP(H139,Clientes!B:D,3,) -> #N/A | O139: =_xlfn.XLOOKUP(D139,'[1]Matriz Brokers'!$C:$C,'[1]Matriz Brokers'!$C:$C,0,0,1) -> 0
A140: =CONCATENATE($J$1,J140,$I$3,M140,$I$3,L140,$I$1,K140,$I$2) -> DESPESA DE REPRESENTAÇÃO - - 0 - () | B140: 46266 | C140: 817991 | H140: =_xlfn.XLOOKUP(SET!L140,Clientes!E:E,Clientes!B:B,0,0,1) -> 0 | M140: =_xlfn.XLOOKUP(L140,Clientes!E:E,Clientes!F:F,0,0,1) -> 0 | N140: =VLOOKUP(H140,Clientes!B:D,3,) -> #N/A | O140: =_xlfn.XLOOKUP(D140,'[1]Matriz Brokers'!$C:$C,'[1]Matriz Brokers'!$C:$C,0,0,1) -> 0
A141: =CONCATENATE($J$1,J141,$I$3,M141,$I$3,L141,$I$1,K141,$I$2) -> DESPESA DE REPRESENTAÇÃO - - 0 - () | B141: 46266 | C141: 817991 | H141: =_xlfn.XLOOKUP(SET!L141,Clientes!E:E,Clientes!B:B,0,0,1) -> 0 | M141: =_xlfn.XLOOKUP(L141,Clientes!E:E,Clientes!F:F,0,0,1) -> 0 | N141: =VLOOKUP(H141,Clientes!B:D,3,) -> #N/A | O141: =_xlfn.XLOOKUP(D141,'[1]Matriz Brokers'!$C:$C,'[1]Matriz Brokers'!$C:$C,0,0,1) -> 0
A142: =CONCATENATE($J$1,J142,$I$3,M142,$I$3,L142,$I$1,K142,$I$2) -> DESPESA DE REPRESENTAÇÃO - - 0 - () | B142: 46266 | C142: 817991 | H142: =_xlfn.XLOOKUP(SET!L142,Clientes!E:E,Clientes!B:B,0,0,1) -> 0 | M142: =_xlfn.XLOOKUP(L142,Clientes!E:E,Clientes!F:F,0,0,1) -> 0 | N142: =VLOOKUP(H142,Clientes!B:D,3,) -> #N/A | O142: =_xlfn.XLOOKUP(D142,'[1]Matriz Brokers'!$C:$C,'[1]Matriz Brokers'!$C:$C,0,0,1) -> 0
A143: =CONCATENATE($J$1,J143,$I$3,M143,$I$3,L143,$I$1,K143,$I$2) -> DESPESA DE REPRESENTAÇÃO - - 0 - () | B143: 46266 | C143: 817991 | H143: =_xlfn.XLOOKUP(SET!L143,Clientes!E:E,Clientes!B:B,0,0,1) -> 0 | M143: =_xlfn.XLOOKUP(L143,Clientes!E:E,Clientes!F:F,0,0,1) -> 0 | N143: =VLOOKUP(H143,Clientes!B:D,3,) -> #N/A | O143: =_xlfn.XLOOKUP(D143,'[1]Matriz Brokers'!$C:$C,'[1]Matriz Brokers'!$C:$C,0,0,1) -> 0
... A204: =CONCATENATE($J$1,J204,$I$3,M204,$I$3,L204,$I$1,K204,$I$2) -> DESPESA DE REPRESENTAÇÃO - - 0 - () | B204: 46266 | C204: 817991 | H204: =_xlfn.XLOOKUP(SET!L204,Clientes!E:E,Clientes!B:B,0,0,1) -> 0 | M204: =_xlfn.XLOOKUP(L204,Clientes!E:E,Clientes!F:F,0,0,1) -> 0 | N204: =VLOOKUP(H204,Clientes!B:D,3,) -> #N/A | O204: =_xlfn.XLOOKUP(D204,'[1]Matriz Brokers'!$C:$C,'[1]Matriz Brokers'!$C:$C,0,0,1) -> 0
O205: =_xlfn.XLOOKUP(D205,'[1]Matriz Brokers'!$C:$C,'[1]Matriz Brokers'!$C:$C,0,0,1) -> 0
O206: =_xlfn.XLOOKUP(D206,'[1]Matriz Brokers'!$C:$C,'[1]Matriz Brokers'!$C:$C,0,0,1) -> 0
O207: =_xlfn.XLOOKUP(D207,'[1]Matriz Brokers'!$C:$C,'[1]Matriz Brokers'!$C:$C,0,0,1) -> 0

Sheet OUT
A1: HISTORICO | B1: DATA COMPETENCIA | C1: CONTA CONTABIL | D1: BROKER | E1: VALOR | F1: FORNECEDOR | G1: DATA LANCAMENTO | H1: CLIENTE | I1: ( | J1: DESPESA DE REPRESENTAÇÃO - | K1: CODIGO | L1: CONVIDADO | M1: CARGO DO CONVIDADO | N1: RAZÃO SOCIAL
A2: =CONCATENATE($J$1,J2,$I$3,M2,$I$3,L2,$I$1,K2,$I$2) -> DESPESA DE REPRESENTAÇÃO - -- () | B2: 46296 | C2: 817991 | I2: ) | N2: =VLOOKUP(H2,Clientes!B:D,3,) -> #N/A
A3: =CONCATENATE($J$1,J3,$I$3,M3,$I$3,L3,$I$1,K3,$I$2) -> DESPESA DE REPRESENTAÇÃO - -- () | B3: 46296 | C3: 817991 | I3: - | N3: =VLOOKUP(H3,Clientes!B:D,3,) -> #N/A
A4: =CONCATENATE($J$1,J4,$I$3,M4,$I$3,L4,$I$1,K4,$I$2) -> DESPESA DE REPRESENTAÇÃO - -- () | B4: 46296 | C4: 817991 | N4: =VLOOKUP(H4,Clientes!B:D,3,) -> #N/A
A5: =CONCATENATE($J$1,J5,$I$3,M5,$I$3,L5,$I$1,K5,$I$2) -> DESPESA DE REPRESENTAÇÃO - -- () | B5: 46296 | C5: 817991 | N5: =VLOOKUP(H5,Clientes!B:D,3,) -> #N/A
A6: =CONCATENATE($J$1,J6,$I$3,M6,$I$3,L6,$I$1,K6,$I$2) -> DESPESA DE REPRESENTAÇÃO - -- () | B6: 46296 | C6: 817991 | N6: =VLOOKUP(H6,Clientes!B:D,3,) -> #N/A
A7: =CONCATENATE($J$1,J7,$I$3,M7,$I$3,L7,$I$1,K7,$I$2) -> DESPESA DE REPRESENTAÇÃO - -- () | B7: 46296 | C7: 817991 | N7: =VLOOKUP(H7,Clientes!B:D,3,) -> #N/A
A8: =CONCATENATE($J$1,J8,$I$3,M8,$I$3,L8,$I$1,K8,$I$2) -> DESPESA DE REPRESENTAÇÃO - -- () | B8: 46296 | C8: 817991 | N8: =VLOOKUP(H8,Clientes!B:D,3,) -> #N/A
A9: =CONCATENATE($J$1,J9,$I$3,M9,$I$3,L9,$I$1,K9,$I$2) -> DESPESA DE REPRESENTAÇÃO - -- () | B9: 46296 | C9: 817991 | N9: =VLOOKUP(H9,Clientes!B:D,3,) -> #N/A
A10: =CONCATENATE($J$1,J10,$I$3,M10,$I$3,L10,$I$1,K10,$I$2) -> DESPESA DE REPRESENTAÇÃO - -- () | B10: 46296 | C10: 817991 | N10: =VLOOKUP(H10,Clientes!B:D,3,) -> #N/A
A11: =CONCATENATE($J$1,J11,$I$3,M11,$I$3,L11,$I$1,K11,$I$2) -> DESPESA DE REPRESENTAÇÃO - -- () | B11: 46296 | C11: 817991 | N11: =VLOOKUP(H11,Clientes!B:D,3,) -> #N/A
A12: =CONCATENATE($J$1,J12,$I$3,M12,$I$3,L12,$I$1,K12,$I$2) -> DESPESA DE REPRESENTAÇÃO - -- () | B12: 46296 | C12: 817991 | N12: =VLOOKUP(H12,Clientes!B:D,3,) -> #N/A
A13: =CONCATENATE($J$1,J13,$I$3,M13,$I$3,L13,$I$1,K13,$I$2) -> DESPESA DE REPRESENTAÇÃO - -- () | B13: 46296 | C13: 817991 | N13: =VLOOKUP(H13,Clientes!B:D,3,) -> #N/A
A14: =CONCATENATE($J$1,J14,$I$3,M14,$I$3,L14,$I$1,K14,$I$2) -> DESPESA DE REPRESENTAÇÃO - -- () | B14: 46296 | C14: 817991 | N14: =VLOOKUP(H14,Clientes!B:D,3,) -> #N/A
A15: =CONCATENATE($J$1,J15,$I$3,M15,$I$3,L15,$I$1,K15,$I$2) -> DESPESA DE REPRESENTAÇÃO - -- () | B15: 46296 | C15: 817991 | N15: =VLOOKUP(H15,Clientes!B:D,3,) -> #N/A
... A200: =CONCATENATE($J$1,J200,$I$3,M200,$I$3,L200,$I$1,K200,$I$2) -> DESPESA DE REPRESENTAÇÃO - -- () | B200: 46296 | C200: 817991 | N200: =VLOOKUP(H200,Clientes!B:D,3,) -> #N/A

Sheet Clientes
A1: Segmento | B1: Codigo | C1: Nome | D1: Grupo (Nome) | E1: Emissor/mandatario/trader padrao | F1: Cargo | G1: Broker
A2: XBMF | B2: 80958 | C2: ITAU UNIBANCO ASSET MANAGEMENT LTDA | D2: ITAU UNIBANCO ASSET - OPTIMUS | E2: 525 | F2: TRADER | G2: ALEXANDRE BRENO STEVENS | H2: FX FUTURES
A3: XBMF | B3: 83024 | C3: ITAU UNIBANCO ASSET MANAGEMENT LTDA | D3: ITAU UNIBANCO ASSET MANAGEMENT LTDA | E3: 525 | F3: TRADER | G3: ALEXANDRE DA COSTA SOARES | H3: BOVESPA EQUITIES
A4: XBMF | B4: 16705 | C4: BANCO BRADESCO S/A | D4: BANCO BRADESCO S/A | E4: 616 | F4: TRADER | G4: ALEXANDRE DE CARVALHO GALHARDO | H4: NDF OFFSHORE
A5: XBMF | B5: 81693 | C5: CREDIT SUISSE HEDGING-GRIFFO WEALTH MANAGEMENT S/A | D5: CREDIT SUISSE HEDGING-GRIFFO WEALTH MANAGEMENT S/A | E5: 628 | F5: TRADER | G5: ALI MOHAMAD KANSAOU | H5: FX SPOT
A6: XBSP | B6: 80996 | C6: OPPORTUNITY HDF ADMINISTRADORA DE RECURSOS LTDA | D6: OPPORTUNITY GESTAO DE INVESTIMENTOS E RECURSOS LTDA | E6: 633 | F6: TRADER | G6: ALINE FAUSTINI | H6: NDF OFFSHORE
A7: XBMF | B7: 81380 | C7: BANCO TOPAZIO S.A. | D7: BANCO TOPAZIO S.A. | E7: 635 | F7: TRADER | G7: ALVARO LUIZ RICOTTA SOARES | H7: FX FUTURES
A8: XBMF | B8: 80343 | C8: BANCO BS2 S.A. | D8: BANCO BS2 S/A | E8: 643 | F8: TRADER | G8: ANDRE FERREIRA DOS SANTOS | H8: DI FUTURES
A9: XBMF | B9: 16705 | C9: BANCO BRADESCO S/A | D9: BANCO BRADESCO S/A | E9: 650 | F9: TRADER | G9: ANDRE HALL ACCIOLY | H9: FRONT OFFICE ADMIN & SUPPORT
A10: XBMF | B10: 81693 | C10: CREDIT SUISSE HEDGING-GRIFFO WEALTH MANAGEMENT S/A | D10: CREDIT SUISSE HEDGING-GRIFFO WEALTH MANAGEMENT S/A | E10: 655 | F10: TRADER | G10: ANDREA LICASSIA ALMEIDA SANTOS | H10: FX SPOT
A11: XBMF | B11: 83074 | C11: UBS BRASIL ADMINISTRADORA DE VALORES MOBILIARIOS LTDA | D11: UBS BRASIL ADMINISTRADORA DE VALORES MOBILIARIOS LTDA | E11: 655 | F11: TRADER | G11: ANNA CAROLINA ABRUNHOSA TAPIAS | H11: FINANCIAL SERVICES BROKING MANAGEMENT - AMERICAS
A12: XBMF | B12: 18857 | C12: BANCO DO BRASIL S/A | D12: BANCO DO BRASIL S/A | E12: 660 | F12: TRADER | G12: ANTONIO AGIZ FILHO | H12: FX SPOT
A13: XBMF | B13: 80343 | C13: BANCO BS2 S.A. | D13: BANCO BS2 S/A | E13: 672 | F13: TRADER | G13: ANTONIO AUGUSTO DAS CHAGAS CARVALHO | H13: FX SPOT
... A70: XBMF | B70: 80386 | C70: LEGACY CAPITAL GESTORA DE RECURSOS LTDA | D70: LEGACY CAPITAL GESTORA DE RECURSOS LTDA | E70: 895 | F70: TRADER | G70: WESLEY MARQUES DA SILVA | H70: INFLATION BONDS
A71: XBSP | B71: 123956 | C71: BNP PARIBAS EQD BRAZIL FUND CLASSE DE INVESTIMENTO MULTI CP | D71: BANCO BNP PARIBAS BRASIL S/A | E71: 950 | F71: TRADER | G71: CLAUDIA TAVARES FERNANDES
A72: XBMF | B72: 81702 | C72: BNP PARIBAS FINANCIAL MARKETS | D72: BANCO BNP PARIBAS BRASIL S/A | E72: 950 | F72: TRADER
A73: XBSP | B73: 123839 | C73: BNP PARIBAS FINANCIAL MARKETS | D73: BANCO BNP PARIBAS BRASIL S/A | E73: 950 | F73: TRADER
A74: XBSP | B74: 123839 | C74: BNP PARIBAS FINANCIAL MARKETS | D74: BANCO BNP PARIBAS BRASIL S/A | E74: 951 | F74: TRADER
A75: XBSP | B75: 82869 | C75: CITIGROUP GLOBAL MARKETS LIMITED | D75: BANCO CITIBANK S/A | E75: 982 | F75: TRADER
A76: XBSP | B76: 82869 | C76: CITIGROUP GLOBAL MARKETS LIMITED | D76: BANCO CITIBANK S/A | E76: 983 | F76: TRADER
A77: XBMF | B77: 80386 | C77: LEGACY CAPITAL GESTORA DE RECURSOS LTDA | D77: LEGACY CAPITAL GESTORA DE RECURSOS LTDA | E77: 1001 | F77: TRADER
A78: XBMF | B78: 144548 | C78: ABSOLUTE GESTAO DE INVESTIMENTOS LTDA | D78: ABSOLUTE GESTAO DE INVESTIMENTOS LTDA | E78: 1002 | F78: TRADER
A79: XBSP | B79: 144548 | C79: ABSOLUTE GESTAO DE INVESTIMENTOS LTDA | D79: ABSOLUTE GESTAO DE INVESTIMENTOS LTDA | E79: 1002 | F79: TRADER
A80: XBMF | B80: 18857 | C80: BANCO DO BRASIL S/A | D80: BANCO DO BRASIL S/A | E80: 1015 | F80: TRADER
A81: XBMF | B81: 82968 | C81: BTG PACTUAL ASSET MANAGEMENT SA DTVM | D81: CLAVE GESTORA DE RECURSOS LTDA | E81: 1018 | F81: TRADER
A82: XBSP | B82: 82968 | C82: BTG PACTUAL ASSET MANAGEMENT SA DTVM | D82: CLAVE GESTORA DE RECURSOS LTDA | E82: 1018 | F82: TRADER
A83: XBMF | B83: 82639 | C83: SAFRA ASSET CORRETORA DE TITULOS E VALORES MOBILIARIOS S.A. | D83: SAFRA ASSET CORRETORA DE TITULOS E VALORES MOBILIARIOS S.A. | E83: 1025 | F83: TRADER
